Workbook
Name _Toc226895311_10: "$#ССЫЛ!.$#ССЫЛ!$#ССЫЛ!"
Name Excel_BuiltIn_Print_Titles_29: #REF!
Name Excel_BuiltIn_Print_Titles_29: #REF!
Name Excel_BuiltIn_Print_Titles_29: #REF!
Name Excel_BuiltIn_Print_Titles_29: #REF!
Name Excel_BuiltIn_Print_Titles_29: #REF!
Name Excel_BuiltIn_Print_Titles_29: #REF!
Name Excel_BuiltIn_Print_Titles_29: #REF!
Name k: #N/A
Name m: #N/A
Name n: #N/A
Name а: #REF!
Name а: #REF!
Name а: #REF!
Name а: #REF!
Name а: #REF!
Name а: #REF!
Name а: #REF!
Name аа: #REF!
Name аа: #REF!
Name аа: #REF!
Name аа: #REF!
Name аа: #REF!
Name аа: #REF!
Name аа: #REF!
Name астана: #REF!
Name астана: #REF!
Name астана: #REF!
Name астана: #REF!
Name астана: #REF!
Name астана: #REF!
Name астана: #REF!
Name ВидПредмета: #NAME?
Name вода: #REF!
Name вода: #REF!
Name вода: #REF!
Name вода: #REF!
Name вода: #REF!
Name вода: #REF!
Name вода: #REF!
Name г: #REF!
Name г: #REF!
Name г: #REF!
Name г: #REF!
Name г: #REF!
Name г: #REF!
Name г: #REF!
Name Год: #NAME?
Name Интеллектуальная_школа_Первого_Президента_физико_математического_направления_в_городе_Астана: #REF!
Name Интеллектуальная_школа_Первого_Президента_физико_математического_направления_в_городе_Астана: #REF!
Name Интеллектуальная_школа_Первого_Президента_физико_математического_направления_в_городе_Астана: #REF!
Name Интеллектуальная_школа_Первого_Президента_физико_математического_направления_в_городе_Астана: #REF!
Name Интеллектуальная_школа_Первого_Президента_физико_математического_направления_в_городе_Астана: #REF!
Name Интеллектуальная_школа_Первого_Президента_физико_математического_направления_в_городе_Астана: #REF!
Name Интеллектуальная_школа_Первого_Президента_физико_математического_направления_в_городе_Астана: #REF!
Name кк: #REF!
Name кк: #REF!
Name кк: #REF!
Name кк: #REF!
Name кк: #REF!

Sheet сводная
G2: Приложение 51
G3: к Правилам составления и
G4: представления бюджетной заявки
B6: Сводный расчет расходов администратора
B7: бюджетных программ по бюджетным программам (подпрограммам)
I8: Коды
B9: Год | I9: 2026-2028
B10: Вид данных(прогноз, план,отчет) | I10: ПЛАН
B11: Функциональная группа | D11: Образование | I11: 4
B12: Админинистратор программ | D12: Министерство просвещения РК | I12: 224
B13: Наименование учреждения
B14: Программа | D14: Обеспечение доступности качественного школьного образования | I14: 004
B15: Подпрограмма | D15: Обучение и воспитание детей в республиканских организациях образования | I15: 100
B17: Наименование | D17: Отчет за 2024 год | F17: Утвер. план 2025г | G17: План
D18: Кассовые расходы | E18: Фактические расходы | G18: 2026г. | H18: 2027г. | I18: 2028г.
B19: 1 | D19: 2 | E19: 3 | F19: 4 | G19: 5 | H19: 6 | I19: 7
B20: 159 | C20: Всего затрат( тенге) | D20: =D21 -> 1339844102 | E20: =E21 -> 1339844102 | F20: =F21 -> 1337971668 | G20: ='Свод '!C26 -> 2.6921171e+09 | H20: ='Свод '!D26 -> 2.689948e+09 | I20: ='Свод '!E26 -> 2.6911e+09
B21: 159 | C21: Прочие услуги и работы | D21: 1339844102 | E21: 1339844102 | F21: 1337971668 | G21: =G20 -> 2.6921171e+09 | H21: =H20 -> 2.689948e+09 | I21: =I20 -> 2.6911e+09
B24: Руководитель аппарата/руководитель
B25: государственного учреждения | H25: _________________
B27: Руководитель бюджетной программы | H27: _________________
B29: Главный бухгалтер (начальник ФЭО) | H29: _________________
B31: Председатель комитета
B32: среднего образования | H32: _________________

Sheet Свод 
B2: Сводный расчет расходов на 2026-2028 годы
B5: По бюджетной программе 004 «Обеспечение доступности качественного школьного образования»
B6: по 100 подпрограмме «Обучение и воспитание детей в республиканских организациях образования»
B7: Контингент учащихся 1186
A9: № | B9: Наименование расходов | C9: 2026г | D9: 2027г | E9: 2028г
A10: 1 | B10: Оплата труда | C10: =('СВОД ФЗП'!F14) -> 1.5956226e+09 | D10: =('СВОД ФЗП'!F22) -> 1.7640392e+09 | E10: =('СВОД ФЗП'!F30) -> 1.7576817e+09
A11: =A10+1 -> 2 | B11: Компенсационные выплаты | C11: =('СВОД ФЗП'!G14) -> 1.8200077e+08 | D11: =('СВОД ФЗП'!G22) -> 1.3984083e+08 | E11: =('СВОД ФЗП'!G30) -> 1.3913335e+08
A12: =A11+1 -> 3 | B12: Обязательные пенсионные взносы 3,5% | C12: ='СВОД ФЗП'!H14 -> 66216817 | D12: ='СВОД ФЗП'!H22 -> 85732203 | E12: ='СВОД ФЗП'!H30 -> 94818193
A13: =A12+1 -> 4 | B13: Социальный налог 6% | C13: =('СВОД ФЗП'!I14) -> 1.3607012e+08 | D13: =('СВОД ФЗП'!I22) -> 98935322 | E13: =('СВОД ФЗП'!I30) -> 98567797
A14: =A13+1 -> 5 | B14: Социальные отчисления 5% | C14: =('СВОД ФЗП'!J14) -> 79993050 | D14: =('СВОД ФЗП'!J22) -> 85674603 | E14: =('СВОД ФЗП'!J30) -> 85356677
A15: =A14+1 -> 6 | B15: Обязательное социальное медицинское страхование 3% | C15: =('СВОД ФЗП'!K14) -> 53328700 | D15: =('СВОД ФЗП'!K22) -> 52921177 | E15: =('СВОД ФЗП'!K30) -> 52730451
A16: =A15+1 -> 7 | B16: Приобретение продуктов питания (питьевая вода) | C16: =('Сводная общая 2026г.'!G18) -> 2510052.9 | D16: ='Сводная общая 2027г.'!G18 -> 6400634.9 | E16: ='Сводная общая 2028г.'!G18 -> 6400634.9
A17: =A16+1 -> 8 | B17: Приобретение медикаментов и прочих средств медицинского назначения | C17: ='Сводная общая 2026г.'!H38 -> 565550 | D17: ='Сводная общая 2027г.'!H38 -> 262415 | E17: ='Сводная общая 2028г.'!H38 -> 262415
A18: =A17+1 -> 9 | B18: Приобретение горюче-смазочных материалов | C18: ='Сводная общая 2026г.'!H79 -> 531700 | D18: ='Сводная общая 2027г.'!H93 -> 702000 | E18: ='Сводная общая 2028г.'!H93 -> 702000
A19: =A18+1 -> 10 | B19: Приобретение прочих запасов | C19: =('Сводная общая 2026г.'!H84) -> 49098621 | D19: ='Сводная общая 2027г.'!H98 -> 14373593 | E19: ='Сводная общая 2028г.'!H98 -> 14373593
A20: =A19+1 -> 11 | B20: Коммунальные услуги | C20: =('Сводная общая 2026г.'!H489) -> 61221609 | D20: ='Сводная общая 2027г.'!H487 -> 41917669 | E20: ='Сводная общая 2028г.'!H487 -> 41917669
A21: =A20+1 -> 12 | B21: Услуги связи и интернет | C21: =('Сводная общая 2026г.'!H505) -> 11100000 | D21: ='Сводная общая 2027г.'!H503 -> 1781232 | E21: ='Сводная общая 2028г.'!H503 -> 1781232
A22: =A21+1 -> 13 | B22: Прочие услуги и работы | C22: =('Сводная общая 2026г.'!H509) -> 85576966 | D22: ='Сводная общая 2027г.'!H507 -> 49238591 | E22: ='Сводная общая 2028г.'!H507 -> 49238590
A23: =A22+1 -> 14 | B23: Командировки и служебные разъезды в пределах страны | C23: =('Сводная общая 2026г.'!H531) -> 5256583 | D23: ='Сводная общая 2027г.'!H528 -> 944172 | E23: ='Сводная общая 2028г.'!H528 -> 944172
A24: =A23+1 -> 15 | B24: Организация горячим пятиразовым питанием | C24: =('Сводная общая 2026г.'!G536) -> 362880000 | D24: ='Сводная общая 2027г.'!G533 -> 347040000 | E24: ='Сводная общая 2028г.'!G533 -> 347040000
A25: =A24+1 -> 16 | B25: Прочие текущие затраты | C25: =('Сводная общая 2026г.'!H561) -> 144022.5 | D25: ='Сводная общая 2027г.'!H559 -> 144355.5 | E25: ='Сводная общая 2028г.'!H559 -> 151581.6
B26: Итого | C26: =SUM(C10:C25) -> 2.6921171e+09 | D26: =SUM(D10:D25) -> 2.689948e+09 | E26: =SUM(E10:E25) -> 2.6911e+09
B28: Руководитель аппарата/руководитель
B29: государственного учреждения | E29: _________________
B31: Руководитель бюджетной программы | E31: _________________
B33: Главный бухгалтер (начальник ФЭО) | E33: _________________
B35: Председатель комитета
B36: среднего образования | E36: _________________
A38: Директор ФНАО «РФМШ» Алматы | E38: Меирбек М.Е.
A40: Экономист | E40: Куюкова Г.Е.

Sheet СВОД ФЗП
A8: Филиал НАО "Республиканская физико-математическая школа" в г.Алматы
A9: Свод по тарификационной ведомости и штатному расписанию за счет средств республиканского бюджета на 2026 год
A11: № п/п | B11: Наименование | C11: Фактическая численность един. | D11: Кол-во часов | E11: Заработная плата за месяц | F11: Годовой ФЗП за 2026 год | G11: Лечебно оздоровительные пособия | H11: ОПВ 3,5% | I11: Социальный налог 6% | J11: Социальные отчисления 5% | K11: Обязательное социальное медицинское схрахование 3% | L11: Годовой ФОТ за 2026 года с налогами (соц.налог,соц отч, мед страх, пен.взн)
A12: 1 | B12: Штатное расписание | C12: ='ШР РБ Алматы'!D173 -> 146.75 | E12: ='ШР РБ Алматы'!T173 -> 62185392 | F12: =E12*12 -> 7.4622471e+08 | G12: ='ШР РБ Алматы'!Z173 -> 1.1020807e+08 | H12: ='ШР РБ Алматы'!AB173 -> 33975147 | I12: ='ШР РБ Алматы'!AC173 -> 89432991 | J12: ='ШР РБ Алматы'!AD173 -> 38539475 | K12: ='ШР РБ Алматы'!AE173 -> 25692983 | L12: =F12+G12+H12+I12+J12+K12 -> 1.0440734e+09
A13: =A12+1 -> 2 | B13: Тарификация | C13: ='Тариф РБ Алматы'!A146 -> 123 | D13: ='Тариф РБ Алматы'!X161 -> 3031 | E13: ='Тариф РБ Алматы'!BA161 -> 70783155 | F13: =E13*12 -> 8.4939785e+08 | G13: ='Тариф РБ Алматы'!BG161 -> 71792703 | H13: ='Тариф РБ Алматы'!BI161 -> 32241670 | I13: ='Тариф РБ Алматы'!BJ161 -> 46637130 | J13: ='Тариф РБ Алматы'!BK161 -> 41453575 | K13: ='Тариф РБ Алматы'!BL161 -> 27635717 | L13: =F13+G13+H13+I13+J13+K13 -> 1.0691586e+09
B14: ИТОГО | C14: =C12+C13 -> 269.75 | D14: =D12+D13 -> 3031 | E14: =E12+E13 -> 1.3296855e+08 | F14: =F12+F13 -> 1.5956226e+09 | G14: =G12+G13 -> 1.8200077e+08 | H14: =H12+H13 -> 66216817 | I14: =I12+I13 -> 1.3607012e+08 | J14: =J12+J13 -> 79993050 | ... L14: =L12+L13 -> 2.113232e+09
A16: Филиал НАО "Республиканская физико-математическая школа" в г.Алматы
A17: Свод по тарификационной ведомости и штатному расписанию за счет средств республиканского бюджета на 2027 год
A19: № п/п | B19: Наименование | C19: Фактическая численность един. | D19: Кол-во часов | E19: Заработная плата за месяц | F19: Годовой ФЗП за 2027 год | G19: Лечебно оздоровительные пособия | H19: ОПВ 3,5% | I19: Социальный налог 6% | J19: Социальные отчисления 5% | K19: Обязательное социальное медицинское схрахование 3% | L19: Годовой ФОТ за 2027 года с налогами (соц.налог,соц отч, мед страх, пен.взн)
A20: 1 | B20: Штатное расписание | C20: 149 | E20: ='ШР 2027'!T233 -> 60679042 | F20: =E20*12 -> 7.281485e+08 | G20: ='ШР 2027'!Z233 -> 56878158 | H20: ='ШР 2027'!AE233 -> 35431380 | I20: ='ШР 2027'!AB233 -> 40796198 | J20: ='ШР 2027'!AC233 -> 35326200 | K20: ='ШР 2027'!AD233 -> 21844455 | L20: =F20+G20+I20+J20+K20+H20 -> 9.1842489e+08
A21: =A20+1 -> 2 | B21: Тарификация | C21: ='Тариф 2027'!A199 -> 149 | D21: ='Тариф 2027'!X201 -> 3843 | E21: ='Тариф 2027'!BA201 -> 86324227 | F21: =E21*12 -> 1.0358907e+09 | G21: ='Тариф 2027'!BG201 -> 82962673 | H21: ='Тариф 2027'!BL201 -> 50300822 | I21: ='Тариф 2027'!BK201 -> 58139124 | J21: ='Тариф 2027'!BI201 -> 50348403 | K21: ='Тариф 2027'!BJ201 -> 31076722 | L21: =F21+G21+I21+J21+K21+H21 -> 1.3087185e+09
B22: ИТОГО | C22: =C20+C21 -> 298 | D22: =D20+D21 -> 3843 | E22: =E20+E21 -> 1.4700327e+08 | F22: =F20+F21 -> 1.7640392e+09 | G22: =G20+G21 -> 1.3984083e+08 | H22: =H20+H21 -> 85732203 | I22: =I20+I21 -> 98935322 | J22: =J20+J21 -> 85674603 | ... L22: =L20+L21 -> 2.2271434e+09
A24: Филиал НАО "Республиканская физико-математическая школа" в г.Алматы
A25: Свод по тарификационной ведомости и штатному расписанию за счет средств республиканского бюджета на 2028 год
A27: № п/п | B27: Наименование | C27: Фактическая численность един. | D27: Кол-во часов | E27: Заработная плата за месяц | F27: Годовой ФЗП за 2028 год | G27: Лечебно оздоровительные пособия | H27: ОПВ 3,5% | I27: Социальный налог 6% | J27: Социальные отчисления 5% | K27: Обязательное социальное медицинское схрахование 3% | L27: Годовой ФОТ за 2028 года с налогами (соц.налог,соц отч, мед страх, пен.взн)
A28: 1 | B28: Штатное расписание | C28: ='ШР 2028'!D233 -> 149 | E28: ='ШР 2028'!T233 -> 60695202 | F28: =E28*12 -> 7.2834242e+08 | G28: ='ШР 2028'!Z233 -> 56878158 | H28: ='ШР 2028'!AE233 -> 39260764 | I28: ='ШР 2028'!AB233 -> 40806243 | J28: ='ШР 2028'!AC233 -> 35334926 | K28: ='ШР 2028'!AD233 -> 21850273 | L28: =F28+G28+I28+J28+K28+H28 -> 9.2247278e+08
A29: =A28+1 -> 2 | B29: Тарификация | C29: ='Тариф 2028'!A199 -> 149 | D29: ='Тариф 2028'!X201 -> 3815 | E29: ='Тариф 2028'!BA201 -> 85778272 | F29: =E29*12 -> 1.0293393e+09 | G29: ='Тариф 2028'!BG201 -> 82255191 | H29: ='Тариф 2028'!BL201 -> 55557429 | I29: ='Тариф 2028'!BK201 -> 57761554 | J29: ='Тариф 2028'!BI201 -> 50021750 | K29: ='Тариф 2028'!BJ201 -> 30880178 | L29: =F29+G29+I29+J29+K29+H29 -> 1.3058154e+09
B30: ИТОГО | C30: =C28+C29 -> 298 | D30: =D28+D29 -> 3815 | E30: =E28+E29 -> 1.4647347e+08 | F30: =F28+F29 -> 1.7576817e+09 | G30: =G28+G29 -> 1.3913335e+08 | H30: =H28+H29 -> 94818193 | I30: =I28+I29 -> 98567797 | J30: =J28+J29 -> 85356677 | ... L30: =L28+L29 -> 2.2282882e+09
B33: Экономист филиала НАО "РФМШ" в г.Алматы | K33: Куюкова Г.Е.

Sheet Сводная общая 2026г.
C3: Сводный расчет расходов на 2026 год
C4: ФНАО «Республиканская физико-математическая школа» в г.Алматы
C5: по бюджетной программе 004 «Обеспечение доступности качественного школьного образования»
C6: по 100 подпрограмме «Обучение и воспитание детей в республиканских организациях образования»
C8: 1. Фонд Оплаты Труда | H8: =H10+H11+H12+H14+H15+H16+H13 -> 2.113232e+09
B9: № п.п | C9: Наименование расходов | H9: Сумма затрат в тенге в рамках лимита
B10: 1 | C10: Штатное расписание | H10: ='СВОД ФЗП'!F12 -> 7.4622471e+08
B11: =B10+1 -> 2 | C11: Оплата труда по тарификации учителей | H11: ='СВОД ФЗП'!F13 -> 8.4939785e+08
B12: =B11+1 -> 3 | C12: Компенсационные выплаты | G12: в размере ДО | H12: ='СВОД ФЗП'!G14 -> 1.8200077e+08
B13: =B12+1 -> 4 | C13: Обязательные пенсионные взносы за счет работодателя | G13: 0.035 | H13: ='СВОД ФЗП'!H14 -> 66216817
B14: =B13+1 -> 5 | C14: Социальный налог | G14: 0.06 | H14: ='СВОД ФЗП'!I14 -> 1.3607012e+08
B15: =B14+1 -> 6 | C15: Социальные отчисления | G15: 0.05 | H15: ='СВОД ФЗП'!J14 -> 79993050
B16: =B15+1 -> 7 | C16: Обязательное социальное медицинское страхование | G16: 0.03 | H16: ='СВОД ФЗП'!K14 -> 53328700
C18: 2. Приобретение питьевой воды для учащихся | G18: =G20 -> 2510052.9
B19: № п.п | C19: Наименование расходов | D19: Дни функционирования учреждения (дни) | E19: Количество бутылей на 2026 год | F19: Стоимость за ед. в тенге | G19: Сумма затрат в тенге
B20: 1 | C20: Вода питьевая бутилированная 18,9 л на 1186 детей | D20: =D23 -> 80 | E20: =G23 -> 2510.0529 | F20: 1000 | G20: =E20*F20 -> 2510052.9
B21: Расшифровка на приобретение питьевой воды для школы
B22: № | C22: Период | D22: Кол-во дней | E22: Цена | F22: Норматив на 1-го на день * (л) | G22: Количество бутылей, в 1 бутыле 18,9 (л) | H22: Сумма (тенге)
C23: Всего: | D23: =SUM(D24:D35) -> 80 | G23: =SUM(G24:G35) -> 2510.0529 | H23: =SUM(H24:H35) -> 2510052.9
B24: 1 | C24: Январь | D24: 10 | E24: 1000 | F24: 0.5 | G24: =1186*F24*D24/18.9 -> 313.75661 | H24: =G24*E24 -> 313756.61
B25: 2 | C25: Февраль | D25: 10 | E25: =E24 -> 1000 | F25: 0.5 | G25: =1186*F25*D25/18.9 -> 313.75661 | H25: =G25*E25 -> 313756.61
B26: 3 | C26: Март | D26: 10 | E26: =E25 -> 1000 | F26: 0.5 | G26: =1186*F26*D26/18.9 -> 313.75661 | H26: =G26*E26 -> 313756.61
B27: 4 | C27: Апрель | D27: 10 | E27: =E26 -> 1000 | F27: 0.5 | G27: =1186*F27*D27/18.9 -> 313.75661 | H27: =G27*E27 -> 313756.61
B28: 5 | C28: Май | D28: 10 | E28: =E27 -> 1000 | F28: 0.5 | G28: =1186*F28*D28/18.9 -> 313.75661 | H28: =G28*E28 -> 313756.61
B29: 6 | C29: Июнь | E29: =E28 -> 1000 | F29: 0.5 | G29: =1186*F29*D29/18.9 -> 0 | H29: =G29*E29 -> 0
B30: 7 | C30: Июль | E30: =E29 -> 1000 | F30: 0.5 | G30: =1186*F30*D30/18.9 -> 0 | H30: =G30*E30 -> 0
B31: 8 | C31: Август | E31: =E30 -> 1000 | F31: 0.5 | G31: =1186*F31*D31/18.9 -> 0 | H31: =G31*E31 -> 0
B32: 9 | C32: Сентябрь | D32: 10 | E32: =E31 -> 1000 | F32: 0.5 | G32: =1186*F32*D32/18.9 -> 313.75661 | H32: =G32*E32 -> 313756.61
B33: 10 | C33: Октябрь | D33: 10 | E33: =E32 -> 1000 | F33: 0.5 | G33: =1186*F33*D33/18.9 -> 313.75661 | H33: =G33*E33 -> 313756.61
B34: 11 | C34: Ноябрь | D34: 10 | E34: =E33 -> 1000 | F34: 0.5 | G34: =1186*F34*D34/18.9 -> 313.75661 | H34: =G34*E34 -> 313756.61
B35: 12 | C35: Декабрь | E35: =E34 -> 1000 | F35: 0.5 | G35: =1186*F35*D35/18.9 -> 0 | H35: =G35*E35 -> 0
B36: *в среднем 0,5 л на 1-го учащегося
C38: 3. Приобретение медикаментов и прочих средств медицинского назначения | H38: =G40 -> 565550
B39: № п.п | C39: Наименование товаров | D39: Среднегодовое количество получателей (ед.) | E39: Дни функционирования в год (дни) | F39: Норма отпуска медикаментов на 1 единицу в день (тенге) | G39: Сумма затрат в тенге
B40: 1 | C40: Медикаменты | D40: =836+350 -> 1186 | E40: 204 | F40: =H77/204 -> 2.3375244 | G40: =D40*E40*F40 -> 565550
C41: Расшифровка расходов по медикаментам для учащихся школы
B42: № п/п | C42: Наименование | D42: Ед.измерения | E42: Кол-во, шт. | F42: Цена, тенге | G42: Итого в год, тенге | H42: Расходы по медикаментам на 1 учащегося в год, тенге
B43: 1 | C43: Адреналин 0,18 % 1 мл №5 | D43: штук | E43: 2 | F43: 2000 | G43: =E43*F43 -> 4000 | H43: =G43/1186 -> 3.3726813
B44: =B43+1 -> 2 | C44: Аллервэй № 10 | D44: штук | E44: 50 | F44: 1200 | G44: =E44*F44 -> 60000 | H44: =G44/1186 -> 50.590219
B45: =B44+1 -> 3 | C45: Аммиак 10 % 20 мл | D45: штук | E45: 5 | F45: 150 | G45: =E45*F45 -> 750 | H45: =G45/1186 -> 0.63237774
B46: =B45+1 -> 4 | C46: Бинт 7х14 см стерильный | D46: штук | E46: 50 | F46: 350 | G46: =E46*F46 -> 17500 | H46: =G46/1186 -> 14.755481
B47: =B46+1 -> 5 | C47: Бинт мед эластичн 2х8 см | D47: штук | E47: 10 | F47: 1700 | G47: =E47*F47 -> 17000 | H47: =G47/1186 -> 14.333895
B48: =B47+1 -> 6 | C48: Бриллиантовая зелень | D48: штук | E48: 3 | F48: 300 | G48: =E48*F48 -> 900 | H48: =G48/1186 -> 0.75885329
B49: =B48+1 -> 7 | C49: Вата стерильная | D49: штук | E49: 5 | F49: 300 | G49: =E49*F49 -> 1500 | H49: =G49/1186 -> 1.2647555
B50: =B49+1 -> 8 | C50: Ватные ушные палочки | D50: штук | E50: 5 | F50: 550 | G50: =E50*F50 -> 2750 | H50: =G50/1186 -> 2.3187184
B51: =B50+1 -> 9 | C51: Долгит крем | D51: штук | E51: 3 | F51: 2300 | G51: =E51*F51 -> 6900 | H51: =G51/1186 -> 5.8178752
B52: =B51+1 -> 10 | C52: Ибупрофен 200 мг № 20 табл | D52: штук | E52: 50 | F52: 2200 | G52: =E52*F52 -> 110000 | H52: =G52/1186 -> 92.748735
B53: =B52+1 -> 11 | C53: Лейкопластырь неткан. 2,5х5 см | D53: штук | E53: 10 | F53: 180 | G53: =E53*F53 -> 1800 | H53: =G53/1186 -> 1.5177066
B54: =B53+1 -> 12 | C54: Одноразовые простыни в рулонах | D54: штук | E54: 2 | F54: 7000 | G54: =E54*F54 -> 14000 | H54: =G54/1186 -> 11.804384
B55: =B54+1 -> 13 | C55: Парацетамол 0,5 мг №10 | D55: штук | E55: 100 | F55: 260 | G55: =E55*F55 -> 26000 | H55: =G55/1186 -> 21.922428
... B76: =B75+1 -> 34 | C76: Шприц 10,0 | D76: штук | E76: 20 | F76: 60 | G76: =E76*F76 -> 1200 | H76: =G76/1186 -> 1.0118044
C77: ИТОГО | G77: =SUM(G43:G76) -> 565550 | H77: =SUM(H43:H76) -> 476.85497
C79: 4. Приобретение горюче-смазочных материалов | H79: =SUM(G81:H82) -> 531700
B80: № п.п | C80: Наименование товаров | D80: Ед.измерения | E80: Количество | F80: Средняя стоимость за единицу, тенге | G80: Общая стоимость, тенге
B81: 1 | C81: ДТ зимнее | D81: Литр | E81: 500 | F81: 600 | G81: =E81*F81 -> 300000
B82: 2 | C82: ДТ летнее | D82: Литр | E82: 700 | F82: 331 | G82: =E82*F82 -> 231700
C84: 5. Приобретение прочих запасов | H84: =SUM(G86:H93) -> 49098621
B85: № п.п | C85: Наименование товаров | D85: Ед.измерения | E85: Количество | F85: Средняя стоимость за единицу, тенге | G85: Общая стоимость, тенге
B86: 1 | C86: Хозяйственные товары | D86: Штук | E86: =B276 -> 176 | F86: =G86/E86 -> 114059.28 | G86: =H100 -> 20074433
B87: 2 | C87: Спец.одежда для тех.персонала | D87: Штук | E87: 3 | F87: =G87/E87 -> 260500 | G87: =H280 -> 781500
B88: 3 | C88: Электротовары | D88: Штук | E88: =B312 -> 25 | F88: =G88/E88 -> 135291.88 | G88: =H287 -> 3382297
B89: 4 | C89: Мыло-моющие товары | D89: Штук | E89: =B333 -> 17 | F89: =G89/E89 -> 299344.41 | G89: =H316 -> 5088855
B90: 5 | C90: Канцелярские товары | D90: Штук | E90: 86 | F90: =G90/E90 -> 101408.57 | G90: =H366 -> 8721137
B91: 6 | C91: Мягкий инвентарь для проживающих воспитанников в интернате | D91: Штук | E91: 3 | F91: =G91/E91 -> 2400000 | G91: =H337 -> 7200000
B92: 7 | C92: Товары для кафедры физической культуры | D92: Штук | E92: 19 | F92: =G92/E92 -> 162518.42 | G92: =H344 -> 3087850
B93: 8 | C93: Подписка на периодические издания | D93: Штук | E93: 26 | F93: =G93/E93 -> 29328.806 | G93: =H456 -> 762548.95
B94: Расшифровка расходов на приобретение прочих запасов хозяйственных товаров, необходимых для обслуживания и содержания
B95: основных средств, строительных материалов, используемых на ремонт основных средств, запасных частей для оборудования,
B96: другие запасы непосредственно связанные с содержанием, обслуживанием и ремонтом здания
B98: № п/п | C98: Наименование | D98: Характеристика товара | E98: Ед. изм. | F98: Кол-во, объём | G98: Цена за единицу, тенге | H98: Сумма, тенге
B99: 1 | C99: 2 | D99: 3 | E99: 4 | F99: 5 | G99: 6 | H99: 7
C100: Хозяйственные товары | H100: =SUM(H101:H276) -> 20074433
B101: 1 | C101: Резиновые прокладки для окон | D101: Клейкая основа: Нет Материал: вспененная резина EPDM Длина: 20.0 м Ширина: 8.0 мм | E101: Упаковка | F101: 3 | G101: 4650 | H101: =F101*G101 -> 13950
B102: =B101+1 -> 2 | C102: Резиновые прокладки для железных дверей | D102: Применяется как уплотнитель дверей Цвет - черный ширина 2см глубина 1см | E102: Штук | F102: 20 | G102: 300 | H102: =F102*G102 -> 6000
B103: =B102+1 -> 3 | C103: Щетка утюжок | D103: Щетка утюжок Имеет удобную ручку и твердую щетину ручка с профилированным упором для большого пальца для чистки твердых поверхностей. | E103: Штук | F103: 25 | G103: 1339 | H103: =F103*G103 -> 33475
B104: =B103+1 -> 4 | C104: Грунт для цветов 50 литров мешок | D104: Грунт универсальный для всех видов культур 50 л | E104: Штук | F104: 10 | G104: 2900 | H104: =F104*G104 -> 29000
B105: =B104+1 -> 5 | C105: Монтажный Клей Professional Classic Fix | D105: Короткое наименование товара для клиента:Клей монтажн T Prof Classic Fix универсальный клей №1 в тубе 310 мл, прозрачный Время схватывания 5-10 мин Вес, кг:0.341Прочность склеивания (кг/см²):0.12 | E105: Штук | F105: 15 | G105: 2980 | H105: =F105*G105 -> 44700
B106: =B105+1 -> 6 | C106: Силикон универсальный, бесцветный 280 мл | D106: Силикон универсальный, бесцветный POL, 280 мл | E106: Штук | F106: 15 | G106: 2450 | H106: =F106*G106 -> 36750
B107: =B106+1 -> 7 | C107: Двухкомпонентный клей | D107: .Клей двухкомпонентный МДФ 400мл+100г GA065B | E107: Штук | F107: 10 | G107: 2850 | H107: =F107*G107 -> 28500
B108: =B107+1 -> 8 | C108: Кисть молярная 38 мм ширина | D108: Кисть молярная 38 мм ширина | E108: Штук | F108: 30 | G108: 283 | H108: =F108*G108 -> 8490
B109: =B108+1 -> 9 | C109: Бур по бетону d 6Х110 мм, | D109: Бур по бетону d 6Х110 мм, | E109: Штук | F109: 8 | G109: 650 | H109: =F109*G109 -> 5200
B110: =B109+1 -> 10 | C110: Дюбель нейлоновый со сверлом 10х40 мм для гипсокартона | D110: Дюбель нейлоновый со сверлом 10х40 мм для гипсокартона | E110: Упаковка | F110: 3 | G110: 2350 | H110: =F110*G110 -> 7050
B111: =B110+1 -> 11 | C111: Дюбель гвозди Потай Нагель-дюбель 6х40 | D111: Дюбель гвозди Потай Нагель-дюбель 6х40 | E111: Упаковка | F111: 8 | G111: 1100 | H111: =F111*G111 -> 8800
B112: =B111+1 -> 12 | C112: Пистолет для монтажной пены | D112: Пистолет для монтажной пены Трещоточный регулятор подачи пены Удобная облегченная рукоятка из ударопрочного пластика. Игольчатый и шариковый клапаны из нержавеющей стали. Полировка внутренней поверхности ствола | E112: Штук | F112: 2 | G112: 2570 | H112: =F112*G112 -> 5140
B113: =B112+1 -> 13 | C113: Швабра для мытья окон | D113: Швабра треугольная для мытья окон снаружы вращающаяся: Металл, пластик Размеры в упаковке: 90x24x6 см Комплектация: Швабра, микрофибровые насадки с коротким ворсом - 2 шт, микрофибровые насадки с длинным ворсом - 2 шт. Длина регулируется от 80-130 см; Диаметр трубы: верхняя часть 2,5 см, нижняя 2,2 см; Крючок для подвешивания: 4х3х2 см Вес в упаковке: 575 г | E113: Штук | F113: 25 | G113: 7250 | H113: =F113*G113 -> 181250
... B276: =B275+1 -> 176 | C276: Зеркало настенное | D276: Форма-прямоугольная, Размещение-настенное, Рама-Да, Размеры-70х50см, Высота -70см, ширина-50, толщина-1,7см. | E276: Штук | F276: 15 | G276: 15000 | H276: =F276*G276 -> 225000
B277: Расшифровка расходов на приобретение спец.одежды для тех.персонала
B278: №п/п | C278: Наименование | D278: Характеристика товара | E278: Ед.изм. | F278: Количество | G278: Средняя стоимость за единицу, тенге | H278: Общая стоимость, тенге
C279: 1 | D279: 2 | E279: 3 | F279: 4 | G279: 5 | H279: 6
C280: Спец. одежда для тех.персонала | H280: =H281+H282+H283 -> 781500
B281: 1 | C281: Спец. одежда для техперсонала женский куртка+брюки) | D281: Спецодежда 80%-хлопок хорошо пропускает воздух и впитывает влагу, материал не вызывает аллергии и не создает дискомфорта во время носки. | E281: Штук | F281: 30 | G281: 17000 | H281: =F281*G281 -> 510000
B282: =B281+1 -> 2 | C282: Костюм летний (куртка+брюки) | D282: Костюм летний Кок-тобе (куртка+брюки) Состав ткани: 100% хлопок, обеспечивающий естественную мягкость и дышащесть. Цвет: Василек, придающий стильный и уникальный вид. Этот костюм "Кок-тобе" создан с учетом комфорта, стиля и функциональности. Идеальный выбор для тех, кто ценит естественные материалы и хочет выглядеть стильно в повседневной жизни. | E282: Штук | F282: 12 | G282: 17000 | H282: =F282*G282 -> 204000
B283: =B282+1 -> 3 | C283: Сапоги резиновые Мегатоп зима | D283: Сапоги резиновые Мегатоп зима Материал: этилвинилацетат (ЭВА) — упругий, эластичный и устойчивый к истиранию, морозам и влаге. Защитный подносок: до 20 Дж Цвета: хаки Высота: 40 см Вес одной пары сапог составляет всего 700 грамм, | E283: Пара | F283: 5 | G283: 13500 | H283: =F283*G283 -> 67500
B284: Расшифровка расходов на приобретение электротоваров
B285: №п/п | C285: Наименование | D285: Характеристика товара | E285: Ед.изм. | F285: Количество | G285: Средняя стоимость за единицу, тенге | H285: Общая стоимость, тенге
C286: 1 | D286: 2 | E286: 3 | F286: 4 | G286: 5 | H286: 6
C287: Электротовары | H287: =SUM(H288:H312) -> 3382297
B288: 1 | C288: Автоматические выключатели | D288: ВА47-29 1Р с16А IP20 | E288: Штук | F288: 20 | G288: 848 | H288: =F288*G288 -> 16960
B289: =B288+1 -> 2 | C289: Автоматические выключатели | D289: ВА47-29 1Р с25А IP20 | E289: Штук | F289: 5 | G289: 2174 | H289: =F289*G289 -> 10870
B290: =B289+1 -> 3 | C290: Автоматический выключатель | D290: ВА47-29 3Р с32А IP20 | E290: Штук | F290: 1 | G290: 2250 | H290: =F290*G290 -> 2250
...

Sheet Сводная общая 2027г.
C3: Сводный расчет расходов на 2027 год ПЛАН
C4: ФНАО «Республиканская физико-математическая школа» в г.Алматы
C5: по бюджетной программе 004 "Обеспечение доступности качественного школьного образования"
C6: по 100 подпрограмме "Обучение и воспитание детей в республиканских организациях образования"
C8: 1. Фонд Оплаты Труда | H8: =H10+H11+H12+H13+H14+H15+H16 -> 2.2271434e+09
B9: № п.п | C9: Наименование расходов | H9: Сумма затрат в тенге в рамках лимита
B10: 1 | C10: Штатное расписание | H10: ='[1]Сводная лимит 2027г.'!H10+'[1]Сводная ДП 2027г.'!H10 -> 7.2818517e+08
B11: =B10+1 -> 2 | C11: Оплата труда по тарификации учителей | H11: ='[1]Сводная лимит 2027г.'!H11+'[1]Сводная ДП 2027г.'!H11 -> 1.0358907e+09
B12: =B11+1 -> 3 | C12: Компенсационные выплаты | G12: в размере ДО | H12: ='[1]Сводная лимит 2027г.'!H12+'[1]Сводная ДП 2027г.'!H12 -> 1.3984083e+08
B13: =B12+1 -> 4 | C13: Социальный налог | G13: 0.06 | H13: ='[1]Сводная лимит 2027г.'!H13+'[1]Сводная ДП 2027г.'!H13 -> 98937221
B14: =B13+1 -> 5 | C14: Социальные отчисления | G14: 0.05 | H14: ='[1]Сводная лимит 2027г.'!H14+'[1]Сводная ДП 2027г.'!H14 -> 85676253
B15: =B14+1 -> 6 | C15: Обязательное социальное медицинское страхование | G15: 0.03 | H15: ='[1]Сводная лимит 2027г.'!H15+'[1]Сводная ДП 2027г.'!H15 -> 52922277
B16: 7 | C16: Обязательные пенсионные взносы за счет работодателя | G16: 0.045 | H16: ='[1]Сводная лимит 2027г.'!H16+'[1]Сводная ДП 2027г.'!H16 -> 85690884
C18: 2.Приобретение питьевой воды для учащихся | G18: =G20 -> 6400634.9
B19: № п.п | C19: Наименование расходов | D19: Дни функционирования учреждения (дни) | E19: Количество бутылей на 2026 год | F19: Стоимость за ед.в тенге | G19: Сумма затрат в тенге
B20: 2 | C20: Вода питьевая бутилированная 18,9 л на 1186 детей | D20: 167 | E20: =G23 -> 6400.6349 | F20: 1000 | G20: =E20*F20 -> 6400634.9
B21: Расшифровка на приобретение питьевой воды
B22: № | C22: Период | D22: Кол-во дней | E22: Цена | F22: Норматив на 1-го на день * (л) | G22: Количество бутылей 1 бутыле 18,9 (л) | H22: Сумма (тенге)
C23: Всего: | D23: =SUM(D24:D35) -> 167 | G23: =SUM(G24:G35) -> 6400.6349 | H23: =SUM(H24:H35) -> 6400634.9
B24: 1 | C24: Январь | D24: 16 | E24: 1000 | F24: 0.5 | G24: 627.51323 | H24: =G24*E24 -> 627513.23
B25: 2 | C25: Февраль | D25: 20 | E25: 1000 | F25: 0.5 | G25: 627.51323 | H25: =G25*E25 -> 627513.23
B26: 3 | C26: Март | D26: 14 | E26: 1000 | F26: 0.5 | G26: 596.13757 | H26: =G26*E26 -> 596137.57
B27: 4 | C27: Апрель | D27: 22 | E27: 1000 | F27: 0.5 | G27: 627.51323 | H27: =G27*E27 -> 627513.23
B28: 5 | C28: Май | D28: 17 | E28: 1000 | F28: 0.5 | G28: 627.51323 | H28: =G28*E28 -> 627513.23
B29: 6 | C29: Июнь | D29: 5 | E29: 1000 | F29: 0.5 | G29: 658.88889 | H29: =G29*E29 -> 658888.89
B30: 7 | C30: Июль | E30: 1000 | F30: 0.5 | G30: 0 | H30: =G30*E30 -> 0
B31: 8 | C31: Август | E31: 1000 | F31: 0.5 | G31: 0 | H31: =G31*E31 -> 0
B32: 9 | C32: Сентябрь | D32: 22 | E32: 1000 | F32: 0.5 | G32: 658.88889 | H32: =G32*E32 -> 658888.89
B33: 10 | C33: Октябрь | D33: 21 | E33: 1000 | F33: 0.5 | G33: 658.88889 | H33: =G33*E33 -> 658888.89
B34: 11 | C34: Ноябрь | D34: 13 | E34: 1000 | F34: 0.5 | G34: 690.26455 | H34: =G34*E34 -> 690264.55
B35: 12 | C35: Декабрь | D35: 17 | E35: 1000 | F35: 0.5 | G35: 627.51323 | H35: =G35*E35 -> 627513.23
B36: *в среднем 1 л на 1-го учащегося
C38: 3. Приобретение медикаментов и прочих средств медицинского назначения | H38: =G40+G41 -> 262415
B39: № п.п | C39: Наименование товаров | D39: Среднегодовое количество получателей (ед) | E39: Дни функционирования в год (дни) | F39: Норма отпуска медикаментов на 1 единицу в день (тенге) | G39: Сумма затрат в тенге
B40: 1 | C40: Медикаменты | D40: =836+350 -> 1186 | E40: 204 | F40: =H91/204 -> 0.39651738 | G40: =D40*E40*F40 -> 95935
B41: 2 | C41: Прочие средства медицинского назначения | G41: =SUM(H45:H50) -> 166480
B43: Расшифровка расходов прочих средств медицинского назначения
B44: № п/п | C44: Наименование | D44: Характеристика товара | E44: Ед. изм. | F44: Кол-во, объём | G44: Цена за единицу, тенге | H44: Сумма, тенге
B45: 1 | C45: Омрон Термометр | E45: шт | F45: 1 | G45: 32300 | H45: =F45*G45 -> 32300
B46: 2 | C46: Тонометр UB-888 | E46: шт | F46: 1 | G46: 26000 | H46: =F46*G46 -> 26000
B47: 3 | C47: Простыни однаразовые в рулоне | E47: шт | F47: 2 | G47: 5000 | H47: =F47*G47 -> 10000
B48: 4 | C48: Халат пл 40 (голубой) | E48: шт | F48: 15 | G48: 385 | H48: =F48*G48 -> 5775
B49: 5 | C49: Комплект шин подросковых | E49: шт | F49: 1 | G49: 84825 | H49: =F49*G49 -> 84825
B50: 6 | C50: Тонометр UA-100 механ. со встав. стетоск. | E50: шт | F50: 1 | G50: 7580 | H50: =F50*G50 -> 7580
C51: ИТОГО | H51: =SUM(H45:H50) -> 166480
C52: Расшифровка расходов по медикаментам для учащихся школы
B53: № п/п | C53: Наименование | D53: Ед.изерения | E53: Кол-во, шт. | F53: Цена, тенге | G53: Итого в год, тенге | H53: Расходы по медикаментам на 1 учащегося в год, тенге
B54: 1 | C54: Перчатки смотровые | D54: шт | E54: 10 | F54: 160 | G54: =E54*F54 -> 1600 | H54: =G54/1186 -> 1.3490725
B55: =B54+1 -> 2 | C55: Бриллиантовой зелени р-р спиртовой | D55: шт | E55: 2 | F55: 80 | G55: =E55*F55 -> 160 | H55: =G55/1186 -> 0.13490725
B56: =B55+1 -> 3 | C56: Бинт нест | D56: шт | E56: 50 | F56: 150 | G56: =E56*F56 -> 7500 | H56: =G56/1186 -> 6.3237774
B57: =B56+1 -> 4 | C57: Ибупрофен | D57: упаковка | E57: 20 | F57: 410 | G57: =E57*F57 -> 8200 | H57: =G57/1186 -> 6.9139966
B58: =B57+1 -> 5 | C58: Шпатель медицинский | D58: упаковка | E58: 1 | F58: 1470 | G58: =E58*F58 -> 1470 | H58: =G58/1186 -> 1.2394604
B59: =B58+1 -> 6 | C59: Фрост спрей охлаждающее ср-во | D59: шт | E59: 2 | F59: 2700 | G59: =E59*F59 -> 5400 | H59: =G59/1186 -> 4.5531197
B60: =B59+1 -> 7 | C60: Троксевазин гель | D60: шт | E60: 2 | F60: 4505 | G60: =E60*F60 -> 9010 | H60: =G60/1186 -> 7.5969646
B61: =B60+1 -> 8 | C61: Перчатки нитриловые смотровые нестерильные неопудренные размер S | D61: упаковка | E61: 2 | F61: 1500 | G61: =E61*F61 -> 3000 | H61: =G61/1186 -> 2.529511
B62: =B61+1 -> 9 | C62: Перчатки нитриловые смотровые нестерильные неопудренные размер M | D62: упаковка | E62: 2 | F62: 1500 | G62: =E62*F62 -> 3000 | H62: =G62/1186 -> 2.529511
B63: =B62+1 -> 10 | C63: Перчатки | D63: шт | E63: 5 | F63: 160 | G63: =E63*F63 -> 800 | H63: =G63/1186 -> 0.67453626
B64: =B63+1 -> 11 | C64: Вата стерильная | D64: шт | E64: 5 | F64: 265 | G64: =E64*F64 -> 1325 | H64: =G64/1186 -> 1.1172007
B65: =B64+1 -> 12 | C65: Отипакс | D65: шт | E65: 1 | F65: 0 | G65: =E65*F65 -> 0 | H65: =G65/1186 -> 0
B66: =B65+1 -> 13 | C66: Бинт стер | D66: шт | E66: 10 | F66: 190 | G66: =E66*F66 -> 1900 | H66: =G66/1186 -> 1.6020236
... B90: =B89+1 -> 37 | C90: Ватные ушные палочки | D90: шт | E90: 5 | F90: 140 | G90: =E90*F90 -> 700 | H90: =G90/1186 -> 0.59021922
C91: ИТОГО | G91: =SUM(G54:G90) -> 95935 | H91: =SUM(H54:H90) -> 80.889545
C93: 4. Приобретение горюче-смазочных материалов | H93: =SUM(G95:H96) -> 702000
B94: № п.п | C94: Наименование товаров | D94: ед изм | E94: Количество | F94: Средняя стоимость за единицу, тенге | G94: Общая стоимость, тенге
B95: 1 | C95: ДТ зимнее | D95: Литр | E95: 600 | F95: 580 | G95: =E95*F95 -> 348000
B96: 2 | C96: ДТ летнее | D96: Литр | E96: 1200 | F96: 295 | G96: =E96*F96 -> 354000
C98: 5. Приобретение прочих запасов | H98: =G100+G101+G103+G102 -> 14373593
B99: № п.п | C99: Наименование товаров | D99: ед изм | E99: Количество | F99: Средняя стоимость за единицу, тенге | G99: Общая стоимость, тенге
B100: 1 | C100: Хозяйственные товары | D100: шт | E100: 254 | F100: =G100/E100 -> 34289.079 | G100: =H110+H311+H343 -> 8709426
B101: 2 | C101: Канцелярские товары | D101: шт | E101: 74 | F101: =G101/E101 -> 31562.426 | G101: =H453 -> 2335619.5
B102: 3 | C102: Инвентарь для проживающих воспитанников в интернате | D102: шт | E102: 4 | F102: =G102/E102 -> 725000 | G102: =H370 -> 2900000
B103: 4 | C103: Подписка на периодические издания | D103: шт | E103: 25 | F103: =G103/E103 -> 17141.909 | G103: =H485 -> 428547.72
B104: Расшифровка расходов на приобретению прочих запасов хозяйственных товаров, необходимых для обслуживания и содержания
B105: основных средств, строительных материалов, используемых на ремонт основных средств, запасных частей для оборудования,
B106: другие запасы непосредственно связанные с содержанием, обслуживанием и ремонтом здания
B108: № п/п | C108: Наименование | D108: Характеристика товара | E108: Ед. изм. | F108: Кол-во, объём | G108: Цена за единицу, тенге | H108: Сумма, тенге
B109: 1 | C109: 2 | D109: 3 | E109: 4 | F109: 5 | G109: 6 | H109: 7
C110: Хозяйственные товары | H110: =SUM(H111:H310) -> 3948356
B111: 1 | C111: Щетка утюжок | D111: Щетка утюжок | E111: Штука | F111: 10 | G111: 1550 | H111: =F111*G111 -> 15500
B112: =B111+1 -> 2 | C112: Грунт для цветов 50 литров мешок | D112: Грунт для цветов 50 литров мешок | E112: Штука | F112: 5 | G112: 2900 | H112: =F112*G112 -> 14500
B113: =B112+1 -> 3 | C113: Монтажный Клей Professional Classic Fix | D113: Монтажный Клей Professional Classic Fix универсальный клей №1 в тубе 310 мл, прозрачный | E113: штука | F113: 5 | G113: 3000 | H113: =F113*G113 -> 15000
B114: =B113+1 -> 4 | C114: Силикон универсальный, бесцветный POL, 280 мл | D114: Силикон универсальный, бесцветный, 280 мл | E114: Штука | F114: 10 | G114: 2600 | H114: =F114*G114 -> 26000
B115: =B114+1 -> 5 | C115: Двухкомпонентный клей | D115: Клей 2-х компонентный 400+100 мл. | E115: Штука | F115: 5 | G115: 3550 | H115: =F115*G115 -> 17750
B116: =B115+1 -> 6 | C116: Кисть молярная 38 мм ширина | D116: Кисть молярная 38 мм ширина | E116: Штука | F116: 20 | G116: 330 | H116: =F116*G116 -> 6600
B117: =B116+1 -> 7 | C117: Бур по бетону d 6Х110 мм, | D117: Бур по бетону d 6Х110 мм, | E117: Штука | F117: 5 | G117: 550 | H117: =F117*G117 -> 2750
B118: =B117+1 -> 8 | C118: Коронка по бетону для подрозетников d 80 | D118: Коронка по бетону для подрозетников d 80 | E118: Штука | F118: 1 | G118: 5100 | H118: =F118*G118 -> 5100
B119: =B118+1 -> 9 | C119: Дюбель нейлоновый со сверлом 10х40 мм для гипсокартона | D119: Дюбель нейлоновый со сверлом 10х40 мм для гипсокартона | E119: упаковка | F119: 2 | G119: 2100 | H119: =F119*G119 -> 4200
B120: =B119+1 -> 10 | C120: Дюбель гвозди Потай Нагель-дюбель 6х40 | D120: Дюбель гвозди Потай Нагель-дюбель 6х40 | E120: упаковка | F120: 2 | G120: 1100 | H120: =F120*G120 -> 2200
B121: =B120+1 -> 11 | C121: Пистолет для монтажной пены | D121: Пистолет для монтажной пены | E121: Штука | F121: 2 | G121: 2800 | H121: =F121*G121 -> 5600
B122: =B121+1 -> 12 | C122: Грабли веерные для листьев550х385/1440 | D122: Грабли веерные для листьев550х385/1440 | E122: Штука | F122: 2 | G122: 6900 | H122: =F122*G122 -> 13800
B123: =B122+1 -> 13 | C123: Удлинитель катушка 50 м. | D123: Удлинитель силовой 50 м, 16А, тип УХ10, ПВС, усиленный, на кабельной катушке, 4 розетки сечение 2 x 2.5 мм IP20 максимальная нагрузка тока 3500 Вт | E123: Штука | F123: 1 | G123: 50100 | H123: =F123*G123 -> 50100
... B310: =B309+1 -> 200 | C310: Строительный нож | D310: Складной нож с пластиковой двухкомпонентной рукояткой и 5 сменными трапециевидными лезвиями пригодится для бытового использования, во время проведения ремонтных и строительных работ. За счет трапециевидного лезвия он легко режет заготовки из картона, линолеума, кожи и других плотных материалов. За счет складной конструкции нож удобен и безопасен в транспортировке и хранении. | E310: шт | F310: 3 | G310: 2530 | H310: =F310*G310 -> 7590
C311: Электротовары | H311: =SUM(H312:H342) -> 1660445
B312: 1 | C312: Датчик движения | D312: FOX-08 1200Вт, 12м,87*145*125 IP44 | E312: Штука | F312: 5 | G312: 3200 | H312: =F312*G312 -> 16000
B313: =B312+1 -> 2 | C313: Автоматические выключатели | D313: ВА47-29 1Р с16А IP20 | E313: Штука | F313: 5 | G313: 825 | H313: =F313*G313 -> 4125
B314: =B313+1 -> 3 | C314: Автоматические выключатели | D314: ВА47-29 1Р с25А IP20 | E314: Штука | F314: 5 | G314: 1045 | H314: =F314*G314 -> 5225
B315: =B314+1 -> 4 | C315: Автоматические выключатели | D315: ВА47-29 3Р с32А IP20 | E315: Штука | F315: 5 | G315: 2535 | H315: =F315*G315 -> 12675
B316: =B315+1 -> 5 | C316: Изолента | D316: ПВХ 19 ХО. 15*20 (синия) | E316: Штука | F316: 5 | G316: 396 | H316: =F316*G316 -> 1980
B317: =B316+1 -> 6 | C317: Дифф. выключатель нагрузки | D317: 11473 УЗО 1Р+Н 16А. 30мА АД63С | E317: Штука | F317: 5 | G317: 26400 | H317: =F317*G317 -> 132000
B318: =B317+1 -> 7 | C318: Электрическая лампа светодиодная | D318: Е-27. 15Вт. 6400к.1200лм.220В-240В. (цвет холодный) | E318: Штука | F318: 100 | G318: 1920 | H318: =F318*G318 -> 192000
...

Sheet Сводная общая 2028г.
C3: Сводный расчет расходов на 2028 год ПЛАН
C4: ФНАО «Республиканская физико-математическая школа» в г.Алматы
C5: по бюджетной программе 004 "Обеспечение доступности качественного школьного образования"
C6: по 100 подпрограмме "Обучение и воспитание детей в республиканских организациях образования"
C8: 1. Фонд Оплаты Труда | H8: =H10+H11+H12+H13+H14+H15+H16 -> 2.2282882e+09
B9: № п.п | C9: Наименование расходов | H9: Сумма затрат в тенге в рамках лимита
B10: 1 | C10: Штатное расписание | H10: ='[1]Сводная лимит 2028г.'!H10+'[1]Сводная ДП 2028г.'!H10 -> 7.2828933e+08
B11: =B10+1 -> 2 | C11: Оплата труда по тарификации учителей | H11: ='[1]Сводная лимит 2028г.'!H11+'[1]Сводная ДП 2028г.'!H11 -> 1.0293393e+09
B12: =B11+1 -> 3 | C12: Компенсационные выплаты | G12: в размере ДО | H12: ='[1]Сводная лимит 2028г.'!H12+'[1]Сводная ДП 2028г.'!H12 -> 1.3913335e+08
B13: =B12+1 -> 4 | C13: Социальный налог | G13: 0.06 | H13: ='[1]Сводная лимит 2028г.'!H13+'[1]Сводная ДП 2028г.'!H13 -> 98565047
B14: =B13+1 -> 5 | C14: Социальные отчисления | G14: 0.05 | H14: ='[1]Сводная лимит 2028г.'!H14+'[1]Сводная ДП 2028г.'!H14 -> 85354287
B15: =B14+1 -> 6 | C15: Обязательное социальное медицинское страхование | G15: 0.03 | H15: ='[1]Сводная лимит 2028г.'!H15+'[1]Сводная ДП 2028г.'!H15 -> 52728858
B16: 7 | C16: Обязательные пенсионные взносы за счет работодателя | G16: 0.05 | H16: ='[1]Сводная лимит 2028г.'!H16+'[1]Сводная ДП 2028г.'!H16 -> 94878016
C18: 2.Приобретение питьевой воды для учащихся | G18: =G20 -> 6400634.9
B19: № п.п | C19: Наименование расходов | D19: Дни функционирования учреждения (дни) | E19: Количество бутылей на 2026 год | F19: Стоимость за ед.в тенге | G19: Сумма затрат в тенге
B20: 2 | C20: Вода питьевая бутилированная 18,9 л на 1186 детей | D20: 167 | E20: =G23 -> 6400.6349 | F20: 1000 | G20: =E20*F20 -> 6400634.9
B21: Расшифровка на приобретение питьевой воды
B22: № | C22: Период | D22: Кол-во дней | E22: Цена | F22: Норматив на 1-го на день * (л) | G22: Количество бутылей 1 бутыле 18,9 (л) | H22: Сумма (тенге)
C23: Всего: | D23: =SUM(D24:D35) -> 167 | G23: =SUM(G24:G35) -> 6400.6349 | H23: =SUM(H24:H35) -> 6400634.9
B24: 1 | C24: Январь | D24: 16 | E24: 1000 | F24: 0.5 | G24: 627.51323 | H24: =G24*E24 -> 627513.23
B25: 2 | C25: Февраль | D25: 20 | E25: 1000 | F25: 0.5 | G25: 627.51323 | H25: =G25*E25 -> 627513.23
B26: 3 | C26: Март | D26: 14 | E26: 1000 | F26: 0.5 | G26: 596.13757 | H26: =G26*E26 -> 596137.57
B27: 4 | C27: Апрель | D27: 22 | E27: 1000 | F27: 0.5 | G27: 627.51323 | H27: =G27*E27 -> 627513.23
B28: 5 | C28: Май | D28: 17 | E28: 1000 | F28: 0.5 | G28: 627.51323 | H28: =G28*E28 -> 627513.23
B29: 6 | C29: Июнь | D29: 5 | E29: 1000 | F29: 0.5 | G29: 658.88889 | H29: =G29*E29 -> 658888.89
B30: 7 | C30: Июль | E30: 1000 | F30: 0.5 | G30: 0 | H30: =G30*E30 -> 0
B31: 8 | C31: Август | E31: 1000 | F31: 0.5 | G31: 0 | H31: =G31*E31 -> 0
B32: 9 | C32: Сентябрь | D32: 22 | E32: 1000 | F32: 0.5 | G32: 658.88889 | H32: =G32*E32 -> 658888.89
B33: 10 | C33: Октябрь | D33: 21 | E33: 1000 | F33: 0.5 | G33: 658.88889 | H33: =G33*E33 -> 658888.89
B34: 11 | C34: Ноябрь | D34: 13 | E34: 1000 | F34: 0.5 | G34: 690.26455 | H34: =G34*E34 -> 690264.55
B35: 12 | C35: Декабрь | D35: 17 | E35: 1000 | F35: 0.5 | G35: 627.51323 | H35: =G35*E35 -> 627513.23
B36: *в среднем 1 л на 1-го учащегося
C38: 3. Приобретение медикаментов и прочих средств медицинского назначения | H38: =G40+G41 -> 262415
B39: № п.п | C39: Наименование товаров | D39: Среднегодовое количество получателей (ед) | E39: Дни функционирования в год (дни) | F39: Норма отпуска медикаментов на 1 единицу в день (тенге) | G39: Сумма затрат в тенге
B40: 1 | C40: Медикаменты | D40: =836+350 -> 1186 | E40: 204 | F40: =H91/204 -> 0.39651738 | G40: =D40*E40*F40 -> 95935
B41: 2 | C41: Прочие средства медицинского назначения | G41: =SUM(H45:H50) -> 166480
B43: Расшифровка расходов прочих средств медицинского назначения
B44: № п/п | C44: Наименование | D44: Характеристика товара | E44: Ед. изм. | F44: Кол-во, объём | G44: Цена за единицу, тенге | H44: Сумма, тенге
B45: 1 | C45: Омрон Термометр | E45: шт | F45: 1 | G45: 32300 | H45: =F45*G45 -> 32300
B46: 2 | C46: Тонометр UB-888 | E46: шт | F46: 1 | G46: 26000 | H46: =F46*G46 -> 26000
B47: 3 | C47: Простыни однаразовые в рулоне | E47: шт | F47: 2 | G47: 5000 | H47: =F47*G47 -> 10000
B48: 4 | C48: Халат пл 40 (голубой) | E48: шт | F48: 15 | G48: 385 | H48: =F48*G48 -> 5775
B49: 5 | C49: Комплект шин подросковых | E49: шт | F49: 1 | G49: 84825 | H49: =F49*G49 -> 84825
B50: 6 | C50: Тонометр UA-100 механ. со встав. стетоск. | E50: шт | F50: 1 | G50: 7580 | H50: =F50*G50 -> 7580
C51: ИТОГО | H51: =SUM(H45:H50) -> 166480
C52: Расшифровка расходов по медикаментам для учащихся школы
B53: № п/п | C53: Наименование | D53: Ед.изерения | E53: Кол-во, шт. | F53: Цена, тенге | G53: Итого в год, тенге | H53: Расходы по медикаментам на 1 учащегося в год, тенге
B54: 1 | C54: Перчатки смотровые | D54: шт | E54: 10 | F54: 160 | G54: =E54*F54 -> 1600 | H54: =G54/1186 -> 1.3490725
B55: =B54+1 -> 2 | C55: Бриллиантовой зелени р-р спиртовой | D55: шт | E55: 2 | F55: 80 | G55: =E55*F55 -> 160 | H55: =G55/1186 -> 0.13490725
B56: =B55+1 -> 3 | C56: Бинт нест | D56: шт | E56: 50 | F56: 150 | G56: =E56*F56 -> 7500 | H56: =G56/1186 -> 6.3237774
B57: =B56+1 -> 4 | C57: Ибупрофен | D57: упаковка | E57: 20 | F57: 410 | G57: =E57*F57 -> 8200 | H57: =G57/1186 -> 6.9139966
B58: =B57+1 -> 5 | C58: Шпатель медицинский | D58: упаковка | E58: 1 | F58: 1470 | G58: =E58*F58 -> 1470 | H58: =G58/1186 -> 1.2394604
B59: =B58+1 -> 6 | C59: Фрост спрей охлаждающее ср-во | D59: шт | E59: 2 | F59: 2700 | G59: =E59*F59 -> 5400 | H59: =G59/1186 -> 4.5531197
B60: =B59+1 -> 7 | C60: Троксевазин гель | D60: шт | E60: 2 | F60: 4505 | G60: =E60*F60 -> 9010 | H60: =G60/1186 -> 7.5969646
B61: =B60+1 -> 8 | C61: Перчатки нитриловые смотровые нестерильные неопудренные размер S | D61: упаковка | E61: 2 | F61: 1500 | G61: =E61*F61 -> 3000 | H61: =G61/1186 -> 2.529511
B62: =B61+1 -> 9 | C62: Перчатки нитриловые смотровые нестерильные неопудренные размер M | D62: упаковка | E62: 2 | F62: 1500 | G62: =E62*F62 -> 3000 | H62: =G62/1186 -> 2.529511
B63: =B62+1 -> 10 | C63: Перчатки | D63: шт | E63: 5 | F63: 160 | G63: =E63*F63 -> 800 | H63: =G63/1186 -> 0.67453626
B64: =B63+1 -> 11 | C64: Вата стерильная | D64: шт | E64: 5 | F64: 265 | G64: =E64*F64 -> 1325 | H64: =G64/1186 -> 1.1172007
B65: =B64+1 -> 12 | C65: Отипакс | D65: шт | E65: 1 | F65: 0 | G65: =E65*F65 -> 0 | H65: =G65/1186 -> 0
B66: =B65+1 -> 13 | C66: Бинт стер | D66: шт | E66: 10 | F66: 190 | G66: =E66*F66 -> 1900 | H66: =G66/1186 -> 1.6020236
... B90: =B89+1 -> 37 | C90: Ватные ушные палочки | D90: шт | E90: 5 | F90: 140 | G90: =E90*F90 -> 700 | H90: =G90/1186 -> 0.59021922
C91: ИТОГО | G91: =SUM(G54:G90) -> 95935 | H91: =SUM(H54:H90) -> 80.889545
C93: 4. Приобретение горюче-смазочных материалов | H93: =SUM(G95:H96) -> 702000
B94: № п.п | C94: Наименование товаров | D94: ед изм | E94: Количество | F94: Средняя стоимость за единицу, тенге | G94: Общая стоимость, тенге
B95: 1 | C95: ДТ зимнее | D95: Литр | E95: 600 | F95: 580 | G95: =E95*F95 -> 348000
B96: 2 | C96: ДТ летнее | D96: Литр | E96: 1200 | F96: 295 | G96: =E96*F96 -> 354000
C98: 5. Приобретение прочих запасов | H98: =G100+G101+G103+G102 -> 14373593
B99: № п.п | C99: Наименование товаров | D99: ед изм | E99: Количество | F99: Средняя стоимость за единицу, тенге | G99: Общая стоимость, тенге
B100: 1 | C100: Хозяйственные товары | D100: шт | E100: 254 | F100: =G100/E100 -> 34289.079 | G100: =H110+H311+H343 -> 8709426
B101: 2 | C101: Канцелярские товары | D101: шт | E101: 74 | F101: =G101/E101 -> 31562.426 | G101: =H453 -> 2335619.5
B102: 3 | C102: Инвентарь для проживающих воспитанников в интернате | D102: шт | E102: 4 | F102: =G102/E102 -> 725000 | G102: =H370 -> 2900000
B103: 4 | C103: Подписка на периодические издания | D103: шт | E103: 25 | F103: =G103/E103 -> 17141.909 | G103: =H485 -> 428547.72
B104: Расшифровка расходов на приобретению прочих запасов хозяйственных товаров, необходимых для обслуживания и содержания
B105: основных средств, строительных материалов, используемых на ремонт основных средств, запасных частей для оборудования,
B106: другие запасы непосредственно связанные с содержанием, обслуживанием и ремонтом здания
B108: № п/п | C108: Наименование | D108: Характеристика товара | E108: Ед. изм. | F108: Кол-во, объём | G108: Цена за единицу, тенге | H108: Сумма, тенге
B109: 1 | C109: 2 | D109: 3 | E109: 4 | F109: 5 | G109: 6 | H109: 7
C110: Хозяйственные товары | H110: =SUM(H111:H310) -> 3948356
B111: 1 | C111: Щетка утюжок | D111: Щетка утюжок | E111: Штука | F111: 10 | G111: 1550 | H111: =F111*G111 -> 15500
B112: =B111+1 -> 2 | C112: Грунт для цветов 50 литров мешок | D112: Грунт для цветов 50 литров мешок | E112: Штука | F112: 5 | G112: 2900 | H112: =F112*G112 -> 14500
B113: =B112+1 -> 3 | C113: Монтажный Клей Professional Classic Fix | D113: Монтажный Клей Professional Classic Fix универсальный клей №1 в тубе 310 мл, прозрачный | E113: штука | F113: 5 | G113: 3000 | H113: =F113*G113 -> 15000
B114: =B113+1 -> 4 | C114: Силикон универсальный, бесцветный POL, 280 мл | D114: Силикон универсальный, бесцветный, 280 мл | E114: Штука | F114: 10 | G114: 2600 | H114: =F114*G114 -> 26000
B115: =B114+1 -> 5 | C115: Двухкомпонентный клей | D115: Клей 2-х компонентный 400+100 мл. | E115: Штука | F115: 5 | G115: 3550 | H115: =F115*G115 -> 17750
B116: =B115+1 -> 6 | C116: Кисть молярная 38 мм ширина | D116: Кисть молярная 38 мм ширина | E116: Штука | F116: 20 | G116: 330 | H116: =F116*G116 -> 6600
B117: =B116+1 -> 7 | C117: Бур по бетону d 6Х110 мм, | D117: Бур по бетону d 6Х110 мм, | E117: Штука | F117: 5 | G117: 550 | H117: =F117*G117 -> 2750
B118: =B117+1 -> 8 | C118: Коронка по бетону для подрозетников d 80 | D118: Коронка по бетону для подрозетников d 80 | E118: Штука | F118: 1 | G118: 5100 | H118: =F118*G118 -> 5100
B119: =B118+1 -> 9 | C119: Дюбель нейлоновый со сверлом 10х40 мм для гипсокартона | D119: Дюбель нейлоновый со сверлом 10х40 мм для гипсокартона | E119: упаковка | F119: 2 | G119: 2100 | H119: =F119*G119 -> 4200
B120: =B119+1 -> 10 | C120: Дюбель гвозди Потай Нагель-дюбель 6х40 | D120: Дюбель гвозди Потай Нагель-дюбель 6х40 | E120: упаковка | F120: 2 | G120: 1100 | H120: =F120*G120 -> 2200
B121: =B120+1 -> 11 | C121: Пистолет для монтажной пены | D121: Пистолет для монтажной пены | E121: Штука | F121: 2 | G121: 2800 | H121: =F121*G121 -> 5600
B122: =B121+1 -> 12 | C122: Грабли веерные для листьев550х385/1440 | D122: Грабли веерные для листьев550х385/1440 | E122: Штука | F122: 2 | G122: 6900 | H122: =F122*G122 -> 13800
B123: =B122+1 -> 13 | C123: Удлинитель катушка 50 м. | D123: Удлинитель силовой 50 м, 16А, тип УХ10, ПВС, усиленный, на кабельной катушке, 4 розетки сечение 2 x 2.5 мм IP20 максимальная нагрузка тока 3500 Вт | E123: Штука | F123: 1 | G123: 50100 | H123: =F123*G123 -> 50100
... B310: =B309+1 -> 200 | C310: Строительный нож | D310: Складной нож с пластиковой двухкомпонентной рукояткой и 5 сменными трапециевидными лезвиями пригодится для бытового использования, во время проведения ремонтных и строительных работ. За счет трапециевидного лезвия он легко режет заготовки из картона, линолеума, кожи и других плотных материалов. За счет складной конструкции нож удобен и безопасен в транспортировке и хранении. | E310: шт | F310: 3 | G310: 2530 | H310: =F310*G310 -> 7590
C311: Электротовары | H311: =SUM(H312:H342) -> 1660445
B312: 1 | C312: Датчик движения | D312: FOX-08 1200Вт, 12м,87*145*125 IP44 | E312: Штука | F312: 5 | G312: 3200 | H312: =F312*G312 -> 16000
B313: =B312+1 -> 2 | C313: Автоматические выключатели | D313: ВА47-29 1Р с16А IP20 | E313: Штука | F313: 5 | G313: 825 | H313: =F313*G313 -> 4125
B314: =B313+1 -> 3 | C314: Автоматические выключатели | D314: ВА47-29 1Р с25А IP20 | E314: Штука | F314: 5 | G314: 1045 | H314: =F314*G314 -> 5225
B315: =B314+1 -> 4 | C315: Автоматические выключатели | D315: ВА47-29 3Р с32А IP20 | E315: Штука | F315: 5 | G315: 2535 | H315: =F315*G315 -> 12675
B316: =B315+1 -> 5 | C316: Изолента | D316: ПВХ 19 ХО. 15*20 (синия) | E316: Штука | F316: 5 | G316: 396 | H316: =F316*G316 -> 1980
B317: =B316+1 -> 6 | C317: Дифф. выключатель нагрузки | D317: 11473 УЗО 1Р+Н 16А. 30мА АД63С | E317: Штука | F317: 5 | G317: 26400 | H317: =F317*G317 -> 132000
B318: =B317+1 -> 7 | C318: Электрическая лампа светодиодная | D318: Е-27. 15Вт. 6400к.1200лм.220В-240В. (цвет холодный) | E318: Штука | F318: 100 | G318: 1920 | H318: =F318*G318 -> 192000
...

Sheet ШР СВОД Алматы 2026 
I5: «УТВЕРЖДЕНО»
I6: Решением Правления НАО «РФМШ»
I7: Протокол №_____ от «______» _____________ 20_____г.
A10: Штатное расписание
A11: Наименование организации: Филиал НАО «Республиканская физико-математическая школа» в г. Алматы на «01» января 2026 года
A12: (в том числе интернат )
A15: Виды доплат /согласно внутреннему Положению о системе оплаты труда работников НАО "Республиканская физико-математическая школа" заполнение в строгости с соблюдением наличие подтверждающих документов (диплом. протокол. приказ. удостоверение и иной докумен подтверждающий документ подлежащий оплате)/ строки полежат дополнению в случае необходимости
A16: № п/п | B16: Наименование должностей | C16: ФИО | D16: Количество штатных единиц | E16: Кол-во штатных единиц /по факту cогласно приказа) | F16: коэффициент | G16: Дата приема на работу/ согласно даты указанной в приказе | H16: Коэффициент для исчисления должностного оклада работников | I16: Должностной оклад/ сумма | J16: Доплата 10% за особые условия труда/ сумма | K16: Ученая степень и магистра | L16: Доплата от ДО за квалификационную категорию руковод. (директорам) и зам.руковод. | M16: Доплата от ДО за квалификацию педагогического мастерства учителей, воспитателей и иных педагогических работников | N16: Доплата от БДО за квалификационную категорию учителей, воспитателей и иных педагогических работников | O16: Доплата от БДО за класса квалификацию водителя | P16: Доплата в размере 30% от БДО за работу с библиотечным фондом, за использование дезинф.средств при уборке туалетов работниками | Q16: Доплата в размере 20% от БДО за использование дезинфицирующих средств работниками | R16: Доплата в размере 25% от БДО за особые условия труда работников | S16: Итого доплаты | T16: Всего ФЗП за месяц | U16: ОПВ 10% | V16: ИПН | W16: ВОСМС | X16: Итого на руки | Y16: Всего ФЗП в год | Z16: Лечебно-оздоровительные пособия | AA16: Всего ФЗП с леч пособием | AB16: ОПВР 3.5% | AC16: Социальный налог 6% | AD16: Социальные отчисления 5% | AE16: ОСМС 3% | AF16: ВСЕГО ФОТ | AG16: Вид бюджета
A18: Административно-управленический персонал (АУП)
A19: 1 | B19: Директор | C19: Меирбек Меирлан Едигерулы | D19: 1 | E19: 1 | G19: 45146 | H19: 80 | I19: =H19*17697 -> 1415760 | J19: =I19*10% -> 141576 | S19: =SUM(J19:R19) -> 141576 | T19: =I19+S19 -> 1557336 | U19: =T19*10% -> 155733.6 | V19: =((T19-U19-W19)-(14*4325))*10% -> 130990.57 | W19: =T19*2% -> 31146.72 | X19: =T19-U19-V19-W19 -> 1239465.1 | Y19: =T19*12 -> 18688032 | Z19: =I19*2 -> 2831520 | AA19: =Y19+Z19 -> 21519552 | AB19: =AA19*3.5% -> 753184.32 | AC19: =(AA19*0.9-(W19*12))*11%-AD19 -> 1120942.1 | AD19: =AA19*0.9*5% -> 968379.84 | AE19: =AA19*3% -> 645586.56 | AF19: =AA19+AC19+AD19+AE19+AB19 -> 25007645 | AG19: РБ
A20: =A19+1 -> 2 | B20: Заместитель директора по учебной работе | C20: Кабулова Нурбану Таргиновна | D20: 2 | E20: 1 | G20: 43395 | H20: 32 | I20: =H20*17697 -> 566304 | J20: =I20*10% -> 56630.4 | L20: =I20*50% -> 283152 | S20: =SUM(J20:R20) -> 339782.4 | T20: =I20+S20 -> 906086.4 | U20: =T20*10% -> 90608.64 | V20: =((T20-U20-W20)-(14*4325))*10% -> 73680.603 | W20: =T20*2% -> 18121.728 | X20: =T20-U20-V20-W20 -> 723675.43 | Y20: =T20*12 -> 10873037 | Z20: =I20*2 -> 1132608 | AA20: =Y20+Z20 -> 12005645 | AB20: =AA20*3.5% -> 420197.57 | AC20: =(AA20*0.9-(W20*12))*11%-AD20 -> 624384.14 | AD20: =AA20*0.9*5% -> 540254.02 | AE20: =AA20*3% -> 360169.34 | AF20: =AA20+AC20+AD20+AE20+AB20 -> 13950650 | AG20: РБ
A21: =A20+1 -> 3 | B21: Заместитель директора по учебной работе | C21: Токтасбаев Бейбарыс Ералиевич | E21: 1 | G21: 44907 | H21: 30 | I21: =H21*17697 -> 530910 | J21: =I21*10% -> 53091 | L21: =I21*30% -> 159273 | S21: =SUM(J21:R21) -> 212364 | T21: =I21+S21 -> 743274 | U21: =T21*10% -> 74327.4 | V21: =((T21-U21-W21)-(14*4325))*10% -> 59353.112 | W21: =T21*2% -> 14865.48 | X21: =T21-U21-V21-W21 -> 594728.01 | Y21: =T21*12 -> 8919288 | Z21: =I21*2 -> 1061820 | AA21: =Y21+Z21 -> 9981108 | AB21: =AA21*3.5% -> 349338.78 | AC21: =(AA21*0.9-(W21*12))*11%-AD21 -> 519357.4 | AD21: =AA21*0.9*5% -> 449149.86 | AE21: =AA21*3% -> 299433.24 | AF21: =AA21+AC21+AD21+AE21+AB21 -> 11598387 | AG21: РБ
A22: =A21+1 -> 4 | B22: Заместитель директора по воспитательной работе | C22: Жасыбаева Лазат Карбозовна | D22: 2 | E22: 1 | G22: 44844 | H22: 30 | I22: =H22*17697 -> 530910 | J22: =I22*10% -> 53091 | L22: =I22*30% -> 159273 | S22: =SUM(J22:R22) -> 212364 | T22: =I22+S22 -> 743274 | U22: =T22*10% -> 74327.4 | V22: =((T22-U22-W22)-(14*4325))*10% -> 59353.112 | W22: =T22*2% -> 14865.48 | X22: =T22-U22-V22-W22 -> 594728.01 | Y22: =T22*12 -> 8919288 | Z22: =I22*2 -> 1061820 | AA22: =Y22+Z22 -> 9981108 | AB22: =AA22*3.5% -> 349338.78 | AC22: =(AA22*0.9-(W22*12))*11%-AD22 -> 519357.4 | AD22: =AA22*0.9*5% -> 449149.86 | AE22: =AA22*3% -> 299433.24 | AF22: =AA22+AC22+AD22+AE22+AB22 -> 11598387 | AG22: РБ
A23: =A22+1 -> 5 | B23: Заместитель директора по воспитательной работе | C23: Таукебаев Куаныш Муратбекович | E23: 1 | G23: 44805 | H23: 30 | I23: =H23*17697 -> 530910 | J23: =I23*10% -> 53091 | S23: =SUM(J23:R23) -> 53091 | T23: =I23+S23 -> 584001 | U23: =T23*10% -> 58400.1 | V23: =((T23-U23-W23)-(14*4325))*10% -> 45337.088 | W23: =T23*2% -> 11680.02 | X23: =T23-U23-V23-W23 -> 468583.79 | Y23: =T23*12 -> 7008012 | Z23: =I23*2 -> 1061820 | AA23: =Y23+Z23 -> 8069832 | AB23: =AA23*3.5% -> 282444.12 | AC23: =(AA23*0.9-(W23*12))*11%-AD23 -> 420353.3 | AD23: =AA23*0.9*5% -> 363142.44 | AE23: =AA23*3% -> 242094.96 | AF23: =AA23+AC23+AD23+AE23+AB23 -> 9377866.8 | AG23: РБ
A24: =A23+1 -> 6 | B24: Заместитель директора по профильно- экспериментальной работе | C24: Бегимбетов Талгат Полатович | D24: 1 | E24: 1 | G24: 45216 | H24: 30 | I24: =H24*17697 -> 530910 | J24: =I24*10% -> 53091 | L24: =I24*30% -> 159273 | S24: =SUM(J24:R24) -> 212364 | T24: =I24+S24 -> 743274 | U24: =T24*10% -> 74327.4 | V24: =((T24-U24-W24)-(14*4325))*10% -> 59353.112 | W24: =T24*2% -> 14865.48 | X24: =T24-U24-V24-W24 -> 594728.01 | Y24: =T24*12 -> 8919288 | Z24: =I24*2 -> 1061820 | AA24: =Y24+Z24 -> 9981108 | AB24: =AA24*3.5% -> 349338.78 | AC24: =(AA24*0.9-(W24*12))*11%-AD24 -> 519357.4 | AD24: =AA24*0.9*5% -> 449149.86 | AE24: =AA24*3% -> 299433.24 | AF24: =AA24+AC24+AD24+AE24+AB24 -> 11598387 | AG24: РБ
A25: =A24+1 -> 7 | B25: Заместитель директора по научно-методической работе | C25: Аубакирова Гульнур Габдувна | D25: 1 | E25: 1 | G25: 43355 | H25: 32 | I25: =H25*17697 -> 566304 | J25: =I25*10% -> 56630.4 | L25: =I25*100% -> 566304 | S25: =SUM(J25:R25) -> 622934.4 | T25: =I25+S25 -> 1189238.4 | U25: =T25*10% -> 118923.84 | V25: =((T25-U25-W25)-(14*4325))*10% -> 98597.979 | W25: =T25*2% -> 23784.768 | X25: =T25-U25-V25-W25 -> 947931.81 | Y25: =T25*12 -> 14270861 | Z25: =I25*2 -> 1132608 | AA25: =Y25+Z25 -> 15403469 | AB25: =AA25*3.5% -> 539121.41 | AC25: =(AA25*0.9-(W25*12))*11%-AD25 -> 800391.42 | AD25: =AA25*0.9*5% -> 693156.1 | AE25: =AA25*3% -> 462104.06 | AF25: =AA25+AC25+AD25+AE25+AB25 -> 17898242 | AG25: РБ
B26: ИТОГО АУП пед работники | D26: =SUM(D19:D25) -> 7 | E26: =SUM(E19:E25) -> 7 | F26: =SUM(F19:F25) -> 0 | I26: =SUM(I19:I25) -> 4672008 | J26: =SUM(J19:J25) -> 467200.8 | K26: =SUM(K19:K25) -> 0 | L26: =SUM(L19:L25) -> 1327275 | M26: =SUM(M19:M25) -> 0 | N26: =SUM(N19:N25) -> 0 | O26: =SUM(O19:O25) -> 0 | P26: =SUM(P19:P25) -> 0 | ... AF26: =SUM(AF19:AF25) -> 1.0102957e+08
A27: =A25+1 -> 8 | B27: Заместитель директора по административно-хозяйственной работе | C27: Алин Береке Адильханович | D27: 2 | E27: 1 | G27: 42263 | H27: 35 | I27: =H27*17697 -> 619395 | J27: =I27*10% -> 61939.5 | S27: =SUM(J27:R27) -> 61939.5 | T27: =I27+S27 -> 681334.5 | U27: =T27*10% -> 68133.45 | V27: =((T27-U27-W27)-(14*4325))*10% -> 53902.436 | W27: =T27*2% -> 13626.69 | X27: =T27-U27-V27-W27 -> 545671.92 | Y27: =T27*12 -> 8176014 | Z27: =I27*2 -> 1238790 | AA27: =Y27+Z27 -> 9414804 | AB27: =AA27*3.5% -> 329518.14 | AC27: =(AA27*0.9-(W27*12))*11%-AD27 -> 490412.19 | AD27: =AA27*0.9*5% -> 423666.18 | AE27: =AA27*3% -> 282444.12 | AF27: =AA27+AC27+AD27+AE27+AB27 -> 10940845 | AG27: РБ
A28: =A27+1 -> 9 | B28: Заведующий по хозяйственной работе | C28: Камбарбаев Айдын Майсаканович | E28: 1 | G28: 44106 | H28: 24 | I28: =H28*17697 -> 424728 | J28: =I28*10% -> 42472.8 | S28: =SUM(J28:R28) -> 42472.8 | T28: =I28+S28 -> 467200.8 | U28: =T28*10% -> 46720.08 | V28: =((T28-U28-W28)-(14*4325))*10% -> 35058.67 | W28: =T28*2% -> 9344.016 | X28: =T28-U28-V28-W28 -> 376078.03 | Y28: =T28*12 -> 5606409.6 | Z28: =I28*2 -> 849456 | AA28: =Y28+Z28 -> 6455865.6 | AB28: =AA28*3.5% -> 225955.3 | AC28: =(AA28*0.9-(W28*12))*11%-AD28 -> 336282.64 | AD28: =AA28*0.9*5% -> 290513.95 | AE28: =AA28*3% -> 193675.97 | AF28: =AA28+AC28+AD28+AE28+AB28 -> 7502293.5 | AG28: РБ
A29: =A28+1 -> 10 | B29: Экономист | C29: Куюкова Гаухар Ермековна | D29: 1 | E29: 1 | G29: 44853 | H29: 30 | I29: =H29*17697 -> 530910 | J29: =I29*10% -> 53091 | S29: =SUM(J29:R29) -> 53091 | T29: =I29+S29 -> 584001 | U29: =T29*10% -> 58400.1 | V29: =((T29-U29-W29)-(14*4325))*10% -> 45337.088 | W29: =T29*2% -> 11680.02 | X29: =T29-U29-V29-W29 -> 468583.79 | Y29: =T29*12 -> 7008012 | Z29: =I29*2 -> 1061820 | AA29: =Y29+Z29 -> 8069832 | AB29: =AA29*3.5% -> 282444.12 | AC29: =(AA29*0.9-(W29*12))*11%-AD29 -> 420353.3 | AD29: =AA29*0.9*5% -> 363142.44 | AE29: =AA29*3% -> 242094.96 | AF29: =AA29+AC29+AD29+AE29+AB29 -> 9377866.8 | AG29: РБ
A30: =A29+1 -> 11 | B30: Главный бухгалтер | C30: Абулова Жулдыз Муратовна | D30: 1 | E30: 1 | G30: 43710 | H30: 35 | I30: =H30*17697 -> 619395 | J30: =I30*10% -> 61939.5 | S30: =SUM(J30:R30) -> 61939.5 | T30: =I30+S30 -> 681334.5 | U30: =T30*10% -> 68133.45 | V30: =((T30-U30-W30)-(14*4325))*10% -> 53902.436 | W30: =T30*2% -> 13626.69 | X30: =T30-U30-V30-W30 -> 545671.92 | Y30: =T30*12 -> 8176014 | Z30: =I30*2 -> 1238790 | AA30: =Y30+Z30 -> 9414804 | AB30: =AA30*3.5% -> 329518.14 | AC30: =(AA30*0.9-(W30*12))*11%-AD30 -> 490412.19 | AD30: =AA30*0.9*5% -> 423666.18 | AE30: =AA30*3% -> 282444.12 | AF30: =AA30+AC30+AD30+AE30+AB30 -> 10940845 | AG30: РБ
A31: =A30+1 -> 12 | B31: Старший бухгалтер | C31: Қожамқұлова Жанна Пірмағанбетқызы | D31: 1 | E31: 1 | G31: 44105 | H31: 30 | I31: =H31*17697 -> 530910 | J31: =I31*10% -> 53091 | S31: =SUM(J31:R31) -> 53091 | T31: =I31+S31 -> 584001 | U31: =T31*10% -> 58400.1 | V31: =((T31-U31-W31)-(14*4325))*10% -> 45337.088 | W31: =T31*2% -> 11680.02 | X31: =T31-U31-V31-W31 -> 468583.79 | Y31: =T31*12 -> 7008012 | Z31: =I31*2 -> 1061820 | AA31: =Y31+Z31 -> 8069832 | AB31: =AA31*3.5% -> 282444.12 | AC31: =(AA31*0.9-(W31*12))*11%-AD31 -> 420353.3 | AD31: =AA31*0.9*5% -> 363142.44 | AE31: =AA31*3% -> 242094.96 | AF31: =AA31+AC31+AD31+AE31+AB31 -> 9377866.8 | AG31: РБ
A32: =A31+1 -> 13 | B32: Бухгалтер | C32: Сабирова Гулжан Саухановна | D32: 2 | E32: 1 | G32: 44939 | H32: 23 | I32: =H32*17697 -> 407031 | J32: =I32*10% -> 40703.1 | S32: =SUM(J32:R32) -> 40703.1 | T32: =I32+S32 -> 447734.1 | U32: =T32*10% -> 44773.41 | V32: =((T32-U32-W32)-(14*4325))*10% -> 33345.601 | W32: =T32*2% -> 8954.682 | X32: =T32-U32-V32-W32 -> 360660.41 | Y32: =T32*12 -> 5372809.2 | Z32: =I32*2 -> 814062 | AA32: =Y32+Z32 -> 6186871.2 | AB32: =AA32*3.5% -> 216540.49 | AC32: =(AA32*0.9-(W32*12))*11%-AD32 -> 322270.86 | AD32: =AA32*0.9*5% -> 278409.2 | AE32: =AA32*3% -> 185606.14 | AF32: =AA32+AC32+AD32+AE32+AB32 -> 7189697.9 | AG32: РБ
A33: =A32+1 -> 14 | B33: Бухгалтер | C33: Каныбетова Балжан Сериковна | E33: 1 | G33: 41860 | H33: 23 | I33: =H33*17697 -> 407031 | J33: =I33*10% -> 40703.1 | S33: =SUM(J33:R33) -> 40703.1 | T33: =I33+S33 -> 447734.1 | U33: =T33*10% -> 44773.41 | V33: =((T33-U33-W33)-(14*4325))*10% -> 33345.601 | W33: =T33*2% -> 8954.682 | X33: =T33-U33-V33-W33 -> 360660.41 | Y33: =T33*12 -> 5372809.2 | Z33: =I33*2 -> 814062 | AA33: =Y33+Z33 -> 6186871.2 | AB33: =AA33*3.5% -> 216540.49 | AC33: =(AA33*0.9-(W33*12))*11%-AD33 -> 322270.86 | AD33: =AA33*0.9*5% -> 278409.2 | AE33: =AA33*3% -> 185606.14 | AF33: =AA33+AC33+AD33+AE33+AB33 -> 7189697.9 | AG33: РБ
A34: =A33+1 -> 15 | B34: Специалист по закупкам | C34: Жанабилов Жандос Ерболатович | D34: 1 | E34: 1 | G34: 45019 | H34: 28 | I34: =H34*17697 -> 495516 | J34: =I34*10% -> 49551.6 | S34: =SUM(J34:R34) -> 49551.6 | T34: =I34+S34 -> 545067.6 | U34: =T34*10% -> 54506.76 | V34: =((T34-U34-W34)-(14*4325))*10% -> 41910.949 | W34: =T34*2% -> 10901.352 | X34: =T34-U34-V34-W34 -> 437748.54 | Y34: =T34*12 -> 6540811.2 | Z34: =I34*2 -> 991032 | AA34: =Y34+Z34 -> 7531843.2 | AB34: =AA34*3.5% -> 263614.51 | AC34: =(AA34*0.9-(W34*12))*11%-AD34 -> 392329.75 | AD34: =AA34*0.9*5% -> 338932.94 | AE34: =AA34*3% -> 225955.3 | AF34: =AA34+AC34+AD34+AE34+AB34 -> 8752675.7 | AG34: РБ
A35: =A34+1 -> 16 | B35: Юрист | C35: Токсеитова Гульмира Назымбековна | D35: 1 | E35: 1 | G35: 45232 | H35: 28 | I35: =H35*17697 -> 495516 | J35: =I35*10% -> 49551.6 | S35: =SUM(J35:R35) -> 49551.6 | T35: =I35+S35 -> 545067.6 | U35: =T35*10% -> 54506.76 | V35: =((T35-U35-W35)-(14*4325))*10% -> 41910.949 | W35: =T35*2% -> 10901.352 | X35: =T35-U35-V35-W35 -> 437748.54 | Y35: =T35*12 -> 6540811.2 | Z35: =I35*2 -> 991032 | AA35: =Y35+Z35 -> 7531843.2 | AB35: =AA35*3.5% -> 263614.51 | AC35: =(AA35*0.9-(W35*12))*11%-AD35 -> 392329.75 | AD35: =AA35*0.9*5% -> 338932.94 | AE35: =AA35*3% -> 225955.3 | AF35: =AA35+AC35+AD35+AE35+AB35 -> 8752675.7 | AG35: РБ
A36: =A35+1 -> 17 | B36: Инспектор по кадрам | C36: Асылова Куралай Мухаметкалиевна | D36: 1 | E36: 1 | G36: 42980 | H36: 25 | I36: =H36*17697 -> 442425 | J36: =I36*10% -> 44242.5 | S36: =SUM(J36:R36) -> 44242.5 | T36: =I36+S36 -> 486667.5 | U36: =T36*10% -> 48666.75 | V36: =((T36-U36-W36)-(14*4325))*10% -> 36771.74 | W36: =T36*2% -> 9733.35 | X36: =T36-U36-V36-W36 -> 391495.66 | Y36: =T36*12 -> 5840010 | Z36: =I36*2 -> 884850 | AA36: =Y36+Z36 -> 6724860 | AB36: =AA36*3.5% -> 235370.1 | AC36: =(AA36*0.9-(W36*12))*11%-AD36 -> 350294.42 | AD36: =AA36*0.9*5% -> 302618.7 | AE36: =AA36*3% -> 201745.8 | AF36: =AA36+AC36+AD36+AE36+AB36 -> 7814889 | AG36: РБ
A37: =A36+1 -> 18 | B37: Секретарь | C37: Жупбаева Жулдуз Ибраимовна | D37: 1 | E37: 1 | G37: 44305 | H37: 22 | I37: =H37*17697 -> 389334 | J37: =I37*10% -> 38933.4 | S37: =SUM(J37:R37) -> 38933.4 | T37: =I37+S37 -> 428267.4 | U37: =T37*10% -> 42826.74 | V37: =((T37-U37-W37)-(14*4325))*10% -> 31632.531 | W37: =T37*2% -> 8565.348 | X37: =T37-U37-V37-W37 -> 345242.78 | Y37: =T37*12 -> 5139208.8 | Z37: =I37*2 -> 778668 | AA37: =Y37+Z37 -> 5917876.8 | AB37: =AA37*3.5% -> 207125.69 | AC37: =(AA37*0.9-(W37*12))*11%-AD37 -> 308259.09 | AD37: =AA37*0.9*5% -> 266304.46 | AE37: =AA37*3% -> 177536.3 | AF37: =AA37+AC37+AD37+AE37+AB37 -> 6877102.3 | AG37: РБ
A38: =A37+1 -> 19 | B38: Архивариус | C38: Ермеккалиева Тлектес Сансизбаевна | D38: 1 | E38: 1 | G38: 42888 | H38: 13 | I38: =H38*17697 -> 230061 | J38: =I38*10% -> 23006.1 | S38: =SUM(J38:R38) -> 23006.1 | T38: =I38+S38 -> 253067.1 | U38: =T38*10% -> 25306.71 | V38: =((T38-U38-W38)-(14*4325))*10% -> 16214.905 | W38: =T38*2% -> 5061.342 | X38: =T38-U38-V38-W38 -> 206484.14 | Y38: =T38*12 -> 3036805.2 | Z38: =I38*2 -> 460122 | AA38: =Y38+Z38 -> 3496927.2 | AB38: =AA38*3.5% -> 122392.45 | AC38: =(AA38*0.9-(W38*12))*11%-AD38 -> 182153.1 | AD38: =AA38*0.9*5% -> 157361.72 | AE38: =AA38*3% -> 104907.82 | AF38: =AA38+AC38+AD38+AE38+AB38 -> 4063742.3 | AG38: РБ
B39: ИТОГО АУП без пед .работников | D39: =SUM(D27:D38) -> 12 | E39: =SUM(E27:E38) -> 12 | I39: =SUM(I27:I38) -> 5592252 | J39: =SUM(J27:J38) -> 559225.2 | K39: =SUM(K27:K38) -> 0 | L39: =SUM(L27:L38) -> 0 | M39: =SUM(M27:M38) -> 0 | N39: =SUM(N27:N38) -> 0 | O39: =SUM(O27:O38) -> 0 | P39: =SUM(P27:P38) -> 0 | ... AF39: =SUM(AF27:AF38) -> 98780197
B40: ВСЕГО по АУП | D40: =D26+D39 -> 19 | E40: =E26+E39 -> 19 | I40: =I26+I39 -> 10264260 | J40: =J26+J39 -> 1026426 | K40: =K26+K39 -> 0 | L40: =L26+L39 -> 1327275 | M40: =M26+M39 -> 0 | N40: =N26+N39 -> 0 | O40: =O26+O39 -> 0 | P40: =P26+P39 -> 0 | ... AF40: =AF26+AF39 -> 1.9980976e+08
A41: Учебно-вспомогательный персонал (УВП)
A42: =A38+1 -> 20 | B42: Консультант по профессиональной ориентации | C42: Амангельдина Айгерім Санатқызы | D42: 4 | E42: 1 | F42: 17697 | G42: 45902 | H42: 32 | I42: =E42*17697*H42 -> 566304 | J42: =I42*10% -> 56630.4 | S42: =SUM(J42:R42) -> 56630.4 | T42: =I42+S42 -> 622934.4 | U42: =T42*10% -> 62293.44 | V42: =((T42-U42-W42)-(14*4325))*10% -> 48763.227 | W42: =T42*2% -> 12458.688 | X42: =T42-U42-V42-W42 -> 499419.04 | Y42: =T42*12 -> 7475212.8 | Z42: =I42*2 -> 1132608 | AA42: =Y42+Z42 -> 8607820.8 | AB42: =AA42*3.5% -> 301273.73 | AC42: =(AA42*0.9-(W42*12))*11%-AD42 -> 448376.86 | AD42: =AA42*0.9*5% -> 387351.94 | AE42: =AA42*3% -> 258234.62 | AF42: =AA42+AC42+AD42+AE42+AB42 -> 10003058 | AG42: РБ
A43: =A42+1 -> 21 | B43: Консультант по профессиональной ориентации | C43: Вакансия-1 | F43: 17697 | G43: 45300 | H43: 70 | I43: =17697*H43 -> 1238790 | J43: =I43*10% -> 123879 | S43: =SUM(J43:R43) -> 123879 | T43: =I43+S43 -> 1362669 | U43: =T43*10% -> 136266.9 | V43: =((T43-U43-W43)-(14*4325))*10% -> 113859.87 | W43: =T43*2% -> 27253.38 | X43: =T43-U43-V43-W43 -> 1085288.8 | Y43: =T43*12 -> 16352028 | Z43: =I43*2 -> 2477580 | AA43: =Y43+Z43 -> 18829608 | AB43: =AA43*3.5% -> 659036.28 | AC43: =(AA43*0.9-(W43*12))*11%-AD43 -> 980824.37 | AD43: =AA43*0.9*5% -> 847332.36 | AE43: =AA43*3% -> 564888.24 | AF43: =AA43+AC43+AD43+AE43+AB43 -> 21881689 | AG43: РБ
A44: =A43+1 -> 22 | B44: Консультант по профессиональной ориентации | C44: Мақашева Нұрила Болатқызы | E44: 1 | F44: 17697 | G44: 45902 | H44: 32 | I44: =17697*H44 -> 566304 | J44: =I44*10% -> 56630.4 | S44: =SUM(J44:R44) -> 56630.4 | T44: =I44+S44 -> 622934.4 | U44: =T44*10% -> 62293.44 | V44: =((T44-U44-W44)-(14*4325))*10% -> 48763.227 | W44: =T44*2% -> 12458.688 | X44: =T44-U44-V44-W44 -> 499419.04 | Y44: =T44*12 -> 7475212.8 | Z44: =I44*2 -> 1132608 | AA44: =Y44+Z44 -> 8607820.8 | AB44: =AA44*3.5% -> 301273.73 | AC44: =(AA44*0.9-(W44*12))*11%-AD44 -> 448376.86 | AD44: =AA44*0.9*5% -> 387351.94 | AE44: =AA44*3% -> 258234.62 | AF44: =AA44+AC44+AD44+AE44+AB44 -> 10003058 | AG44: РБ
A45: =A44+1 -> 23 | B45: Консультант по профессиональной ориентации | C45: Муратова Алина Кабыловна | E45: 1 | F45: 17697 | G45: 45902 | H45: 27 | I45: =17697*H45 -> 477819 | J45: =I45*10% -> 47781.9 | S45: =SUM(J45:R45) -> 47781.9 | T45: =I45+S45 -> 525600.9 | U45: =T45*10% -> 52560.09 | V45: =((T45-U45-W45)-(14*4325))*10% -> 40197.879 | W45: =T45*2% -> 10512.018 | X45: =T45-U45-V45-W45 -> 422330.91 | Y45: =T45*12 -> 6307210.8 | Z45: =I45*2 -> 955638 | AA45: =Y45+Z45 -> 7262848.8 | AB45: =AA45*3.5% -> 254199.71 | AC45: =(AA45*0.9-(W45*12))*11%-AD45 -> 378317.97 | AD45: =AA45*0.9*5% -> 326828.2 | AE45: =AA45*3% -> 217885.46 | AF45: =AA45+AC45+AD45+AE45+AB45 -> 8440080.1 | AG45: РБ
A46: =A45+1 -> 24 | B46: Менеджер УР | C46: Ахметова Алия Нуртаевна | D46: 6 | E46: 1 | F46: 17697 | G46: 43078 | H46: 22 | I46: =E46*17697*H46 -> 389334 | J46: =I46*10% -> 38933.4 | S46: =SUM(J46:R46) -> 38933.4 | T46: =I46+S46 -> 428267.4 | U46: =T46*10% -> 42826.74 | V46: =((T46-U46-W46)-(14*4325))*10% -> 31632.531 | W46: =T46*2% -> 8565.348 | X46: =T46-U46-V46-W46 -> 345242.78 | Y46: =T46*12 -> 5139208.8 | Z46: =I46*2 -> 778668 | AA46: =Y46+Z46 -> 5917876.8 | AB46: =AA46*3.5% -> 207125.69 | AC46: =(AA46*0.9-(W46*12))*11%-AD46 -> 308259.09 | AD46: =AA46*0.9*5% -> 266304.46 | AE46: =AA46*3% -> 177536.3 | AF46: =AA46+AC46+AD46+AE46+AB46 -> 6877102.3 | AG46: РБ
A47: =A46+1 -> 25 | B47: Менеджер УР | C47: Абдыкаримова Акерке Маратовна | E47: 1 | F47: 17697 | G47: 45891 | H47: 17 | I47: =E47*17697*H47 -> 300849 | J47: =I47*10% -> 30084.9 | S47: =SUM(J47:R47) -> 30084.9 | T47: =I47+S47 -> 330933.9 | U47: =T47*10% -> 33093.39 | V47: =((T47-U47-W47)-(14*4325))*10% -> 23067.183 | W47: =T47*2% -> 6618.678 | X47: =T47-U47-V47-W47 -> 268154.65 | Y47: =T47*12 -> 3971206.8 | Z47: =I47*2 -> 601698 | AA47: =Y47+Z47 -> 4572904.8 | AB47: =AA47*3.5% -> 160051.67 | AC47: =(AA47*0.9-(W47*12))*11%-AD47 -> 238200.2 | AD47: =AA47*0.9*5% -> 205780.72 | AE47: =AA47*3% -> 137187.14 | AF47: =AA47+AC47+AD47+AE47+AB47 -> 5314124.5 | AG47: РБ
A48: =A47+1 -> 26 | B48: Менеджер УР | C48: Нусибақын Аружан Ерболқызы | E48: 1 | F48: 17697 | G48: 45904 | H48: 17 | I48: =E48*17697*H48 -> 300849 | J48: =I48*10% -> 30084.9 | S48: =SUM(J48:R48) -> 30084.9 | T48: =I48+S48 -> 330933.9 | U48: =T48*10% -> 33093.39 | V48: =((T48-U48-W48)-(14*4325))*10% -> 23067.183 | W48: =T48*2% -> 6618.678 | X48: =T48-U48-V48-W48 -> 268154.65 | Y48: =T48*12 -> 3971206.8 | Z48: =I48*2 -> 601698 | AA48: =Y48+Z48 -> 4572904.8 | AB48: =AA48*3.5% -> 160051.67 | AC48: =(AA48*0.9-(W48*12))*11%-AD48 -> 238200.2 | AD48: =AA48*0.9*5% -> 205780.72 | AE48: =AA48*3% -> 137187.14 | AF48: =AA48+AC48+AD48+AE48+AB48 -> 5314124.5 | AG48: РБ
A49: =A48+1 -> 27 | B49: Менеджер УР | C49: Вакансия-2 | F49: 17697 | H49: 35 | I49: =2*17697*H49 -> 1238790 | J49: =I49*10% -> 123879 | S49: =SUM(J49:R49) -> 123879 | T49: =I49+S49 -> 1362669 | U49: =T49*10% -> 136266.9 | V49: =((T49-U49-W49)-(14*4325))*10% -> 113859.87 | W49: =T49*2% -> 27253.38 | X49: =T49-U49-V49-W49 -> 1085288.8 | Y49: =T49*12 -> 16352028 | Z49: =I49*2 -> 2477580 | AA49: =Y49+Z49 -> 18829608 | AB49: =AA49*3.5% -> 659036.28 | AC49: =(AA49*0.9-(W49*12))*11%-AD49+5000000 -> 5980824.4 | AD49: =AA49*0.9*5% -> 847332.36 | AE49: =AA49*3% -> 564888.24 | AF49: =AA49+AC49+AD49+AE49+AB49 -> 26881689 | AG49: РБ
A50: =A49+1 -> 28 | B50: Менеджер ВР | C50: Вакансия-1 | F50: 17697 | H50: 35 | I50: =17697*H50 -> 619395 | J50: =I50*10% -> 61939.5 | S50: =SUM(J50:R50) -> 61939.5 | T50: =I50+S50 -> 681334.5 | U50: =T50*10% -> 68133.45 | V50: =((T50-U50-W50)-(14*4325))*10% -> 53902.436 | W50: =T50*2% -> 13626.69 | X50: =T50-U50-V50-W50 -> 545671.92 | Y50: =T50*12 -> 8176014 | Z50: =I50*2 -> 1238790 | AA50: =Y50+Z50 -> 9414804 | AB50: =AA50*3.5% -> 329518.14 | AC50: =(AA50*0.9-(W50*12))*11%-AD50+5000000 -> 5490412.2 | AD50: =AA50*0.9*5% -> 423666.18 | AE50: =AA50*3% -> 282444.12 | AF50: =AA50+AC50+AD50+AE50+AB50 -> 15940845 | AG50: РБ
A51: =A50+1 -> 29 | B51: Педагог-организатор-куратор | C51: Асадилла Әсем Талғатқызы | D51: 9 | E51: 1 | F51: 17697 | G51: 45519 | H51: 20 | I51: =E51*17697*H51 -> 353940 | J51: =I51*10% -> 35394 | S51: =SUM(J51:R51) -> 35394 | T51: =I51+S51 -> 389334 | U51: =T51*10% -> 38933.4 | V51: =((T51-U51-W51)-(14*4325))*10% -> 28206.392 | W51: =T51*2% -> 7786.68 | X51: =T51-U51-V51-W51 -> 314407.53 | Y51: =T51*12 -> 4672008 | Z51: =I51*2 -> 707880 | AA51: =Y51+Z51 -> 5379888 | AB51: =AA51*3.5% -> 188296.08 | AC51: =(AA51*0.9-(W51*12))*11%-AD51 -> 280235.53 | AD51: =AA51*0.9*5% -> 242094.96 | AE51: =AA51*3% -> 161396.64 | AF51: =AA51+AC51+AD51+AE51+AB51 -> 6251911.2 | AG51: РБ
A52: =A51+1 -> 30 | B52: Педагог-организатор-куратор | C52: Жәнәбіл Айжан Нышанбайқызы | E52: 1 | F52: 17697 | G52: 45170 | H52: 20 | I52: =E52*17697*H52 -> 353940 | J52: =I52*10% -> 35394 | S52: =SUM(J52:R52) -> 35394 | T52: =I52+S52 -> 389334 | U52: =T52*10% -> 38933.4 | V52: =((T52-U52-W52)-(14*4325))*10% -> 28206.392 | W52: =T52*2% -> 7786.68 | X52: =T52-U52-V52-W52 -> 314407.53 | Y52: =T52*12 -> 4672008 | Z52: =I52*2 -> 707880 | AA52: =Y52+Z52 -> 5379888 | AB52: =AA52*3.5% -> 188296.08 | AC52: =(AA52*0.9-(W52*12))*11%-AD52 -> 280235.53 | AD52: =AA52*0.9*5% -> 242094.96 | AE52: =AA52*3% -> 161396.64 | AF52: =AA52+AC52+AD52+AE52+AB52 -> 6251911.2 | AG52: РБ
A53: =A52+1 -> 31 | B53: Педагог-организатор-куратор | C53: Маханбет Ақмоншақ Қайратқызы | E53: 1 | F53: 17697 | G53: 45237 | H53: 20 | I53: =E53*17697*H53 -> 353940 | J53: =I53*10% -> 35394 | S53: =SUM(J53:R53) -> 35394 | T53: =I53+S53 -> 389334 | U53: =T53*10% -> 38933.4 | V53: =((T53-U53-W53)-(14*4325))*10% -> 28206.392 | W53: =T53*2% -> 7786.68 | X53: =T53-U53-V53-W53 -> 314407.53 | Y53: =T53*12 -> 4672008 | Z53: =I53*2 -> 707880 | AA53: =Y53+Z53 -> 5379888 | AB53: =AA53*3.5% -> 188296.08 | AC53: =(AA53*0.9-(W53*12))*11%-AD53 -> 280235.53 | AD53: =AA53*0.9*5% -> 242094.96 | AE53: =AA53*3% -> 161396.64 | AF53: =AA53+AC53+AD53+AE53+AB53 -> 6251911.2 | AG53: РБ
A54: =A53+1 -> 32 | B54: Педагог-организатор-куратор | C54: Нурымова Шолпан Искандировна | E54: 1 | F54: 17697 | G54: 42264 | H54: 22 | I54: =E54*17697*H54 -> 389334 | J54: =I54*10% -> 38933.4 | S54: =SUM(J54:R54) -> 38933.4 | T54: =I54+S54 -> 428267.4 | U54: =T54*10% -> 42826.74 | V54: =((T54-U54-W54)-(14*4325))*10% -> 31632.531 | W54: =T54*2% -> 8565.348 | X54: =T54-U54-V54-W54 -> 345242.78 | Y54: =T54*12 -> 5139208.8 | Z54: =I54*2 -> 778668 | AA54: =Y54+Z54 -> 5917876.8 | AB54: =AA54*3.5% -> 207125.69 | AC54: =(AA54*0.9-(W54*12))*11%-AD54 -> 308259.09 | AD54: =AA54*0.9*5% -> 266304.46 | AE54: =AA54*3% -> 177536.3 | AF54: =AA54+AC54+AD54+AE54+AB54 -> 6877102.3 | AG54: РБ
A55: =A54+1 -> 33 | B55: Педагог-организатор-куратор | C55: Нусипкожаева Диляра Касымхановна | E55: 1 | F55: 17697 | G55: 45540 | H55: 20 | I55: =E55*17697*H55 -> 353940 | J55: =I55*10% -> 35394 | S55: =SUM(J55:R55) -> 35394 | T55: =I55+S55 -> 389334 | U55: =T55*10% -> 38933.4 | V55: =((T55-U55-W55)-(14*4325))*10% -> 28206.392 | W55: =T55*2% -> 7786.68 | X55: =T55-U55-V55-W55 -> 314407.53 | Y55: =T55*12 -> 4672008 | Z55: =I55*2 -> 707880 | AA55: =Y55+Z55 -> 5379888 | AB55: =AA55*3.5% -> 188296.08 | AC55: =(AA55*0.9-(W55*12))*11%-AD55 -> 280235.53 | AD55: =AA55*0.9*5% -> 242094.96 | AE55: =AA55*3% -> 161396.64 | AF55: =AA55+AC55+AD55+AE55+AB55 -> 6251911.2 | AG55: РБ
A56: =A55+1 -> 34 | B56: Педагог-организатор-куратор | C56: Оралбаева Ардак Бектасовна | E56: 1 | F56: 17697 | G56: 45537 | H56: 20 | I56: =E56*17697*H56 -> 353940 | J56: =I56*10% -> 35394 | S56: =SUM(J56:R56) -> 35394 | T56: =I56+S56 -> 389334 | U56: =T56*10% -> 38933.4 | V56: =((T56-U56-W56)-(14*4325))*10% -> 28206.392 | W56: =T56*2% -> 7786.68 | X56: =T56-U56-V56-W56 -> 314407.53 | Y56: =T56*12 -> 4672008 | Z56: =I56*2 -> 707880 | AA56: =Y56+Z56 -> 5379888 | AB56: =AA56*3.5% -> 188296.08 | AC56: =(AA56*0.9-(W56*12))*11%-AD56 -> 280235.53 | AD56: =AA56*0.9*5% -> 242094.96 | AE56: =AA56*3% -> 161396.64 | AF56: =AA56+AC56+AD56+AE56+AB56 -> 6251911.2 | AG56: РБ
A57: =A56+1 -> 35 | B57: Педагог-организатор-куратор | C57: Сайлауханқызы Зарина | E57: 1 | F57: 17697 | G57: 40788 | H57: 22 | I57: =E57*17697*H57 -> 389334 | J57: =I57*10% -> 38933.4 | S57: =SUM(J57:R57) -> 38933.4 | T57: =I57+S57 -> 428267.4 | U57: =T57*10% -> 42826.74 | V57: =((T57-U57-W57)-(14*4325))*10% -> 31632.531 | W57: =T57*2% -> 8565.348 | X57: =T57-U57-V57-W57 -> 345242.78 | Y57: =T57*12 -> 5139208.8 | Z57: =I57*2 -> 778668 | AA57: =Y57+Z57 -> 5917876.8 | AB57: =AA57*3.5% -> 207125.69 | AC57: =(AA57*0.9-(W57*12))*11%-AD57 -> 308259.09 | AD57: =AA57*0.9*5% -> 266304.46 | AE57: =AA57*3% -> 177536.3 | AF57: =AA57+AC57+AD57+AE57+AB57 -> 6877102.3 | AG57: РБ
A58: =A57+1 -> 36 | B58: Педагог-организатор-куратор | C58: Вакансия -2 | E58: 2 | F58: 17697 | H58: 35 | I58: =2*17697*H58 -> 1238790 | J58: =I58*10% -> 123879 | S58: =SUM(J58:R58) -> 123879 | T58: =I58+S58 -> 1362669 | U58: =T58*10% -> 136266.9 | V58: =((T58-U58-W58)-(14*4325))*10% -> 113859.87 | W58: =T58*2% -> 27253.38 | X58: =T58-U58-V58-W58 -> 1085288.8 | Y58: =T58*12 -> 16352028 | Z58: =I58*2 -> 2477580 | AA58: =Y58+Z58 -> 18829608 | AB58: =AA58*3.5% -> 659036.28 | AC58: =(AA58*0.9-(W58*12))*11%-AD58+8552148.25 -> 9532972.6 | AD58: =AA58*0.9*5% -> 847332.36 | AE58: =AA58*3% -> 564888.24 | AF58: =AA58+AC58+AD58+AE58+AB58 -> 30433838 | AG58: РБ
A59: =A58+1 -> 37 | B59: Педагог дополнительного образования | C59: Адилов Шерзод Рустамович | D59: 11 | E59: 0.25 | F59: 17697 | G59: 45901 | H59: 40 | I59: =E59*17697*H59 -> 176970 | J59: =I59*10% -> 17697 | S59: =SUM(J59:R59) -> 17697 | T59: =I59+S59 -> 194667 | U59: =T59*10% -> 19466.7 | V59: =((T59-U59-W59)-(14*4325))*10% -> 11075.696 | W59: =T59*2% -> 3893.34 | X59: =T59-U59-V59-W59 -> 160231.26 | Y59: =T59*12 -> 2336004 | Z59: =I59*2 -> 353940 | AA59: =Y59+Z59 -> 2689944 | AB59: =AA59*3.5% -> 94148.04 | AC59: =(AA59*0.9-(W59*12))*11%-AD59 -> 140117.77 | AD59: =AA59*0.9*5% -> 121047.48 | AE59: =AA59*3% -> 80698.32 | AF59: =AA59+AC59+AD59+AE59+AB59 -> 3125955.6 | AG59: РБ
A60: =A59+1 -> 38 | B60: Педагог дополнительного образования | C60: Ақан Дәулет Ардақұлы | E60: 0.25 | F60: 17697 | G60: 45902 | H60: 40 | I60: =E60*17697*H60 -> 176970 | J60: =I60*10% -> 17697 | S60: =SUM(J60:R60) -> 17697 | T60: =I60+S60 -> 194667 | U60: =T60*10% -> 19466.7 | V60: =((T60-U60-W60)-(14*4325))*10% -> 11075.696 | W60: =T60*2% -> 3893.34 | X60: =T60-U60-V60-W60 -> 160231.26 | Y60: =T60*12 -> 2336004 | Z60: =I60*2 -> 353940 | AA60: =Y60+Z60 -> 2689944 | AB60: =AA60*3.5% -> 94148.04 | AC60: =(AA60*0.9-(W60*12))*11%-AD60 -> 140117.77 | AD60: =AA60*0.9*5% -> 121047.48 | AE60: =AA60*3% -> 80698.32 | AF60: =AA60+AC60+AD60+AE60+AB60 -> 3125955.6 | AG60: РБ
A61: =A60+1 -> 39 | B61: Педагог дополнительного образования | C61: Амантай Баянбек | E61: 0.5 | F61: 17697 | G61: 45901 | H61: 40 | I61: =E61*17697*H61 -> 353940 | J61: =I61*10% -> 35394 | S61: =SUM(J61:R61) -> 35394 | T61: =I61+S61 -> 389334 | U61: =T61*10% -> 38933.4 | V61: =((T61-U61-W61)-(14*4325))*10% -> 28206.392 | W61: =T61*2% -> 7786.68 | X61: =T61-U61-V61-W61 -> 314407.53 | Y61: =T61*12 -> 4672008 | Z61: =I61*2 -> 707880 | AA61: =Y61+Z61 -> 5379888 | AB61: =AA61*3.5% -> 188296.08 | AC61: =(AA61*0.9-(W61*12))*11%-AD61 -> 280235.53 | AD61: =AA61*0.9*5% -> 242094.96 | AE61: =AA61*3% -> 161396.64 | AF61: =AA61+AC61+AD61+AE61+AB61 -> 6251911.2 | AG61: РБ
A62: =A61+1 -> 40 | B62: Педагог дополнительного образования | C62: Бегимбетов Талгат Полатович | E62: 0.25 | F62: 17697 | G62: 45901 | H62: 40 | I62: =E62*17697*H62 -> 176970 | J62: =I62*10% -> 17697 | S62: =SUM(J62:R62) -> 17697 | T62: =I62+S62 -> 194667 | U62: =T62*10% -> 19466.7 | V62: =((T62-U62-W62)-(14*4325))*10% -> 11075.696 | W62: =T62*2% -> 3893.34 | X62: =T62-U62-V62-W62 -> 160231.26 | Y62: =T62*12 -> 2336004 | Z62: =I62*2 -> 353940 | AA62: =Y62+Z62 -> 2689944 | AB62: =AA62*3.5% -> 94148.04 | AC62: =(AA62*0.9-(W62*12))*11%-AD62 -> 140117.77 | AD62: =AA62*0.9*5% -> 121047.48 | AE62: =AA62*3% -> 80698.32 | AF62: =AA62+AC62+AD62+AE62+AB62 -> 3125955.6 | AG62: РБ
A63: =A62+1 -> 41 | B63: Педагог дополнительного образования | C63: Гуламов Бахтияр Нишантаевич | E63: 0.25 | F63: 17697 | G63: 45902 | H63: 40 | I63: =E63*17697*H63 -> 176970 | J63: =I63*10% -> 17697 | S63: =SUM(J63:R63) -> 17697 | T63: =I63+S63 -> 194667 | U63: =T63*10% -> 19466.7 | V63: =((T63-U63-W63)-(14*4325))*10% -> 11075.696 | W63: =T63*2% -> 3893.34 | X63: =T63-U63-V63-W63 -> 160231.26 | Y63: =T63*12 -> 2336004 | Z63: =I63*2 -> 353940 | AA63: =Y63+Z63 -> 2689944 | AB63: =AA63*3.5% -> 94148.04 | AC63: =(AA63*0.9-(W63*12))*11%-AD63 -> 140117.77 | AD63: =AA63*0.9*5% -> 121047.48 | AE63: =AA63*3% -> 80698.32 | AF63: =AA63+AC63+AD63+AE63+AB63 -> 3125955.6 | AG63: РБ
A64: =A63+1 -> 42 | B64: Педагог дополнительного образования | C64: Джумабекова Қасиет Айдарқызы | E64: 0.25 | F64: 17697 | G64: 45901 | H64: 40 | I64: =E64*17697*H64 -> 176970 | J64: =I64*10% -> 17697 | S64: =SUM(J64:R64) -> 17697 | T64: =I64+S64 -> 194667 | U64: =T64*10% -> 19466.7 | V64: =((T64-U64-W64)-(14*4325))*10% -> 11075.696 | W64: =T64*2% -> 3893.34 | X64: =T64-U64-V64-W64 -> 160231.26 | Y64: =T64*12 -> 2336004 | Z64: =I64*2 -> 353940 | AA64: =Y64+Z64 -> 2689944 | AB64: =AA64*3.5% -> 94148.04 | AC64: =(AA64*0.9-(W64*12))*11%-AD64 -> 140117.77 | AD64: =AA64*0.9*5% -> 121047.48 | AE64: =AA64*3% -> 80698.32 | AF64: =AA64+AC64+AD64+AE64+AB64 -> 3125955.6 | AG64: РБ
A65: =A64+1 -> 43 | B65: Педагог дополнительного образования | C65: Елшибеков Халыкбек Ерикұлы | E65: 0.5 | F65: 17697 | G65: 45901 | H65: 40 | I65: =E65*17697*H65 -> 353940 | J65: =I65*10% -> 35394 | S65: =SUM(J65:R65) -> 35394 | T65: =I65+S65 -> 389334 | U65: =T65*10% -> 38933.4 | V65: =((T65-U65-W65)-(14*4325))*10% -> 28206.392 | W65: =T65*2% -> 7786.68 | X65: =T65-U65-V65-W65 -> 314407.53 | Y65: =T65*12 -> 4672008 | Z65: =I65*2 -> 707880 | AA65: =Y65+Z65 -> 5379888 | AB65: =AA65*3.5% -> 188296.08 | AC65: =(AA65*0.9-(W65*12))*11%-AD65 -> 280235.53 | AD65: =AA65*0.9*5% -> 242094.96 | AE65: =AA65*3% -> 161396.64 | AF65: =AA65+AC65+AD65+AE65+AB65 -> 6251911.2 | AG65: РБ
A66: =A65+1 -> 44 | B66: Педагог дополнительного образования | C66: Мақашева Нұрила Болатқызы | E66: 0.25 | F66: 17697 | G66: 45901 | H66: 40 | I66: =E66*17697*H66 -> 176970 | J66: =I66*10% -> 17697 | S66: =SUM(J66:R66) -> 17697 | T66: =I66+S66 -> 194667 | U66: =T66*10% -> 19466.7 | V66: =((T66-U66-W66)-(14*4325))*10% -> 11075.696 | W66: =T66*2% -> 3893.34 | X66: =T66-U66-V66-W66 -> 160231.26 | Y66: =T66*12 -> 2336004 | Z66: =I66*2 -> 353940 | AA66: =Y66+Z66 -> 2689944 | AB66: =AA66*3.5% -> 94148.04 | AC66: =(AA66*0.9-(W66*12))*11%-AD66 -> 140117.77 | AD66: =AA66*0.9*5% -> 121047.48 | AE66: =AA66*3% -> 80698.32 | AF66: =AA66+AC66+AD66+AE66+AB66 -> 3125955.6 | AG66: РБ
A67: =A66+1 -> 45 | B67: Педагог дополнительного образования | C67: Мамышев Бақыт Жанасұлы | E67: 0.25 | F67: 17697 | G67: 45917 | H67: 18 | I67: =E67*17697*H67 -> 79636.5 | J67: =I67*10% -> 7963.65 | S67: =SUM(J67:R67) -> 7963.65 | T67: =I67+S67 -> 87600.15 | U67: =T67*10% -> 8760.015 | V67: =((T67-U67-W67)-(14*4325))*10% -> 1653.8132 | W67: =T67*2% -> 1752.003 | X67: =T67-U67-V67-W67 -> 75434.319 | Y67: =T67*12 -> 1051201.8 | Z67: =I67*2 -> 159273 | AA67: =Y67+Z67 -> 1210474.8 | AB67: =AA67*3.5% -> 42366.618 | AC67: =(AA67*0.9-(W67*12))*11%-AD67 -> 63052.995 | AD67: =AA67*0.9*5% -> 54471.366 | AE67: =AA67*3% -> 36314.244 | AF67: =AA67+AC67+AD67+AE67+AB67 -> 1406680 | AG67: РБ
A68: =A67+1 -> 46 | B68: Педагог дополнительного образования | C68: Муратова Алина Кабыловна | E68: 0.25 | F68: 17697 | G68: 45917 | H68: 18 | I68: =E68*17697*H68 -> 79636.5 | J68: =I68*10% -> 7963.65 | S68: =SUM(J68:R68) -> 7963.65 | T68: =I68+S68 -> 87600.15 | U68: =T68*10% -> 8760.015 | V68: =((T68-U68-W68)-(14*4325))*10% -> 1653.8132 | W68: =T68*2% -> 1752.003 | X68: =T68-U68-V68-W68 -> 75434.319 | Y68: =T68*12 -> 1051201.8 | Z68: =I68*2 -> 159273 | AA68: =Y68+Z68 -> 1210474.8 | AB68: =AA68*3.5% -> 42366.618 | AC68: =(AA68*0.9-(W68*12))*11%-AD68 -> 63052.995 | AD68: =AA68*0.9*5% -> 54471.366 | AE68: =AA68*3% -> 36314.244 | AF68: =AA68+AC68+AD68+AE68+AB68 -> 1406680 | AG68: РБ
A69: =A68+1 -> 47 | B69: Педагог дополнительного образования | C69: Мусатай Санат Сагатұлы | E69: 0.25 | F69: 17697 | G69: 45917 | H69: 18 | I69: =E69*17697*H69 -> 79636.5 | J69: =I69*10% -> 7963.65 | S69: =SUM(J69:R69) -> 7963.65 | T69: =I69+S69 -> 87600.15 | U69: =T69*10% -> 8760.015 | V69: =((T69-U69-W69)-(14*4325))*10% -> 1653.8132 | W69: =T69*2% -> 1752.003 | X69: =T69-U69-V69-W69 -> 75434.319 | Y69: =T69*12 -> 1051201.8 | Z69: =I69*2 -> 159273 | AA69: =Y69+Z69 -> 1210474.8 | AB69: =AA69*3.5% -> 42366.618 | AC69: =(AA69*0.9-(W69*12))*11%-AD69 -> 63052.995 | AD69: =AA69*0.9*5% -> 54471.366 | AE69: =AA69*3% -> 36314.244 | AF69: =AA69+AC69+AD69+AE69+AB69 -> 1406680 | AG69: РБ
A70: =A69+1 -> 48 | B70: Педагог дополнительного образования | C70: Онаев Айнабек Тогайбекович | E70: 0.5 | F70: 17697 | G70: 45901 | H70: 40 | I70: =E70*17697*H70 -> 353940 | J70: =I70*10% -> 35394 | S70: =SUM(J70:R70) -> 35394 | T70: =I70+S70 -> 389334 | U70: =T70*10% -> 38933.4 | V70: =((T70-U70-W70)-(14*4325))*10% -> 28206.392 | W70: =T70*2% -> 7786.68 | X70: =T70-U70-V70-W70 -> 314407.53 | Y70: =T70*12 -> 4672008 | Z70: =I70*2 -> 707880 | AA70: =Y70+Z70 -> 5379888 | AB70: =AA70*3.5% -> 188296.08 | AC70: =(AA70*0.9-(W70*12))*11%-AD70 -> 280235.53 | AD70: =AA70*0.9*5% -> 242094.96 | AE70: =AA70*3% -> 161396.64 | AF70: =AA70+AC70+AD70+AE70+AB70 -> 6251911.2 | AG70: РБ
A71: =A70+1 -> 49 | B71: Педагог дополнительного образования | C71: Сәлден Шахназар Қанағатұлы | E71: 0.5 | F71: 17697 | G71: 45931 | H71: 40 | I71: =E71*17697*H71 -> 353940 | J71: =I71*10% -> 35394 | S71: =SUM(J71:R71) -> 35394 | T71: =I71+S71 -> 389334 | U71: =T71*10% -> 38933.4 | V71: =((T71-U71-W71)-(14*4325))*10% -> 28206.392 | W71: =T71*2% -> 7786.68 | X71: =T71-U71-V71-W71 -> 314407.53 | Y71: =T71*12 -> 4672008 | Z71: =I71*2 -> 707880 | AA71: =Y71+Z71 -> 5379888 | AB71: =AA71*3.5% -> 188296.08 | AC71: =(AA71*0.9-(W71*12))*11%-AD71 -> 280235.53 | AD71: =AA71*0.9*5% -> 242094.96 | AE71: =AA71*3% -> 161396.64 | AF71: =AA71+AC71+AD71+AE71+AB71 -> 6251911.2 | AG71: РБ
... A74: =A73+1 -> 52 | B74: Педагог дополнительного образования | C74: Шакиров Аман Кайратұлы | E74: 0.25 | F74: 17697 | G74: 45901 | H74: 40 | I74: =E74*17697*H74 -> 176970 | J74: =I74*10% -> 17697 | S74: =SUM(J74:R74) -> 17697 | T74: =I74+S74 -> 194667 | U74: =T74*10% -> 19466.7 | V74: =((T74-U74-W74)-(14*4325))*10% -> 11075.696 | W74: =T74*2% -> 3893.34 | X74: =T74-U74-V74-W74 -> 160231.26 | Y74: =T74*12 -> 2336004 | Z74: =I74*2 -> 353940 | AA74: =Y74+Z74 -> 2689944 | AB74: =AA74*3.5% -> 94148.04 | AC74: =(AA74*0.9-(W74*12))*11%-AD74 -> 140117.77 | AD74: =AA74*0.9*5% -> 121047.48 | AE74: =AA74*3% -> 80698.32 | AF74: =AA74+AC74+AD74+AE74+AB74 -> 3125955.6 | AG74: РБ
A75: =A74+1 -> 53 | B75: Педагог дополнительного образования | C75: Вакансия-3 | F75: 17697 | H75: 40 | I75: =3*17697*H75 -> 2123640 | J75: =I75*10% -> 212364 | S75: =SUM(J75:R75) -> 212364 | T75: =I75+S75 -> 2336004 | U75: =T75*10% -> 233600.4 | V75: =((T75-U75-W75)-(14*4325))*10% -> 199513.35 | W75: =T75*2% -> 46720.08 | X75: =T75-U75-V75-W75 -> 1856170.2 | Y75: =T75*12 -> 28032048 | Z75: =I75*2 -> 4247280 | AA75: =Y75+Z75 -> 32279328 | AB75: =AA75*3.5% -> 1129776.5 | AC75: =(AA75*0.9-(W75*12))*11%-AD75 -> 1681413.2 | AD75: =AA75*0.9*5% -> 1452569.8 | AE75: =AA75*3% -> 968379.84 | AF75: =AA75+AC75+AD75+AE75+AB75 -> 37511467 | AG75: РБ
A76: =A75+1 -> 54 | B76: Педагог дополнительного образования | C76: Каирбекова Жанна Нуртолеуовна | E76: 0.5 | F76: 17697 | G76: 44819 | H76: 16 | I76: =E76*17697*H76 -> 141576 | J76: =I76*10% -> 14157.6 | S76: =SUM(J76:R76) -> 14157.6 | T76: =I76+S76 -> 155733.6 | U76: =T76*10% -> 15573.36 | V76: =((T76-U76-W76)-(14*4325))*10% -> 7649.5568 | W76: =T76*2% -> 3114.672 | X76: =T76-U76-V76-W76 -> 129396.01 | Y76: =T76*12 -> 1868803.2 | Z76: =I76*2 -> 283152 | AA76: =Y76+Z76 -> 2151955.2 | AB76: =AA76*3.5% -> 75318.432 | AC76: =(AA76*0.9-(W76*12))*11%-AD76 -> 112094.21 | AD76: =AA76*0.9*5% -> 96837.984 | AE76: =AA76*3% -> 64558.656 | AF76: =AA76+AC76+AD76+AE76+AB76 -> 2500764.5 | AG76: РБ
A77: =A76+1 -> 55 | B77: Педагог дополнительного образования | C77: Кунгожин Медеубек Аманкельдиевич | E77: 1 | F77: 17697 | G77: 42860 | H77: 24 | I77: =E77*17697*H77 -> 424728 | J77: =I77*10% -> 42472.8 | S77: =SUM(J77:R77) -> 42472.8 | T77: =I77+S77 -> 467200.8 | U77: =T77*10% -> 46720.08 | V77: =((T77-U77-W77)-(14*4325))*10% -> 35058.67 | W77: =T77*2% -> 9344.016 | X77: =T77-U77-V77-W77 -> 376078.03 | Y77: =T77*12 -> 5606409.6 | Z77: =I77*2 -> 849456 | AA77: =Y77+Z77 -> 6455865.6 | AB77: =AA77*3.5% -> 225955.3 | AC77: =(AA77*0.9-(W77*12))*11%-AD77 -> 336282.64 | AD77: =AA77*0.9*5% -> 290513.95 | AE77: =AA77*3% -> 193675.97 | AF77: =AA77+AC77+AD77+AE77+AB77 -> 7502293.5 | AG77: РБ
A78: =A77+1 -> 56 | B78: Педагог дополнительного образования | C78: Талғатұлы Дәурен | E78: 1 | F78: 17697 | G78: 45183 | H78: 17 | I78: =E78*17697*H78 -> 300849 | J78: =I78*10% -> 30084.9 | S78: =SUM(J78:R78) -> 30084.9 | T78: =I78+S78 -> 330933.9 | U78: =T78*10% -> 33093.39 | V78: =((T78-U78-W78)-(14*4325))*10% -> 23067.183 | W78: =T78*2% -> 6618.678 | X78: =T78-U78-V78-W78 -> 268154.65 | Y78: =T78*12 -> 3971206.8 | Z78: =I78*2 -> 601698 | AA78: =Y78+Z78 -> 4572904.8 | AB78: =AA78*3.5% -> 160051.67 | AC78: =(AA78*0.9-(W78*12))*11%-AD78 -> 238200.2 | AD78: =AA78*0.9*5% -> 205780.72 | AE78: =AA78*3% -> 137187.14 | AF78: =AA78+AC78+AD78+AE78+AB78 -> 5314124.5 | AG78: РБ
A79: =A78+1 -> 57 | B79: Педагог дополнительного образования | C79: Туреханова Кундуз Моминовна (по совместиттельству) | E79: 0.5 | F79: 17697 | G79: 44774 | H79: 20 | I79: =E79*17697*H79 -> 176970 | J79: =I79*10% -> 17697 | S79: =SUM(J79:R79) -> 17697 | T79: =I79+S79 -> 194667 | U79: =T79*10% -> 19466.7 | V79: =((T79-U79-W79)-(14*4325))*10% -> 11075.696 | W79: =T79*2% -> 3893.34 | X79: =T79-U79-V79-W79 -> 160231.26 | Y79: =T79*12 -> 2336004 | Z79: =I79*2 -> 353940 | AA79: =Y79+Z79 -> 2689944 | AB79: =AA79*3.5% -> 94148.04 | AC79: =(AA79*0.9-(W79*12))*11%-AD79 -> 140117.77 | AD79: =AA79*0.9*5% -> 121047.48 | AE79: =AA79*3% -> 80698.32 | AF79: =AA79+AC79+AD79+AE79+AB79 -> 3125955.6 | AG79: РБ
A80: =A79+1 -> 58 | B80: Музыкально- художественный руководитель | C80: Сизов Евгений Николаевич | D80: 1 | E80: 1 | F80: 17697 | G80: 44287 | H80: 14 | I80: =E80*17697*H80 -> 247758 | J80: =I80*10% -> 24775.8 | S80: =SUM(J80:R80) -> 24775.8 | T80: =I80+S80 -> 272533.8 | U80: =T80*10% -> 27253.38 | V80: =((T80-U80-W80)-(14*4325))*10% -> 17927.974 | W80: =T80*2% -> 5450.676 | X80: =T80-U80-V80-W80 -> 221901.77 | Y80: =T80*12 -> 3270405.6 | Z80: =I80*2 -> 495516 | AA80: =Y80+Z80 -> 3765921.6 | AB80: =AA80*3.5% -> 131807.26 | AC80: =(AA80*0.9-(W80*12))*11%-AD80 -> 196164.87 | AD80: =AA80*0.9*5% -> 169466.47 | AE80: =AA80*3% -> 112977.65 | AF80: =AA80+AC80+AD80+AE80+AB80 -> 4376337.9 | AG80: РБ
A81: =A80+1 -> 59 | B81: Педагог-психолог | C81: Динсаламова Бакыткул Мукагалиевна | D81: 4 | E81: 1 | F81: 17697 | G81: 42293 | H81: 25 | I81: =E81*17697*H81 -> 442425 | J81: =I81*10% -> 44242.5 | S81: =SUM(J81:R81) -> 44242.5 | T81: =I81+S81 -> 486667.5 | U81: =T81*10% -> 48666.75 | V81: =((T81-U81-W81)-(14*4325))*10% -> 36771.74 | W81: =T81*2% -> 9733.35 | X81: =T81-U81-V81-W81 -> 391495.66 | Y81: =T81*12 -> 5840010 | Z81: =I81*2 -> 884850 | AA81: =Y81+Z81 -> 6724860 | AB81: =AA81*3.5% -> 235370.1 | AC81: =(AA81*0.9-(W81*12))*11%-AD81 -> 350294.42 | AD81: =AA81*0.9*5% -> 302618.7 | AE81: =AA81*3% -> 201745.8 | AF81: =AA81+AC81+AD81+AE81+AB81 -> 7814889 | AG81: РБ
A82: =A81+1 -> 60 | B82: Педагог-психолог | C82: Мансурова Румилям Карлиновна | E82: 1 | F82: 17697 | G82: 44908 | H82: 20 | I82: =E82*17697*H82 -> 353940 | J82: =I82*10% -> 35394 | M82: =I82*30% -> 106182 | S82: =SUM(J82:R82) -> 141576 | T82: =I82+S82 -> 495516 | U82: =T82*10% -> 49551.6 | V82: =((T82-U82-W82)-(14*4325))*10% -> 37550.408 | W82: =T82*2% -> 9910.32 | X82: =T82-U82-V82-W82 -> 398503.67 | Y82: =T82*12 -> 5946192 | Z82: =I82*2 -> 707880 | AA82: =Y82+Z82 -> 6654072 | AB82: =AA82*3.5% -> 232892.52 | AC82: =(AA82*0.9-(W82*12))*11%-AD82 -> 346238.27 | AD82: =AA82*0.9*5% -> 299433.24 | AE82: =AA82*3% -> 199622.16 | AF82: =AA82+AC82+AD82+AE82+AB82 -> 7732258.2 | AG82: РБ
A83: =A82+1 -> 61 | B83: Педагог-психолог | C83: Сеиткали Дидар Мараткызы | E83: 1 | F83: 17697 | G83: 45160 | H83: 19 | I83: =E83*17697*H83 -> 336243 | J83: =I83*10% -> 33624.3 | K83: =10*4325 -> 43250 | S83: =SUM(J83:R83) -> 76874.3 | T83: =I83+S83 -> 413117.3 | U83: =T83*10% -> 41311.73 | V83: =((T83-U83-W83)-(14*4325))*10% -> 30299.322 | W83: =T83*2% -> 8262.346 | X83: =T83-U83-V83-W83 -> 333243.9 | Y83: =T83*12 -> 4957407.6 | Z83: =I83*2 -> 672486 | AA83: =Y83+Z83 -> 5629893.6 | AB83: =AA83*3.5% -> 197046.28 | AC83: =(AA83*0.9-(W83*12))*11%-AD83 -> 293107.96 | AD83: =AA83*0.9*5% -> 253345.21 | AE83: =AA83*3% -> 168896.81 | AF83: =AA83+AC83+AD83+AE83+AB83 -> 6542289.9 | AG83: РБ
A84: =A83+1 -> 62 | B84: Педагог-психолог | C84: Тлеубердинова Жанат Мураткановна | E84: 1 | F84: 17697 | G84: 43773 | H84: 25 | I84: =E84*17697*H84 -> 442425 | J84: =I84*10% -> 44242.5 | M84: =I84*30% -> 132727.5 | S84: =SUM(J84:R84) -> 176970 | T84: =I84+S84 -> 619395 | U84: =T84*10% -> 61939.5 | V84: =((T84-U84-W84)-(14*4325))*10% -> 48451.76 | W84: =T84*2% -> 12387.9 | X84: =T84-U84-V84-W84 -> 496615.84 | Y84: =T84*12 -> 7432740 | Z84: =I84*2 -> 884850 | AA84: =Y84+Z84 -> 8317590 | AB84: =AA84*3.5% -> 291115.65 | AC84: =(AA84*0.9-(W84*12))*11%-AD84 -> 432797.83 | AD84: =AA84*0.9*5% -> 374291.55 | AE84: =AA84*3% -> 249527.7 | AF84: =AA84+AC84+AD84+AE84+AB84 -> 9665322.7 | AG84: РБ
A85: =A84+1 -> 63 | B85: Социальный педагог | C85: Дюсупова Зарина Канатпаевна | D85: 1 | E85: 1 | F85: 17697 | G85: 43064 | H85: 22 | I85: =E85*17697*H85 -> 389334 | J85: =I85*10% -> 38933.4 | K85: =10*4325 -> 43250 | M85: =I85*30% -> 116800.2 | S85: =SUM(J85:R85) -> 198983.6 | T85: =I85+S85 -> 588317.6 | U85: =T85*10% -> 58831.76 | V85: =((T85-U85-W85)-(14*4325))*10% -> 45716.949 | W85: =T85*2% -> 11766.352 | X85: =T85-U85-V85-W85 -> 472002.54 | Y85: =T85*12 -> 7059811.2 | Z85: =I85*2 -> 778668 | AA85: =Y85+Z85 -> 7838479.2 | AB85: =AA85*3.5% -> 274346.77 | AC85: =(AA85*0.9-(W85*12))*11%-AD85 -> 407746.29 | AD85: =AA85*0.9*5% -> 352731.56 | AE85: =AA85*3% -> 235154.38 | AF85: =AA85+AC85+AD85+AE85+AB85 -> 9108458.2 | AG85: РБ
A86: =A85+1 -> 64 | B86: Заведующий библиотекой | C86: Смагулова Нургуль Бактурсыновна | D86: 1 | E86: 1 | F86: 17697 | G86: 42661 | H86: 20 | I86: =E86*17697*H86 -> 353940 | J86: =I86*10% -> 35394 | P86: =17697*30% -> 5309.1 | S86: =SUM(J86:R86) -> 40703.1 | T86: =I86+S86 -> 394643.1 | U86: =T86*10% -> 39464.31 | V86: =((T86-U86-W86)-(14*4325))*10% -> 28673.593 | W86: =T86*2% -> 7892.862 | X86: =T86-U86-V86-W86 -> 318612.34 | Y86: =T86*12 -> 4735717.2 | Z86: =I86*2 -> 707880 | AA86: =Y86+Z86 -> 5443597.2 | AB86: =AA86*3.5% -> 190525.9 | AC86: =(AA86*0.9-(W86*12))*11%-AD86 -> 283535.67 | AD86: =AA86*0.9*5% -> 244961.87 | AE86: =AA86*3% -> 163307.92 | AF86: =AA86+AC86+AD86+AE86+AB86 -> 6325928.6 | AG86: РБ
A87: =A86+1 -> 65 | B87: Библиотекарь | C87: Алжанова Айжан Копжасаровна | D87: 2 | E87: 1 | F87: 17697 | G87: 34736 | H87: 16 | I87: =E87*17697*H87 -> 283152 | J87: =I87*10% -> 28315.2 | P87: =17697*30% -> 5309.1 | S87: =SUM(J87:R87) -> 33624.3 | T87: =I87+S87 -> 316776.3 | U87: =T87*10% -> 31677.63 | V87: =((T87-U87-W87)-(14*4325))*10% -> 21821.314 | W87: =T87*2% -> 6335.526 | X87: =T87-U87-V87-W87 -> 256941.83 | Y87: =T87*12 -> 3801315.6 | Z87: =I87*2 -> 566304 | AA87: =Y87+Z87 -> 4367619.6 | AB87: =AA87*3.5% -> 152866.69 | AC87: =(AA87*0.9-(W87*12))*11%-AD87 -> 227488.56 | AD87: =AA87*0.9*5% -> 196542.88 | AE87: =AA87*3% -> 131028.59 | AF87: =AA87+AC87+AD87+AE87+AB87 -> 5075546.3 | AG87: РБ
A88: =A87+1 -> 66 | B88: Библиотекарь | C88: Имангожина Рая Аскергалиевна | E88: 1 | F88: 17697 | G88: 44536 | H88: 16 | I88: =E88*17697*H88 -> 283152 | J88: =I88*10% -> 28315.2 | P88: =17697*30% -> 5309.1 | S88: =SUM(J88:R88) -> 33624.3 | T88: =I88+S88 -> 316776.3 | U88: =T88*10% -> 31677.63 | V88: =((T88-U88-W88)-(14*4325))*10% -> 21821.314 | W88: =T88*2% -> 6335.526 | X88: =T88-U88-V88-W88 -> 256941.83 | Y88: =T88*12 -> 3801315.6 | Z88: =I88*2 -> 566304 | AA88: =Y88+Z88 -> 4367619.6 | AB88: =AA88*3.5% -> 152866.69 | AC88: =(AA88*0.9-(W88*12))*11%-AD88 -> 227488.56 | AD88: =AA88*0.9*5% -> 196542.88 | AE88: =AA88*3% -> 131028.59 | AF88: =AA88+AC88+AD88+AE88+AB88 -> 5075546.3 | AG88: РБ
A89: =A88+1 -> 67 | B89: Педагог организатор НВП | C89: Атканов Нурлан Аканович | D89: 1 | E89: 0.5 | F89: 17697 | G89: 45903 | H89: 11 | I89: =E89*17697*H89 -> 97333.5 | J89: =I89*10% -> 9733.35 | S89: =SUM(J89:R89) -> 9733.35 | T89: =I89+S89 -> 107066.85 | U89: =T89*10% -> 10706.685 | V89: =((T89-U89-W89)-(14*4325))*10% -> 3366.8828 | W89: =T89*2% -> 2141.337 | X89: =T89-U89-V89-W89 -> 90851.945 | Y89: =T89*12 -> 1284802.2 | Z89: =I89*2 -> 194667 | AA89: =Y89+Z89 -> 1479469.2 | AB89: =AA89*3.5% -> 51781.422 | AC89: =(AA89*0.9-(W89*12))*11%-AD89 -> 77064.772 | AD89: =AA89*0.9*5% -> 66576.114 | AE89: =AA89*3% -> 44384.076 | AF89: =AA89+AC89+AD89+AE89+AB89 -> 1719275.6 | AG89: РБ
A90: =A89+1 -> 68 | B90: Педагог организатор НВП | C90: Вакансия-0,5 | F90: 17697 | H90: 25 | I90: =0.5*17697*H90 -> 221212.5 | J90: =I90*10% -> 22121.25 | K90: =10*4325 -> 43250 | S90: =SUM(J90:R90) -> 65371.25 | T90: =I90+S90 -> 286583.75 | U90: =T90*10% -> 28658.375 | V90: =((T90-U90-W90)-(14*4325))*10% -> 19164.37 | W90: =T90*2% -> 5731.675 | X90: =T90-U90-V90-W90 -> 233029.33 | Y90: =T90*12 -> 3439005 | Z90: =I90*2 -> 442425 | AA90: =Y90+Z90 -> 3881430 | AB90: =AA90*3.5% -> 135850.05 | AC90: =(AA90*0.9-(W90*12))*11%-AD90 -> 202031.41 | AD90: =AA90*0.9*5% -> 174664.35 | AE90: =AA90*3% -> 116442.9 | AF90: =AA90+AC90+AD90+AE90+AB90 -> 4510418.7 | AG90: РБ
A91: =A90+1 -> 69 | B91: Системный администратор | C91: Құсатай Серікжан Қалимұратұлы | D91: 1 | E91: 1 | F91: 17697 | G91: 40702 | H91: 24 | I91: =E91*17697*H91 -> 424728 | J91: =I91*10% -> 42472.8 | S91: =SUM(J91:R91) -> 42472.8 | T91: =I91+S91 -> 467200.8 | U91: =T91*10% -> 46720.08 | V91: =((T91-U91-W91)-(14*4325))*10% -> 35058.67 | W91: =T91*2% -> 9344.016 | X91: =T91-U91-V91-W91 -> 376078.03 | Y91: =T91*12 -> 5606409.6 | Z91: =I91*2 -> 849456 | AA91: =Y91+Z91 -> 6455865.6 | AB91: =AA91*3.5% -> 225955.3 | AC91: =(AA91*0.9-(W91*12))*11%-AD91 -> 336282.64 | AD91: =AA91*0.9*5% -> 290513.95 | AE91: =AA91*3% -> 193675.97 | AF91: =AA91+AC91+AD91+AE91+AB91 -> 7502293.5 | AG91: РБ
A92: =A91+1 -> 70 | B92: Специалист по специальному оборудованию (фото-видео) | C92: Ізбай Арнұр Рысбекұлы | D92: 1 | E92: 1 | F92: 17697 | G92: 44998 | H92: 18 | I92: =E92*17697*H92 -> 318546 | J92: =I92*10% -> 31854.6 | S92: =SUM(J92:R92) -> 31854.6 | T92: =I92+S92 -> 350400.6 | U92: =T92*10% -> 35040.06 | V92: =((T92-U92-W92)-(14*4325))*10% -> 24780.253 | W92: =T92*2% -> 7008.012 | X92: =T92-U92-V92-W92 -> 283572.28 | Y92: =T92*12 -> 4204807.2 | Z92: =I92*2 -> 637092 | AA92: =Y92+Z92 -> 4841899.2 | AB92: =AA92*3.5% -> 169466.47 | AC92: =(AA92*0.9-(W92*12))*11%-AD92 -> 252211.98 | AD92: =AA92*0.9*5% -> 217885.46 | AE92: =AA92*3% -> 145256.98 | AF92: =AA92+AC92+AD92+AE92+AB92 -> 5626720.1 | AG92: РБ
A93: =A92+1 -> 71 | B93: Специалист по программному обепечению | C93: Альжанов Мадияр Ерғалиұлы | D93: 2 | E93: 1 | F93: 17697 | G93: 43077 | H93: 24 | I93: =E93*17697*H93 -> 424728 | J93: =I93*10% -> 42472.8 | S93: =SUM(J93:R93) -> 42472.8 | T93: =I93+S93 -> 467200.8 | U93: =T93*10% -> 46720.08 | V93: =((T93-U93-W93)-(14*4325))*10% -> 35058.67 | W93: =T93*2% -> 9344.016 | X93: =T93-U93-V93-W93 -> 376078.03 | Y93: =T93*12 -> 5606409.6 | Z93: =I93*2 -> 849456 | AA93: =Y93+Z93 -> 6455865.6 | AB93: =AA93*3.5% -> 225955.3 | AC93: =(AA93*0.9-(W93*12))*11%-AD93 -> 336282.64 | AD93: =AA93*0.9*5% -> 290513.95 | AE93: =AA93*3% -> 193675.97 | AF93: =AA93+AC93+AD93+AE93+AB93 -> 7502293.5 | AG93: РБ
A94: =A93+1 -> 72 | B94: Специалист по программному обепечению | C94: Вакансия-1 | F94: 17697 | H94: 25 | I94: =17697*H94 -> 442425 | J94: =I94*10% -> 44242.5 | S94: =SUM(J94:R94) -> 44242.5 | T94: =I94+S94 -> 486667.5 | U94: =T94*10% -> 48666.75 | V94: =((T94-U94-W94)-(14*4325))*10% -> 36771.74 | W94: =T94*2% -> 9733.35 | X94: =T94-U94-V94-W94 -> 391495.66 | Y94: =T94*12 -> 5840010 | Z94: =I94*2 -> 884850 | AA94: =Y94+Z94 -> 6724860 | AB94: =AA94*3.5%+2000000 -> 2235370.1 | AC94: =(AA94*0.9-(W94*12))*11%-AD94+5000000 -> 5350294.4 | AD94: =AA94*0.9*5% -> 302618.7 | AE94: =AA94*3% -> 201745.8 | AF94: =AA94+AC94+AD94+AE94+AB94 -> 14814889 | AG94: РБ
A95: =A94+1 -> 73 | B95: Лаборант | C95: Ахметов Нурали Боранказыұлы | D95: 8 | E95: 1 | F95: 17697 | G95: 45183 | H95: 15 | I95: =E95*17697*H95 -> 265455 | J95: =I95*10% -> 26545.5 | S95: =SUM(J95:R95) -> 26545.5 | T95: =I95+S95 -> 292000.5 | U95: =T95*10% -> 29200.05 | V95: =((T95-U95-W95)-(14*4325))*10% -> 19641.044 | W95: =T95*2% -> 5840.01 | X95: =T95-U95-V95-W95 -> 237319.4 | Y95: =T95*12 -> 3504006 | Z95: =I95*2 -> 530910 | AA95: =Y95+Z95 -> 4034916 | AB95: =AA95*3.5% -> 141222.06 | AC95: =(AA95*0.9-(W95*12))*11%-AD95 -> 210176.65 | AD95: =AA95*0.9*5% -> 181571.22 | AE95: =AA95*3% -> 121047.48 | AF95: =AA95+AC95+AD95+AE95+AB95 -> 4688933.4 | AG95: РБ
A96: =A95+1 -> 74 | B96: Лаборант | C96: Қуанышбай Айбар Мұратұлы | E96: 0.75 | F96: 17697 | G96: 44890 | H96: 24 | I96: =E96*17697*H96 -> 318546 | J96: =I96*10% -> 31854.6 | S96: =SUM(J96:R96) -> 31854.6 | T96: =I96+S96 -> 350400.6 | U96: =T96*10% -> 35040.06 | V96: =((T96-U96-W96)-(14*4325))*10% -> 24780.253 | W96: =T96*2% -> 7008.012 | X96: =T96-U96-V96-W96 -> 283572.28 | Y96: =T96*12 -> 4204807.2 | Z96: =I96*2 -> 637092 | AA96: =Y96+Z96 -> 4841899.2 | AB96: =AA96*3.5% -> 169466.47 | AC96: =(AA96*0.9-(W96*12))*11%-AD96 -> 252211.98 | AD96: =AA96*0.9*5% -> 217885.46 | AE96: =AA96*3% -> 145256.98 | AF96: =AA96+AC96+AD96+AE96+AB96 -> 5626720.1 | AG96: РБ
A97: =A96+1 -> 75 | B97: Лаборант | C97: Жамишева Сауле Абрашовна | E97: 0.5 | F97: 17697 | G97: 45562 | H97: 12 | I97: =E97*17697*H97 -> 106182 | J97: =I97*10% -> 10618.2 | S97: =SUM(J97:R97) -> 10618.2 | T97: =I97+S97 -> 116800.2 | U97: =T97*10% -> 11680.02 | V97: =((T97-U97-W97)-(14*4325))*10% -> 4223.4176 | W97: =T97*2% -> 2336.004 | X97: =T97-U97-V97-W97 -> 98560.758 | Y97: =T97*12 -> 1401602.4 | Z97: =I97*2 -> 212364 | AA97: =Y97+Z97 -> 1613966.4 | AB97: =AA97*3.5% -> 56488.824 | AC97: =(AA97*0.9-(W97*12))*11%-AD97 -> 84070.66 | AD97: =AA97*0.9*5% -> 72628.488 | AE97: =AA97*3% -> 48418.992 | AF97: =AA97+AC97+AD97+AE97+AB97 -> 1875573.4 | AG97: РБ
A98: =A97+1 -> 76 | B98: Лаборант | C98: Тулғанова Аида Әшірәліқызы | E98: 1 | F98: 17697 | G98: 45537 | H98: 15 | I98: =E98*17697*H98 -> 265455 | J98: =I98*10% -> 26545.5 | S98: =SUM(J98:R98) -> 26545.5 | T98: =I98+S98 -> 292000.5 | U98: =T98*10% -> 29200.05 | V98: =((T98-U98-W98)-(14*4325))*10% -> 19641.044 | W98: =T98*2% -> 5840.01 | X98: =T98-U98-V98-W98 -> 237319.4 | Y98: =T98*12 -> 3504006 | Z98: =I98*2 -> 530910 | AA98: =Y98+Z98 -> 4034916 | AB98: =AA98*3.5% -> 141222.06 | AC98: =(AA98*0.9-(W98*12))*11%-AD98 -> 210176.65 | AD98: =AA98*0.9*5% -> 181571.22 | AE98: =AA98*3% -> 121047.48 | AF98: =AA98+AC98+AD98+AE98+AB98 -> 4688933.4 | AG98: РБ
A99: =A98+1 -> 77 | B99: Лаборант | C99: Алтынбеков Батырхан | E99: 0.75 | F99: 17697 | G99: 45902 | H99: 20 | I99: =E99*17697*H99 -> 265455 | J99: =I99*10% -> 26545.5 | S99: =SUM(J99:R99) -> 26545.5 | T99: =I99+S99 -> 292000.5 | U99: =T99*10% -> 29200.05 | V99: =((T99-U99-W99)-(14*4325))*10% -> 19641.044 | W99: =T99*2% -> 5840.01 | X99: =T99-U99-V99-W99 -> 237319.4 | Y99: =T99*12 -> 3504006 | Z99: =I99*2 -> 530910 | AA99: =Y99+Z99 -> 4034916 | AB99: =AA99*3.5% -> 141222.06 | AC99: =(AA99*0.9-(W99*12))*11%-AD99 -> 210176.65 | AD99: =AA99*0.9*5% -> 181571.22 | AE99: =AA99*3% -> 121047.48 | AF99: =AA99+AC99+AD99+AE99+AB99 -> 4688933.4 | AG99: РБ
A100: =A99+1 -> 78 | B100: Лаборант | C100: Асқар Аманжол (по совместительству) | E100: 0.75 | F100: 17697 | G100: 45902 | H100: 24 | I100: =E100*17697*H100 -> 318546 | J100: =I100*10% -> 31854.6 | S100: =SUM(J100:R100) -> 31854.6 | T100: =I100+S100 -> 350400.6 | U100: =T100*10% -> 35040.06 | V100: =((T100-U100-W100)-(14*4325))*10% -> 24780.253 | W100: =T100*2% -> 7008.012 | X100: =T100-U100-V100-W100 -> 283572.28 | Y100: =T100*12 -> 4204807.2 | Z100: =I100*2 -> 637092 | AA100: =Y100+Z100 -> 4841899.2 | AB100: =AA100*3.5% -> 169466.47 | AC100: =(AA100*0.9-(W100*12))*11%-AD100 -> 252211.98 | AD100: =AA100*0.9*5% -> 217885.46 | AE100: =AA100*3% -> 145256.98 | AF100: =AA100+AC100+AD100+AE100+AB100 -> 5626720.1 | AG100: РБ
A101: =A100+1 -> 79 | B101: Лаборант | C101: Меньщиков Андрей Борисович | E101: 1 | F101: 17697 | G101: 45902 | H101: 21 | I101: =E101*17697*H101 -> 371637 | J101: =I101*10% -> 37163.7 | S101: =SUM(J101:R101) -> 37163.7 | T101: =I101+S101 -> 408800.7 | U101: =T101*10% -> 40880.07 | V101: =((T101-U101-W101)-(14*4325))*10% -> 29919.462 | W101: =T101*2% -> 8176.014 | X101: =T101-U101-V101-W101 -> 329825.15 | Y101: =T101*12 -> 4905608.4 | Z101: =I101*2 -> 743274 | AA101: =Y101+Z101 -> 5648882.4 | AB101: =AA101*3.5% -> 197710.88 | AC101: =(AA101*0.9-(W101*12))*11%-AD101 -> 294247.31 | AD101: =AA101*0.9*5% -> 254199.71 | AE101: =AA101*3% -> 169466.47 | AF101: =AA101+AC101+AD101+AE101+AB101 -> 6564506.8 | AG101: РБ
A102: =A101+1 -> 80 | B102: Лаборант | C102: Рабиғұлова Гүлдана Берікханқызы | E102: 0.5 | F102: 17697 | G102: 45901 | H102: 20 | I102: =E102*17697*H102 -> 176970 | J102: =I102*10% -> 17697 | S102: =SUM(J102:R102) -> 17697 | T102: =I102+S102 -> 194667 | U102: =T102*10% -> 19466.7 | V102: =((T102-U102-W102)-(14*4325))*10% -> 11075.696 | W102: =T102*2% -> 3893.34 | X102: =T102-U102-V102-W102 -> 160231.26 | Y102: =T102*12 -> 2336004 | Z102: =I102*2 -> 353940 | AA102: =Y102+Z102 -> 2689944 | AB102: =AA102*3.5% -> 94148.04 | AC102: =(AA102*0.9-(W102*12))*11%-AD102 -> 140117.77 | AD102: =AA102*0.9*5% -> 121047.48 | AE102: =AA102*3% -> 80698.32 | AF102: =AA102+AC102+AD102+AE102+AB102 -> 3125955.6 | AG102: РБ
A103: =A102+1 -> 81 | B103: Лаборант | C103: Вакансия-1,75 | F103: 17697 | H103: 25 | I103: =1.75*17697*H103 -> 774243.75 | J103: =I103*10% -> 77424.375 | S103: =SUM(J103:R103) -> 77424.375 | T103: =I103+S103 -> 851668.12 | U103: =T103*10% -> 85166.812 | V103: =((T103-U103-W103)-(14*4325))*10% -> 68891.795 | W103: =T103*2% -> 17033.362 | X103: =T103-U103-V103-W103 -> 680576.15 | Y103: =T103*12 -> 10220018 | Z103: =I103*2 -> 1548487.5 | AA103: =Y103+Z103 -> 11768505 | AB103: =AA103*3.5%+2000000 -> 2411897.7 | AC103: =(AA103*0.9-(W103*12))*11%-AD103+5000000 -> 5613015.2 | AD103: =AA103*0.9*5% -> 529582.72 | AE103: =AA103*3% -> 353055.15 | AF103: =AA103+AC103+AD103+AE103+AB103 -> 20676056 | AG103: РБ
B104: ИТОГО по УВП | D104: =SUM(D42:D103) -> 52 | E104: =SUM(E42:E103) -> 41.75 | I104: =SUM(I42:I103) -> 23629919 | J104: =SUM(J42:J103) -> 2362991.9 | K104: =SUM(K42:K103) -> 129750 | L104: =SUM(L42:L103) -> 0 | M104: =SUM(M42:M103) -> 355709.7 | N104: =SUM(N42:N103) -> 0 | O104: =SUM(O42:O103) -> 0 | P104: =SUM(P42:P103) -> 15927.3 | ... AF104: =SUM(AF42:AF103) -> 4.5693551e+08
A105: Медицинский персонал (МП)
A106: =A103+1 -> 82 | B106: Врач-педиатр | C106: Даулетярова Нургайша Адаевна | D106: 1 | E106: 1 | G106: 44797 | H106: 21 | I106: =E106*17697*H106 -> 371637 | J106: =I106*10% -> 37163.7 | S106: =SUM(J106:R106) -> 37163.7 | T106: =I106+S106 -> 408800.7 | U106: =T106*10% -> 40880.07 | V106: =((T106-U106-W106)-(14*4325))*10% -> 29919.462 | W106: =T106*2% -> 8176.014 | X106: =T106-U106-V106-W106 -> 329825.15 | Y106: =T106*12 -> 4905608.4 | Z106: =I106*2 -> 743274 | AA106: =Y106+Z106 -> 5648882.4 | AB106: =AA106*3.5% -> 197710.88 | AC106: =(AA106*0.9-(W106*12))*11%-AD106 -> 294247.31 | AD106: =AA106*0.9*5% -> 254199.71 | AE106: =AA106*3% -> 169466.47 | AF106: =AA106+AC106+AD106+AE106+AB106 -> 6564506.8 | AG106: РБ
A107: =A106+1 -> 83 | B107: Медицинская сестра | C107: Вакансия-1 | D107: 1 | G107: 45699 | H107: 25 | I107: =17697*H107 -> 442425 | J107: =I107*10% -> 44242.5 | S107: =SUM(J107:R107) -> 44242.5 | T107: =I107+S107 -> 486667.5 | U107: =T107*10% -> 48666.75 | V107: =((T107-U107-W107)-(14*4325))*10% -> 36771.74 | W107: =T107*2% -> 9733.35 | X107: =T107-U107-V107-W107 -> 391495.66 | Y107: =T107*12 -> 5840010 | Z107: =I107*2 -> 884850 | AA107: =Y107+Z107 -> 6724860 | AB107: =AA107*3.5% -> 235370.1 | AC107: =(AA107*0.9-(W107*12))*11%-AD107+6667589.35 -> 7017883.8 | AD107: =AA107*0.9*5% -> 302618.7 | AE107: =AA107*3% -> 201745.8 | AF107: =AA107+AC107+AD107+AE107+AB107 -> 14482478 | AG107: РБ
A108: =A107+1 -> 84 | B108: Диетическая медсестра | C108: Аксакалова Анар Сагидолдановна | D108: 1 | E108: 1 | G108: 44151 | H108: 16 | I108: =E108*17697*H108 -> 283152 | J108: =I108*10% -> 28315.2 | S108: =SUM(J108:R108) -> 28315.2 | T108: =I108+S108 -> 311467.2 | U108: =T108*10% -> 31146.72 | V108: =((T108-U108-W108)-(14*4325))*10% -> 21354.114 | W108: =T108*2% -> 6229.344 | X108: =T108-U108-V108-W108 -> 252737.02 | Y108: =T108*12 -> 3737606.4 | Z108: =I108*2 -> 566304 | AA108: =Y108+Z108 -> 4303910.4 | AB108: =AA108*3.5% -> 150636.86 | AC108: =(AA108*0.9-(W108*12))*11%-AD108 -> 224188.43 | AD108: =AA108*0.9*5% -> 193675.97 | AE108: =AA108*3% -> 129117.31 | AF108: =AA108+AC108+AD108+AE108+AB108 -> 5001529 | AG108: РБ
B109: ИТОГО по МП | D109: =SUM(D106:D108) -> 3 | E109: =SUM(E106:E108) -> 2 | I109: =SUM(I106:I108) -> 1097214 | J109: =SUM(J106:J108) -> 109721.4 | K109: =SUM(K106:K108) -> 0 | L109: =SUM(L106:L108) -> 0 | M109: =SUM(M106:M108) -> 0 | N109: =SUM(N106:N108) -> 0 | O109: =SUM(O106:O108) -> 0 | P109: =SUM(P106:P108) -> 0 | ... AF109: =SUM(AF106:AF108) -> 26048514
A110: Обслуживающий и вспомогательный персонал (ОВП)
A111: =A108+1 -> 85 | B111: Инженер по охране труда и техники безопасности | C111: Алимжанов Ислам Алимжанович | D111: 1 | E111: 1 | G111: 44872 | H111: 30 | I111: =E111*17697*H111 -> 530910 | J111: =I111*10% -> 53091 | S111: =SUM(J111:R111) -> 53091 | T111: =I111+S111 -> 584001 | U111: =T111*10% -> 58400.1 | V111: =((T111-U111-W111)-(14*4325))*10% -> 45337.088 | W111: =T111*2% -> 11680.02 | X111: =T111-U111-V111-W111 -> 468583.79 | Y111: =T111*12 -> 7008012 | Z111: =I111*2 -> 1061820 | AA111: =Y111+Z111 -> 8069832 | AB111: =AA111*3.5% -> 282444.12 | AC111: =(AA111*0.9-(W111*12))*11%-AD111 -> 420353.3 | AD111: =AA111*0.9*5% -> 363142.44 | AE111: =AA111*3% -> 242094.96 | AF111: =AA111+AC111+AD111+AE111+AB111 -> 9377866.8 | AG111: РБ
...

Sheet ШР РБ Алматы
I5: «УТВЕРЖДЕНО»
I6: Решением Правления НАО «РФМШ»
I7: Протокол №_____ от «______» _____________ 20_____г.
A10: Штатное расписание
A11: Наименование организации: Филиал НАО «Республиканская физико-математическая школа» в г. Алматы на «01» января 2026 года
A12: (в том числе интернат )
A15: Виды доплат /согласно внутреннему Положению о системе оплаты труда работников НАО "Республиканская физико-математическая школа" заполнение в строгости с соблюдением наличие подтверждающих документов (диплом. протокол. приказ. удостоверение и иной докумен подтверждающий документ подлежащий оплате)/ строки полежат дополнению в случае необходимости
A16: № п/п | B16: Наименование должностей | C16: ФИО | D16: Количество штатных единиц | E16: Кол-во штатных единиц /по факту cогласно приказа) | F16: коэффициент | G16: Дата приема на работу/ согласно даты указанной в приказе | H16: Коэффициент для исчисления должностного оклада работников | I16: Должностной оклад/ сумма | J16: Доплата 10% за особые условия труда/ сумма | K16: Ученая степень и магистра | L16: Доплата от ДО за квалификационную категорию руковод. (директорам) и зам.руковод. | M16: Доплата от ДО за квалификацию педагогического мастерства учителей, воспитателей и иных педагогических работников | N16: Доплата от БДО за квалификационную категорию учителей, воспитателей и иных педагогических работников | O16: Доплата от БДО за класса квалификацию водителя | P16: Доплата в размере 30% от БДО за работу с библиотечным фондом, за использование дезинф.средств при уборке туалетов работниками | Q16: Доплата в размере 20% от БДО за использование дезинфицирующих средств работниками | R16: Доплата в размере 25% от БДО за особые условия труда работников | S16: Итого доплаты | T16: Всего ФЗП за месяц | U16: ОПВ 10% | V16: ИПН | W16: ВОСМС | X16: Итого на руки | Y16: Всего ФЗП в год | Z16: Лечебно-оздоровительные пособия | AA16: Всего ФЗП с леч пособием | AB16: ОПВР 3.5% | AC16: Социальный налог 6% | AD16: Социальные отчисления 5% | AE16: ОСМС 3% | AF16: ВСЕГО ФОТ | AG16: Вид бюджета
A18: Административно-управленический персонал (АУП)
A19: 1 | B19: Директор | C19: Меирбек Меирлан Едигерулы | D19: 1 | E19: 1 | G19: 45146 | H19: 80 | I19: =H19*17697 -> 1415760 | J19: =I19*10% -> 141576 | S19: =SUM(J19:R19) -> 141576 | T19: =I19+S19 -> 1557336 | U19: =T19*10% -> 155733.6 | V19: =((T19-U19-W19)-(14*4325))*10% -> 130990.57 | W19: =T19*2% -> 31146.72 | X19: =T19-U19-V19-W19 -> 1239465.1 | Y19: =T19*12 -> 18688032 | Z19: =I19*2 -> 2831520 | AA19: =Y19+Z19 -> 21519552 | AB19: =AA19*3.5% -> 753184.32 | AC19: =(AA19*0.9-(W19*12))*11%-AD19 -> 1120942.1 | AD19: =AA19*0.9*5% -> 968379.84 | AE19: =AA19*3% -> 645586.56 | AF19: =AA19+AC19+AD19+AE19+AB19 -> 25007645 | AG19: РБ
A20: =A19+1 -> 2 | B20: Заместитель директора по учебной работе | C20: Кабулова Нурбану Таргиновна | D20: 2 | E20: 1 | G20: 43395 | H20: 32 | I20: =H20*17697 -> 566304 | J20: =I20*10% -> 56630.4 | S20: =SUM(J20:R20) -> 56630.4 | T20: =I20+S20 -> 622934.4 | U20: =T20*10% -> 62293.44 | V20: =((T20-U20-W20)-(14*4325))*10% -> 48763.227 | W20: =T20*2% -> 12458.688 | X20: =T20-U20-V20-W20 -> 499419.04 | Y20: =T20*12 -> 7475212.8 | Z20: =I20*2 -> 1132608 | AA20: =Y20+Z20 -> 8607820.8 | AB20: =AA20*3.5% -> 301273.73 | AC20: =(AA20*0.9-(W20*12))*11%-AD20 -> 448376.86 | AD20: =AA20*0.9*5% -> 387351.94 | AE20: =AA20*3% -> 258234.62 | AF20: =AA20+AC20+AD20+AE20+AB20 -> 10003058 | AG20: РБ
A21: =A20+1 -> 3 | B21: Заместитель директора по учебной работе | C21: Токтасбаев Бейбарыс Ералиевич | E21: 1 | G21: 44907 | H21: 30 | I21: =H21*17697 -> 530910 | J21: =I21*10% -> 53091 | S21: =SUM(J21:R21) -> 53091 | T21: =I21+S21 -> 584001 | U21: =T21*10% -> 58400.1 | V21: =((T21-U21-W21)-(14*4325))*10% -> 45337.088 | W21: =T21*2% -> 11680.02 | X21: =T21-U21-V21-W21 -> 468583.79 | Y21: =T21*12 -> 7008012 | Z21: =I21*2 -> 1061820 | AA21: =Y21+Z21 -> 8069832 | AB21: =AA21*3.5% -> 282444.12 | AC21: =(AA21*0.9-(W21*12))*11%-AD21 -> 420353.3 | AD21: =AA21*0.9*5% -> 363142.44 | AE21: =AA21*3% -> 242094.96 | AF21: =AA21+AC21+AD21+AE21+AB21 -> 9377866.8 | AG21: РБ
A22: =A21+1 -> 4 | B22: Заместитель директора по воспитательной работе | C22: Жасыбаева Лазат Карбозовна | D22: 2 | E22: 1 | G22: 44844 | H22: 30 | I22: =H22*17697 -> 530910 | J22: =I22*10% -> 53091 | S22: =SUM(J22:R22) -> 53091 | T22: =I22+S22 -> 584001 | U22: =T22*10% -> 58400.1 | V22: =((T22-U22-W22)-(14*4325))*10% -> 45337.088 | W22: =T22*2% -> 11680.02 | X22: =T22-U22-V22-W22 -> 468583.79 | Y22: =T22*12 -> 7008012 | Z22: =I22*2 -> 1061820 | AA22: =Y22+Z22 -> 8069832 | AB22: =AA22*3.5% -> 282444.12 | AC22: =(AA22*0.9-(W22*12))*11%-AD22 -> 420353.3 | AD22: =AA22*0.9*5% -> 363142.44 | AE22: =AA22*3% -> 242094.96 | AF22: =AA22+AC22+AD22+AE22+AB22 -> 9377866.8 | AG22: РБ
A23: =A22+1 -> 5 | B23: Заместитель директора по воспитательной работе | C23: Таукебаев Куаныш Муратбекович | E23: 1 | G23: 44805 | H23: 30 | I23: =H23*17697 -> 530910 | J23: =I23*10% -> 53091 | S23: =SUM(J23:R23) -> 53091 | T23: =I23+S23 -> 584001 | U23: =T23*10% -> 58400.1 | V23: =((T23-U23-W23)-(14*4325))*10% -> 45337.088 | W23: =T23*2% -> 11680.02 | X23: =T23-U23-V23-W23 -> 468583.79 | Y23: =T23*12 -> 7008012 | Z23: =I23*2 -> 1061820 | AA23: =Y23+Z23 -> 8069832 | AB23: =AA23*3.5% -> 282444.12 | AC23: =(AA23*0.9-(W23*12))*11%-AD23 -> 420353.3 | AD23: =AA23*0.9*5% -> 363142.44 | AE23: =AA23*3% -> 242094.96 | AF23: =AA23+AC23+AD23+AE23+AB23 -> 9377866.8 | AG23: РБ
A24: =A23+1 -> 6 | B24: Заместитель директора по профильно- экспериментальной работе | C24: Бегимбетов Талгат Полатович | D24: 1 | E24: 1 | G24: 45216 | H24: 30 | I24: =H24*17697 -> 530910 | J24: =I24*10% -> 53091 | S24: =SUM(J24:R24) -> 53091 | T24: =I24+S24 -> 584001 | U24: =T24*10% -> 58400.1 | V24: =((T24-U24-W24)-(14*4325))*10% -> 45337.088 | W24: =T24*2% -> 11680.02 | X24: =T24-U24-V24-W24 -> 468583.79 | Y24: =T24*12 -> 7008012 | Z24: =I24*2 -> 1061820 | AA24: =Y24+Z24 -> 8069832 | AB24: =AA24*3.5% -> 282444.12 | AC24: =(AA24*0.9-(W24*12))*11%-AD24 -> 420353.3 | AD24: =AA24*0.9*5% -> 363142.44 | AE24: =AA24*3% -> 242094.96 | AF24: =AA24+AC24+AD24+AE24+AB24 -> 9377866.8 | AG24: РБ
A25: =A24+1 -> 7 | B25: Заместитель директора по научно-методической работе | C25: Аубакирова Гульнур Габдувна | D25: 1 | E25: 1 | G25: 43355 | H25: 32 | I25: =H25*17697 -> 566304 | J25: =I25*10% -> 56630.4 | S25: =SUM(J25:R25) -> 56630.4 | T25: =I25+S25 -> 622934.4 | U25: =T25*10% -> 62293.44 | V25: =((T25-U25-W25)-(14*4325))*10% -> 48763.227 | W25: =T25*2% -> 12458.688 | X25: =T25-U25-V25-W25 -> 499419.04 | Y25: =T25*12 -> 7475212.8 | Z25: =I25*2 -> 1132608 | AA25: =Y25+Z25 -> 8607820.8 | AB25: =AA25*3.5% -> 301273.73 | AC25: =(AA25*0.9-(W25*12))*11%-AD25 -> 448376.86 | AD25: =AA25*0.9*5% -> 387351.94 | AE25: =AA25*3% -> 258234.62 | AF25: =AA25+AC25+AD25+AE25+AB25 -> 10003058 | AG25: РБ
B26: ИТОГО АУП пед работники | D26: =SUM(D19:D25) -> 7 | E26: =SUM(E19:E25) -> 7 | F26: =SUM(F19:F25) -> 0 | I26: =SUM(I19:I25) -> 4672008 | J26: =SUM(J19:J25) -> 467200.8 | K26: =SUM(K19:K25) -> 0 | L26: =SUM(L19:L25) -> 0 | M26: =SUM(M19:M25) -> 0 | N26: =SUM(N19:N25) -> 0 | O26: =SUM(O19:O25) -> 0 | P26: =SUM(P19:P25) -> 0 | ... AF26: =SUM(AF19:AF25) -> 82525228
A27: =A25+1 -> 8 | B27: Заместитель директора по административно-хозяйственной работе | C27: Алин Береке Адильханович | D27: 2 | E27: 1 | G27: 42263 | H27: 35 | I27: =H27*17697 -> 619395 | J27: =I27*10% -> 61939.5 | S27: =SUM(J27:R27) -> 61939.5 | T27: =I27+S27 -> 681334.5 | U27: =T27*10% -> 68133.45 | V27: =((T27-U27-W27)-(14*4325))*10% -> 53902.436 | W27: =T27*2% -> 13626.69 | X27: =T27-U27-V27-W27 -> 545671.92 | Y27: =T27*12 -> 8176014 | Z27: =I27*2 -> 1238790 | AA27: =Y27+Z27 -> 9414804 | AB27: =AA27*3.5% -> 329518.14 | AC27: =(AA27*0.9-(W27*12))*11%-AD27 -> 490412.19 | AD27: =AA27*0.9*5% -> 423666.18 | AE27: =AA27*3% -> 282444.12 | AF27: =AA27+AC27+AD27+AE27+AB27 -> 10940845 | AG27: РБ
A28: =A27+1 -> 9 | B28: Заведующий по хозяйственной работе | C28: Камбарбаев Айдын Майсаканович | E28: 1 | G28: 44106 | H28: 24 | I28: =H28*17697 -> 424728 | J28: =I28*10% -> 42472.8 | S28: =SUM(J28:R28) -> 42472.8 | T28: =I28+S28 -> 467200.8 | U28: =T28*10% -> 46720.08 | V28: =((T28-U28-W28)-(14*4325))*10% -> 35058.67 | W28: =T28*2% -> 9344.016 | X28: =T28-U28-V28-W28 -> 376078.03 | Y28: =T28*12 -> 5606409.6 | Z28: =I28*2 -> 849456 | AA28: =Y28+Z28 -> 6455865.6 | AB28: =AA28*3.5% -> 225955.3 | AC28: =(AA28*0.9-(W28*12))*11%-AD28 -> 336282.64 | AD28: =AA28*0.9*5% -> 290513.95 | AE28: =AA28*3% -> 193675.97 | AF28: =AA28+AC28+AD28+AE28+AB28 -> 7502293.5 | AG28: РБ
A29: =A28+1 -> 10 | B29: Экономист | C29: Куюкова Гаухар Ермековна | D29: 1 | E29: 1 | G29: 44853 | H29: 30 | I29: =H29*17697 -> 530910 | J29: =I29*10% -> 53091 | S29: =SUM(J29:R29) -> 53091 | T29: =I29+S29 -> 584001 | U29: =T29*10% -> 58400.1 | V29: =((T29-U29-W29)-(14*4325))*10% -> 45337.088 | W29: =T29*2% -> 11680.02 | X29: =T29-U29-V29-W29 -> 468583.79 | Y29: =T29*12 -> 7008012 | Z29: =I29*2 -> 1061820 | AA29: =Y29+Z29 -> 8069832 | AB29: =AA29*3.5% -> 282444.12 | AC29: =(AA29*0.9-(W29*12))*11%-AD29 -> 420353.3 | AD29: =AA29*0.9*5% -> 363142.44 | AE29: =AA29*3% -> 242094.96 | AF29: =AA29+AC29+AD29+AE29+AB29 -> 9377866.8 | AG29: РБ
A30: =A29+1 -> 11 | B30: Главный бухгалтер | C30: Абулова Жулдыз Муратовна | D30: 1 | E30: 1 | G30: 43710 | H30: 35 | I30: =H30*17697 -> 619395 | J30: =I30*10% -> 61939.5 | S30: =SUM(J30:R30) -> 61939.5 | T30: =I30+S30 -> 681334.5 | U30: =T30*10% -> 68133.45 | V30: =((T30-U30-W30)-(14*4325))*10% -> 53902.436 | W30: =T30*2% -> 13626.69 | X30: =T30-U30-V30-W30 -> 545671.92 | Y30: =T30*12 -> 8176014 | Z30: =I30*2 -> 1238790 | AA30: =Y30+Z30 -> 9414804 | AB30: =AA30*3.5% -> 329518.14 | AC30: =(AA30*0.9-(W30*12))*11%-AD30 -> 490412.19 | AD30: =AA30*0.9*5% -> 423666.18 | AE30: =AA30*3% -> 282444.12 | AF30: =AA30+AC30+AD30+AE30+AB30 -> 10940845 | AG30: РБ
A31: =A30+1 -> 12 | B31: Старший бухгалтер | C31: Қожамқұлова Жанна Пірмағанбетқызы | D31: 1 | E31: 1 | G31: 44105 | H31: 30 | I31: =H31*17697 -> 530910 | J31: =I31*10% -> 53091 | S31: =SUM(J31:R31) -> 53091 | T31: =I31+S31 -> 584001 | U31: =T31*10% -> 58400.1 | V31: =((T31-U31-W31)-(14*4325))*10% -> 45337.088 | W31: =T31*2% -> 11680.02 | X31: =T31-U31-V31-W31 -> 468583.79 | Y31: =T31*12 -> 7008012 | Z31: =I31*2 -> 1061820 | AA31: =Y31+Z31 -> 8069832 | AB31: =AA31*3.5% -> 282444.12 | AC31: =(AA31*0.9-(W31*12))*11%-AD31 -> 420353.3 | AD31: =AA31*0.9*5% -> 363142.44 | AE31: =AA31*3% -> 242094.96 | AF31: =AA31+AC31+AD31+AE31+AB31 -> 9377866.8 | AG31: РБ
A32: =A31+1 -> 13 | B32: Бухгалтер | C32: Сабирова Гулжан Саухановна | D32: 2 | E32: 1 | G32: 44939 | H32: 23 | I32: =H32*17697 -> 407031 | J32: =I32*10% -> 40703.1 | S32: =SUM(J32:R32) -> 40703.1 | T32: =I32+S32 -> 447734.1 | U32: =T32*10% -> 44773.41 | V32: =((T32-U32-W32)-(14*4325))*10% -> 33345.601 | W32: =T32*2% -> 8954.682 | X32: =T32-U32-V32-W32 -> 360660.41 | Y32: =T32*12 -> 5372809.2 | Z32: =I32*2 -> 814062 | AA32: =Y32+Z32 -> 6186871.2 | AB32: =AA32*3.5% -> 216540.49 | AC32: =(AA32*0.9-(W32*12))*11%-AD32 -> 322270.86 | AD32: =AA32*0.9*5% -> 278409.2 | AE32: =AA32*3% -> 185606.14 | AF32: =AA32+AC32+AD32+AE32+AB32 -> 7189697.9 | AG32: РБ
A33: =A32+1 -> 14 | B33: Бухгалтер | C33: Каныбетова Балжан Сериковна | E33: 1 | G33: 41860 | H33: 23 | I33: =H33*17697 -> 407031 | J33: =I33*10% -> 40703.1 | S33: =SUM(J33:R33) -> 40703.1 | T33: =I33+S33 -> 447734.1 | U33: =T33*10% -> 44773.41 | V33: =((T33-U33-W33)-(14*4325))*10% -> 33345.601 | W33: =T33*2% -> 8954.682 | X33: =T33-U33-V33-W33 -> 360660.41 | Y33: =T33*12 -> 5372809.2 | Z33: =I33*2 -> 814062 | AA33: =Y33+Z33 -> 6186871.2 | AB33: =AA33*3.5% -> 216540.49 | AC33: =(AA33*0.9-(W33*12))*11%-AD33 -> 322270.86 | AD33: =AA33*0.9*5% -> 278409.2 | AE33: =AA33*3% -> 185606.14 | AF33: =AA33+AC33+AD33+AE33+AB33 -> 7189697.9 | AG33: РБ
A34: =A33+1 -> 15 | B34: Специалист по закупкам | C34: Жанабилов Жандос Ерболатович | D34: 1 | E34: 1 | G34: 45019 | H34: 28 | I34: =H34*17697 -> 495516 | J34: =I34*10% -> 49551.6 | S34: =SUM(J34:R34) -> 49551.6 | T34: =I34+S34 -> 545067.6 | U34: =T34*10% -> 54506.76 | V34: =((T34-U34-W34)-(14*4325))*10% -> 41910.949 | W34: =T34*2% -> 10901.352 | X34: =T34-U34-V34-W34 -> 437748.54 | Y34: =T34*12 -> 6540811.2 | Z34: =I34*2 -> 991032 | AA34: =Y34+Z34 -> 7531843.2 | AB34: =AA34*3.5% -> 263614.51 | AC34: =(AA34*0.9-(W34*12))*11%-AD34 -> 392329.75 | AD34: =AA34*0.9*5% -> 338932.94 | AE34: =AA34*3% -> 225955.3 | AF34: =AA34+AC34+AD34+AE34+AB34 -> 8752675.7 | AG34: РБ
A35: =A34+1 -> 16 | B35: Юрист | C35: Токсеитова Гульмира Назымбековна | D35: 1 | E35: 1 | G35: 45232 | H35: 28 | I35: =H35*17697 -> 495516 | J35: =I35*10% -> 49551.6 | S35: =SUM(J35:R35) -> 49551.6 | T35: =I35+S35 -> 545067.6 | U35: =T35*10% -> 54506.76 | V35: =((T35-U35-W35)-(14*4325))*10% -> 41910.949 | W35: =T35*2% -> 10901.352 | X35: =T35-U35-V35-W35 -> 437748.54 | Y35: =T35*12 -> 6540811.2 | Z35: =I35*2 -> 991032 | AA35: =Y35+Z35 -> 7531843.2 | AB35: =AA35*3.5% -> 263614.51 | AC35: =(AA35*0.9-(W35*12))*11%-AD35 -> 392329.75 | AD35: =AA35*0.9*5% -> 338932.94 | AE35: =AA35*3% -> 225955.3 | AF35: =AA35+AC35+AD35+AE35+AB35 -> 8752675.7 | AG35: РБ
A36: =A35+1 -> 17 | B36: Инспектор по кадрам | C36: Асылова Куралай Мухаметкалиевна | D36: 1 | E36: 1 | G36: 42980 | H36: 25 | I36: =H36*17697 -> 442425 | J36: =I36*10% -> 44242.5 | S36: =SUM(J36:R36) -> 44242.5 | T36: =I36+S36 -> 486667.5 | U36: =T36*10% -> 48666.75 | V36: =((T36-U36-W36)-(14*4325))*10% -> 36771.74 | W36: =T36*2% -> 9733.35 | X36: =T36-U36-V36-W36 -> 391495.66 | Y36: =T36*12 -> 5840010 | Z36: =I36*2 -> 884850 | AA36: =Y36+Z36 -> 6724860 | AB36: =AA36*3.5% -> 235370.1 | AC36: =(AA36*0.9-(W36*12))*11%-AD36 -> 350294.42 | AD36: =AA36*0.9*5% -> 302618.7 | AE36: =AA36*3% -> 201745.8 | AF36: =AA36+AC36+AD36+AE36+AB36 -> 7814889 | AG36: РБ
A37: =A36+1 -> 18 | B37: Секретарь | C37: Жупбаева Жулдуз Ибраимовна | D37: 1 | E37: 1 | G37: 44305 | H37: 22 | I37: =H37*17697 -> 389334 | J37: =I37*10% -> 38933.4 | S37: =SUM(J37:R37) -> 38933.4 | T37: =I37+S37 -> 428267.4 | U37: =T37*10% -> 42826.74 | V37: =((T37-U37-W37)-(14*4325))*10% -> 31632.531 | W37: =T37*2% -> 8565.348 | X37: =T37-U37-V37-W37 -> 345242.78 | Y37: =T37*12 -> 5139208.8 | Z37: =I37*2 -> 778668 | AA37: =Y37+Z37 -> 5917876.8 | AB37: =AA37*3.5% -> 207125.69 | AC37: =(AA37*0.9-(W37*12))*11%-AD37 -> 308259.09 | AD37: =AA37*0.9*5% -> 266304.46 | AE37: =AA37*3% -> 177536.3 | AF37: =AA37+AC37+AD37+AE37+AB37 -> 6877102.3 | AG37: РБ
A38: =A37+1 -> 19 | B38: Архивариус | C38: Ермеккалиева Тлектес Сансизбаевна | D38: 1 | E38: 1 | G38: 42888 | H38: 13 | I38: =H38*17697 -> 230061 | J38: =I38*10% -> 23006.1 | S38: =SUM(J38:R38) -> 23006.1 | T38: =I38+S38 -> 253067.1 | U38: =T38*10% -> 25306.71 | V38: =((T38-U38-W38)-(14*4325))*10% -> 16214.905 | W38: =T38*2% -> 5061.342 | X38: =T38-U38-V38-W38 -> 206484.14 | Y38: =T38*12 -> 3036805.2 | Z38: =I38*2 -> 460122 | AA38: =Y38+Z38 -> 3496927.2 | AB38: =AA38*3.5% -> 122392.45 | AC38: =(AA38*0.9-(W38*12))*11%-AD38 -> 182153.1 | AD38: =AA38*0.9*5% -> 157361.72 | AE38: =AA38*3% -> 104907.82 | AF38: =AA38+AC38+AD38+AE38+AB38 -> 4063742.3 | AG38: РБ
B39: ИТОГО АУП без пед .работников | D39: =SUM(D27:D38) -> 12 | E39: =SUM(E27:E38) -> 12 | I39: =SUM(I27:I38) -> 5592252 | J39: =SUM(J27:J38) -> 559225.2 | K39: =SUM(K27:K38) -> 0 | L39: =SUM(L27:L38) -> 0 | M39: =SUM(M27:M38) -> 0 | N39: =SUM(N27:N38) -> 0 | O39: =SUM(O27:O38) -> 0 | P39: =SUM(P27:P38) -> 0 | ... AF39: =SUM(AF27:AF38) -> 98780197
B40: ВСЕГО по АУП | D40: =D26+D39 -> 19 | E40: =E26+E39 -> 19 | I40: =I26+I39 -> 10264260 | J40: =J26+J39 -> 1026426 | K40: =K26+K39 -> 0 | L40: =L26+L39 -> 0 | M40: =M26+M39 -> 0 | N40: =N26+N39 -> 0 | O40: =O26+O39 -> 0 | P40: =P26+P39 -> 0 | ... AF40: =AF26+AF39 -> 1.8130543e+08
A41: Учебно-вспомогательный персонал (УВП)
A42: =A38+1 -> 20 | B42: Консультант по профессиональной ориентации | C42: Амангельдина Айгерім Санатқызы | D42: 4 | E42: 1 | F42: 17697 | G42: 45902 | H42: 32 | I42: =E42*17697*H42 -> 566304 | J42: =I42*10% -> 56630.4 | S42: =SUM(J42:R42) -> 56630.4 | T42: =I42+S42 -> 622934.4 | U42: =T42*10% -> 62293.44 | V42: =((T42-U42-W42)-(14*4325))*10% -> 48763.227 | W42: =T42*2% -> 12458.688 | X42: =T42-U42-V42-W42 -> 499419.04 | Y42: =T42*12 -> 7475212.8 | Z42: =I42*2 -> 1132608 | AA42: =Y42+Z42 -> 8607820.8 | AB42: =AA42*3.5% -> 301273.73 | AC42: =(AA42*0.9-(W42*12))*11%-AD42 -> 448376.86 | AD42: =AA42*0.9*5% -> 387351.94 | AE42: =AA42*3% -> 258234.62 | AF42: =AA42+AC42+AD42+AE42+AB42 -> 10003058 | AG42: РБ
A43: =A42+1 -> 21 | B43: Консультант по профессиональной ориентации | C43: Вакансия-1 | F43: 17697 | G43: 45300 | H43: 70 | I43: =17697*H43 -> 1238790 | J43: =I43*10% -> 123879 | S43: =SUM(J43:R43) -> 123879 | T43: =I43+S43 -> 1362669 | U43: =T43*10% -> 136266.9 | V43: =((T43-U43-W43)-(14*4325))*10% -> 113859.87 | W43: =T43*2% -> 27253.38 | X43: =T43-U43-V43-W43 -> 1085288.8 | Y43: =T43*12 -> 16352028 | Z43: =I43*2 -> 2477580 | AA43: =Y43+Z43 -> 18829608 | AB43: =AA43*3.5% -> 659036.28 | AC43: =(AA43*0.9-(W43*12))*11%-AD43 -> 980824.37 | AD43: =AA43*0.9*5% -> 847332.36 | AE43: =AA43*3% -> 564888.24 | AF43: =AA43+AC43+AD43+AE43+AB43 -> 21881689 | AG43: РБ
A44: =A43+1 -> 22 | B44: Консультант по профессиональной ориентации | C44: Мақашева Нұрила Болатқызы | E44: 1 | F44: 17697 | G44: 45902 | H44: 32 | I44: =17697*H44 -> 566304 | J44: =I44*10% -> 56630.4 | S44: =SUM(J44:R44) -> 56630.4 | T44: =I44+S44 -> 622934.4 | U44: =T44*10% -> 62293.44 | V44: =((T44-U44-W44)-(14*4325))*10% -> 48763.227 | W44: =T44*2% -> 12458.688 | X44: =T44-U44-V44-W44 -> 499419.04 | Y44: =T44*12 -> 7475212.8 | Z44: =I44*2 -> 1132608 | AA44: =Y44+Z44 -> 8607820.8 | AB44: =AA44*3.5% -> 301273.73 | AC44: =(AA44*0.9-(W44*12))*11%-AD44 -> 448376.86 | AD44: =AA44*0.9*5% -> 387351.94 | AE44: =AA44*3% -> 258234.62 | AF44: =AA44+AC44+AD44+AE44+AB44 -> 10003058 | AG44: РБ
A45: =A44+1 -> 23 | B45: Консультант по профессиональной ориентации | C45: Муратова Алина Кабыловна | E45: 1 | F45: 17697 | G45: 45902 | H45: 27 | I45: =17697*H45 -> 477819 | J45: =I45*10% -> 47781.9 | S45: =SUM(J45:R45) -> 47781.9 | T45: =I45+S45 -> 525600.9 | U45: =T45*10% -> 52560.09 | V45: =((T45-U45-W45)-(14*4325))*10% -> 40197.879 | W45: =T45*2% -> 10512.018 | X45: =T45-U45-V45-W45 -> 422330.91 | Y45: =T45*12 -> 6307210.8 | Z45: =I45*2 -> 955638 | AA45: =Y45+Z45 -> 7262848.8 | AB45: =AA45*3.5% -> 254199.71 | AC45: =(AA45*0.9-(W45*12))*11%-AD45 -> 378317.97 | AD45: =AA45*0.9*5% -> 326828.2 | AE45: =AA45*3% -> 217885.46 | AF45: =AA45+AC45+AD45+AE45+AB45 -> 8440080.1 | AG45: РБ
A46: =A45+1 -> 24 | B46: Менеджер УР | C46: Ахметова Алия Нуртаевна | D46: 6 | E46: 1 | F46: 17697 | G46: 43078 | H46: 22 | I46: =E46*17697*H46 -> 389334 | J46: =I46*10% -> 38933.4 | S46: =SUM(J46:R46) -> 38933.4 | T46: =I46+S46 -> 428267.4 | U46: =T46*10% -> 42826.74 | V46: =((T46-U46-W46)-(14*4325))*10% -> 31632.531 | W46: =T46*2% -> 8565.348 | X46: =T46-U46-V46-W46 -> 345242.78 | Y46: =T46*12 -> 5139208.8 | Z46: =I46*2 -> 778668 | AA46: =Y46+Z46 -> 5917876.8 | AB46: =AA46*3.5% -> 207125.69 | AC46: =(AA46*0.9-(W46*12))*11%-AD46 -> 308259.09 | AD46: =AA46*0.9*5% -> 266304.46 | AE46: =AA46*3% -> 177536.3 | AF46: =AA46+AC46+AD46+AE46+AB46 -> 6877102.3 | AG46: РБ
A47: =A46+1 -> 25 | B47: Менеджер УР | C47: Абдыкаримова Акерке Маратовна | E47: 1 | F47: 17697 | G47: 45891 | H47: 17 | I47: =E47*17697*H47 -> 300849 | J47: =I47*10% -> 30084.9 | S47: =SUM(J47:R47) -> 30084.9 | T47: =I47+S47 -> 330933.9 | U47: =T47*10% -> 33093.39 | V47: =((T47-U47-W47)-(14*4325))*10% -> 23067.183 | W47: =T47*2% -> 6618.678 | X47: =T47-U47-V47-W47 -> 268154.65 | Y47: =T47*12 -> 3971206.8 | Z47: =I47*2 -> 601698 | AA47: =Y47+Z47 -> 4572904.8 | AB47: =AA47*3.5% -> 160051.67 | AC47: =(AA47*0.9-(W47*12))*11%-AD47 -> 238200.2 | AD47: =AA47*0.9*5% -> 205780.72 | AE47: =AA47*3% -> 137187.14 | AF47: =AA47+AC47+AD47+AE47+AB47 -> 5314124.5 | AG47: РБ
A48: =A47+1 -> 26 | B48: Менеджер УР | C48: Нусибақын Аружан Ерболқызы | E48: 1 | F48: 17697 | G48: 45904 | H48: 17 | I48: =E48*17697*H48 -> 300849 | J48: =I48*10% -> 30084.9 | S48: =SUM(J48:R48) -> 30084.9 | T48: =I48+S48 -> 330933.9 | U48: =T48*10% -> 33093.39 | V48: =((T48-U48-W48)-(14*4325))*10% -> 23067.183 | W48: =T48*2% -> 6618.678 | X48: =T48-U48-V48-W48 -> 268154.65 | Y48: =T48*12 -> 3971206.8 | Z48: =I48*2 -> 601698 | AA48: =Y48+Z48 -> 4572904.8 | AB48: =AA48*3.5% -> 160051.67 | AC48: =(AA48*0.9-(W48*12))*11%-AD48 -> 238200.2 | AD48: =AA48*0.9*5% -> 205780.72 | AE48: =AA48*3% -> 137187.14 | AF48: =AA48+AC48+AD48+AE48+AB48 -> 5314124.5 | AG48: РБ
A49: =A48+1 -> 27 | B49: Менеджер УР | C49: Вакансия-2 | F49: 17697 | H49: 35 | I49: =2*17697*H49 -> 1238790 | J49: =I49*10% -> 123879 | S49: =SUM(J49:R49) -> 123879 | T49: =I49+S49 -> 1362669 | U49: =T49*10% -> 136266.9 | V49: =((T49-U49-W49)-(14*4325))*10% -> 113859.87 | W49: =T49*2% -> 27253.38 | X49: =T49-U49-V49-W49 -> 1085288.8 | Y49: =T49*12 -> 16352028 | Z49: =I49*2 -> 2477580 | AA49: =Y49+Z49 -> 18829608 | AB49: =AA49*3.5% -> 659036.28 | AC49: =(AA49*0.9-(W49*12))*11%-AD49+5000000 -> 5980824.4 | AD49: =AA49*0.9*5% -> 847332.36 | AE49: =AA49*3% -> 564888.24 | AF49: =AA49+AC49+AD49+AE49+AB49 -> 26881689 | AG49: РБ
A50: =#REF!+1 -> #REF! | B50: Менеджер ВР | C50: Вакансия-1 | F50: 17697 | H50: 35 | I50: =17697*H50 -> 619395 | J50: =I50*10% -> 61939.5 | S50: =SUM(J50:R50) -> 61939.5 | T50: =I50+S50 -> 681334.5 | U50: =T50*10% -> 68133.45 | V50: =((T50-U50-W50)-(14*4325))*10% -> 53902.436 | W50: =T50*2% -> 13626.69 | X50: =T50-U50-V50-W50 -> 545671.92 | Y50: =T50*12 -> 8176014 | Z50: =I50*2 -> 1238790 | AA50: =Y50+Z50 -> 9414804 | AB50: =AA50*3.5% -> 329518.14 | AC50: =(AA50*0.9-(W50*12))*11%-AD50+5000000 -> 5490412.2 | AD50: =AA50*0.9*5% -> 423666.18 | AE50: =AA50*3% -> 282444.12 | AF50: =AA50+AC50+AD50+AE50+AB50 -> 15940845 | AG50: РБ
A51: =A50+1 -> #REF! | B51: Педагог-организатор-куратор | C51: Асадилла Әсем Талғатқызы | D51: 9 | E51: 1 | F51: 17697 | G51: 45519 | H51: 20 | I51: =E51*17697*H51 -> 353940 | J51: =I51*10% -> 35394 | S51: =SUM(J51:R51) -> 35394 | T51: =I51+S51 -> 389334 | U51: =T51*10% -> 38933.4 | V51: =((T51-U51-W51)-(14*4325))*10% -> 28206.392 | W51: =T51*2% -> 7786.68 | X51: =T51-U51-V51-W51 -> 314407.53 | Y51: =T51*12 -> 4672008 | Z51: =I51*2 -> 707880 | AA51: =Y51+Z51 -> 5379888 | AB51: =AA51*3.5% -> 188296.08 | AC51: =(AA51*0.9-(W51*12))*11%-AD51 -> 280235.53 | AD51: =AA51*0.9*5% -> 242094.96 | AE51: =AA51*3% -> 161396.64 | AF51: =AA51+AC51+AD51+AE51+AB51 -> 6251911.2 | AG51: РБ
A52: =A51+1 -> #REF! | B52: Педагог-организатор-куратор | C52: Жәнәбіл Айжан Нышанбайқызы | E52: 1 | F52: 17697 | G52: 45170 | H52: 20 | I52: =E52*17697*H52 -> 353940 | J52: =I52*10% -> 35394 | S52: =SUM(J52:R52) -> 35394 | T52: =I52+S52 -> 389334 | U52: =T52*10% -> 38933.4 | V52: =((T52-U52-W52)-(14*4325))*10% -> 28206.392 | W52: =T52*2% -> 7786.68 | X52: =T52-U52-V52-W52 -> 314407.53 | Y52: =T52*12 -> 4672008 | Z52: =I52*2 -> 707880 | AA52: =Y52+Z52 -> 5379888 | AB52: =AA52*3.5% -> 188296.08 | AC52: =(AA52*0.9-(W52*12))*11%-AD52 -> 280235.53 | AD52: =AA52*0.9*5% -> 242094.96 | AE52: =AA52*3% -> 161396.64 | AF52: =AA52+AC52+AD52+AE52+AB52 -> 6251911.2 | AG52: РБ
A53: =A52+1 -> #REF! | B53: Педагог-организатор-куратор | C53: Маханбет Ақмоншақ Қайратқызы | E53: 1 | F53: 17697 | G53: 45237 | H53: 20 | I53: =E53*17697*H53 -> 353940 | J53: =I53*10% -> 35394 | S53: =SUM(J53:R53) -> 35394 | T53: =I53+S53 -> 389334 | U53: =T53*10% -> 38933.4 | V53: =((T53-U53-W53)-(14*4325))*10% -> 28206.392 | W53: =T53*2% -> 7786.68 | X53: =T53-U53-V53-W53 -> 314407.53 | Y53: =T53*12 -> 4672008 | Z53: =I53*2 -> 707880 | AA53: =Y53+Z53 -> 5379888 | AB53: =AA53*3.5% -> 188296.08 | AC53: =(AA53*0.9-(W53*12))*11%-AD53 -> 280235.53 | AD53: =AA53*0.9*5% -> 242094.96 | AE53: =AA53*3% -> 161396.64 | AF53: =AA53+AC53+AD53+AE53+AB53 -> 6251911.2 | AG53: РБ
A54: =A53+1 -> #REF! | B54: Педагог-организатор-куратор | C54: Нурымова Шолпан Искандировна | E54: 1 | F54: 17697 | G54: 42264 | H54: 22 | I54: =E54*17697*H54 -> 389334 | J54: =I54*10% -> 38933.4 | S54: =SUM(J54:R54) -> 38933.4 | T54: =I54+S54 -> 428267.4 | U54: =T54*10% -> 42826.74 | V54: =((T54-U54-W54)-(14*4325))*10% -> 31632.531 | W54: =T54*2% -> 8565.348 | X54: =T54-U54-V54-W54 -> 345242.78 | Y54: =T54*12 -> 5139208.8 | Z54: =I54*2 -> 778668 | AA54: =Y54+Z54 -> 5917876.8 | AB54: =AA54*3.5% -> 207125.69 | AC54: =(AA54*0.9-(W54*12))*11%-AD54 -> 308259.09 | AD54: =AA54*0.9*5% -> 266304.46 | AE54: =AA54*3% -> 177536.3 | AF54: =AA54+AC54+AD54+AE54+AB54 -> 6877102.3 | AG54: РБ
A55: =A54+1 -> #REF! | B55: Педагог-организатор-куратор | C55: Нусипкожаева Диляра Касымхановна | E55: 1 | F55: 17697 | G55: 45540 | H55: 20 | I55: =E55*17697*H55 -> 353940 | J55: =I55*10% -> 35394 | S55: =SUM(J55:R55) -> 35394 | T55: =I55+S55 -> 389334 | U55: =T55*10% -> 38933.4 | V55: =((T55-U55-W55)-(14*4325))*10% -> 28206.392 | W55: =T55*2% -> 7786.68 | X55: =T55-U55-V55-W55 -> 314407.53 | Y55: =T55*12 -> 4672008 | Z55: =I55*2 -> 707880 | AA55: =Y55+Z55 -> 5379888 | AB55: =AA55*3.5% -> 188296.08 | AC55: =(AA55*0.9-(W55*12))*11%-AD55 -> 280235.53 | AD55: =AA55*0.9*5% -> 242094.96 | AE55: =AA55*3% -> 161396.64 | AF55: =AA55+AC55+AD55+AE55+AB55 -> 6251911.2 | AG55: РБ
A56: =A55+1 -> #REF! | B56: Педагог-организатор-куратор | C56: Оралбаева Ардак Бектасовна | E56: 1 | F56: 17697 | G56: 45537 | H56: 20 | I56: =E56*17697*H56 -> 353940 | J56: =I56*10% -> 35394 | S56: =SUM(J56:R56) -> 35394 | T56: =I56+S56 -> 389334 | U56: =T56*10% -> 38933.4 | V56: =((T56-U56-W56)-(14*4325))*10% -> 28206.392 | W56: =T56*2% -> 7786.68 | X56: =T56-U56-V56-W56 -> 314407.53 | Y56: =T56*12 -> 4672008 | Z56: =I56*2 -> 707880 | AA56: =Y56+Z56 -> 5379888 | AB56: =AA56*3.5% -> 188296.08 | AC56: =(AA56*0.9-(W56*12))*11%-AD56 -> 280235.53 | AD56: =AA56*0.9*5% -> 242094.96 | AE56: =AA56*3% -> 161396.64 | AF56: =AA56+AC56+AD56+AE56+AB56 -> 6251911.2 | AG56: РБ
A57: =A56+1 -> #REF! | B57: Педагог-организатор-куратор | C57: Сайлауханқызы Зарина | E57: 1 | F57: 17697 | G57: 40788 | H57: 22 | I57: =E57*17697*H57 -> 389334 | J57: =I57*10% -> 38933.4 | S57: =SUM(J57:R57) -> 38933.4 | T57: =I57+S57 -> 428267.4 | U57: =T57*10% -> 42826.74 | V57: =((T57-U57-W57)-(14*4325))*10% -> 31632.531 | W57: =T57*2% -> 8565.348 | X57: =T57-U57-V57-W57 -> 345242.78 | Y57: =T57*12 -> 5139208.8 | Z57: =I57*2 -> 778668 | AA57: =Y57+Z57 -> 5917876.8 | AB57: =AA57*3.5% -> 207125.69 | AC57: =(AA57*0.9-(W57*12))*11%-AD57 -> 308259.09 | AD57: =AA57*0.9*5% -> 266304.46 | AE57: =AA57*3% -> 177536.3 | AF57: =AA57+AC57+AD57+AE57+AB57 -> 6877102.3 | AG57: РБ
A58: =A57+1 -> #REF! | B58: Педагог-организатор-куратор | C58: Вакансия -2 | F58: 17697 | H58: 35 | I58: =2*17697*H58 -> 1238790 | J58: =I58*10% -> 123879 | S58: =SUM(J58:R58) -> 123879 | T58: =I58+S58 -> 1362669 | U58: =T58*10% -> 136266.9 | V58: =((T58-U58-W58)-(14*4325))*10% -> 113859.87 | W58: =T58*2% -> 27253.38 | X58: =T58-U58-V58-W58 -> 1085288.8 | Y58: =T58*12 -> 16352028 | Z58: =I58*2 -> 2477580 | AA58: =Y58+Z58 -> 18829608 | AB58: =AA58*3.5% -> 659036.28 | AC58: =(AA58*0.9-(W58*12))*11%-AD58+8552148.25-1392421.81 -> 8140550.8 | AD58: =AA58*0.9*5% -> 847332.36 | AE58: =AA58*3% -> 564888.24 | AF58: =AA58+AC58+AD58+AE58+AB58 -> 29041416 | AG58: РБ
A59: =#REF!+1 -> #REF! | B59: Педагог дополнительного образования | C59: Вакансия-1,75 | D59: 4.75 | F59: 17697 | H59: 40 | I59: =1.75*17697*H59 -> 1238790 | J59: =I59*10% -> 123879 | S59: =SUM(J59:R59) -> 123879 | T59: =I59+S59 -> 1362669 | U59: =T59*10% -> 136266.9 | V59: =((T59-U59-W59)-(14*4325))*10% -> 113859.87 | W59: =T59*2% -> 27253.38 | X59: =T59-U59-V59-W59 -> 1085288.8 | Y59: =T59*12 -> 16352028 | Z59: =I59*2 -> 2477580 | AA59: =Y59+Z59 -> 18829608 | AB59: =AA59*3.5% -> 659036.28 | AC59: =(AA59*0.9-(W59*12))*11%-AD59 -> 980824.37 | AD59: =AA59*0.9*5% -> 847332.36 | AE59: =AA59*3% -> 564888.24 | AF59: =AA59+AC59+AD59+AE59+AB59 -> 21881689 | AG59: РБ
A60: =A59+1 -> #REF! | B60: Педагог дополнительного образования | C60: Каирбекова Жанна Нуртолеуовна | E60: 0.5 | F60: 17697 | G60: 44819 | H60: 16 | I60: =E60*17697*H60 -> 141576 | J60: =I60*10% -> 14157.6 | S60: =SUM(J60:R60) -> 14157.6 | T60: =I60+S60 -> 155733.6 | U60: =T60*10% -> 15573.36 | V60: =((T60-U60-W60)-(14*4325))*10% -> 7649.5568 | W60: =T60*2% -> 3114.672 | X60: =T60-U60-V60-W60 -> 129396.01 | Y60: =T60*12 -> 1868803.2 | Z60: =I60*2 -> 283152 | AA60: =Y60+Z60 -> 2151955.2 | AB60: =AA60*3.5% -> 75318.432 | AC60: =(AA60*0.9-(W60*12))*11%-AD60 -> 112094.21 | AD60: =AA60*0.9*5% -> 96837.984 | AE60: =AA60*3% -> 64558.656 | AF60: =AA60+AC60+AD60+AE60+AB60 -> 2500764.5 | AG60: РБ
A61: =A60+1 -> #REF! | B61: Педагог дополнительного образования | C61: Кунгожин Медеубек Аманкельдиевич | E61: 1 | F61: 17697 | G61: 42860 | H61: 24 | I61: =E61*17697*H61 -> 424728 | J61: =I61*10% -> 42472.8 | S61: =SUM(J61:R61) -> 42472.8 | T61: =I61+S61 -> 467200.8 | U61: =T61*10% -> 46720.08 | V61: =((T61-U61-W61)-(14*4325))*10% -> 35058.67 | W61: =T61*2% -> 9344.016 | X61: =T61-U61-V61-W61 -> 376078.03 | Y61: =T61*12 -> 5606409.6 | Z61: =I61*2 -> 849456 | AA61: =Y61+Z61 -> 6455865.6 | AB61: =AA61*3.5% -> 225955.3 | AC61: =(AA61*0.9-(W61*12))*11%-AD61 -> 336282.64 | AD61: =AA61*0.9*5% -> 290513.95 | AE61: =AA61*3% -> 193675.97 | AF61: =AA61+AC61+AD61+AE61+AB61 -> 7502293.5 | AG61: РБ
A62: =A61+1 -> #REF! | B62: Педагог дополнительного образования | C62: Талғатұлы Дәурен | E62: 1 | F62: 17697 | G62: 45183 | H62: 17 | I62: =E62*17697*H62 -> 300849 | J62: =I62*10% -> 30084.9 | S62: =SUM(J62:R62) -> 30084.9 | T62: =I62+S62 -> 330933.9 | U62: =T62*10% -> 33093.39 | V62: =((T62-U62-W62)-(14*4325))*10% -> 23067.183 | W62: =T62*2% -> 6618.678 | X62: =T62-U62-V62-W62 -> 268154.65 | Y62: =T62*12 -> 3971206.8 | Z62: =I62*2 -> 601698 | AA62: =Y62+Z62 -> 4572904.8 | AB62: =AA62*3.5% -> 160051.67 | AC62: =(AA62*0.9-(W62*12))*11%-AD62 -> 238200.2 | AD62: =AA62*0.9*5% -> 205780.72 | AE62: =AA62*3% -> 137187.14 | AF62: =AA62+AC62+AD62+AE62+AB62 -> 5314124.5 | AG62: РБ
A63: =A62+1 -> #REF! | B63: Педагог дополнительного образования | C63: Туреханова Кундуз Моминовна (по совместиттельству) | E63: 0.5 | F63: 17697 | G63: 44774 | H63: 20 | I63: =E63*17697*H63 -> 176970 | J63: =I63*10% -> 17697 | S63: =SUM(J63:R63) -> 17697 | T63: =I63+S63 -> 194667 | U63: =T63*10% -> 19466.7 | V63: =((T63-U63-W63)-(14*4325))*10% -> 11075.696 | W63: =T63*2% -> 3893.34 | X63: =T63-U63-V63-W63 -> 160231.26 | Y63: =T63*12 -> 2336004 | Z63: =I63*2 -> 353940 | AA63: =Y63+Z63 -> 2689944 | AB63: =AA63*3.5% -> 94148.04 | AC63: =(AA63*0.9-(W63*12))*11%-AD63 -> 140117.77 | AD63: =AA63*0.9*5% -> 121047.48 | AE63: =AA63*3% -> 80698.32 | AF63: =AA63+AC63+AD63+AE63+AB63 -> 3125955.6 | AG63: РБ
A64: =A63+1 -> #REF! | B64: Музыкально- художественный руководитель | C64: Сизов Евгений Николаевич | D64: 1 | E64: 1 | F64: 17697 | G64: 44287 | H64: 14 | I64: =E64*17697*H64 -> 247758 | J64: =I64*10% -> 24775.8 | S64: =SUM(J64:R64) -> 24775.8 | T64: =I64+S64 -> 272533.8 | U64: =T64*10% -> 27253.38 | V64: =((T64-U64-W64)-(14*4325))*10% -> 17927.974 | W64: =T64*2% -> 5450.676 | X64: =T64-U64-V64-W64 -> 221901.77 | Y64: =T64*12 -> 3270405.6 | Z64: =I64*2 -> 495516 | AA64: =Y64+Z64 -> 3765921.6 | AB64: =AA64*3.5% -> 131807.26 | AC64: =(AA64*0.9-(W64*12))*11%-AD64 -> 196164.87 | AD64: =AA64*0.9*5% -> 169466.47 | AE64: =AA64*3% -> 112977.65 | AF64: =AA64+AC64+AD64+AE64+AB64 -> 4376337.9 | AG64: РБ
A65: =A64+1 -> #REF! | B65: Педагог-психолог | C65: Динсаламова Бакыткул Мукагалиевна | D65: 4 | E65: 1 | F65: 17697 | G65: 42293 | H65: 25 | I65: =E65*17697*H65 -> 442425 | J65: =I65*10% -> 44242.5 | S65: =SUM(J65:R65) -> 44242.5 | T65: =I65+S65 -> 486667.5 | U65: =T65*10% -> 48666.75 | V65: =((T65-U65-W65)-(14*4325))*10% -> 36771.74 | W65: =T65*2% -> 9733.35 | X65: =T65-U65-V65-W65 -> 391495.66 | Y65: =T65*12 -> 5840010 | Z65: =I65*2 -> 884850 | AA65: =Y65+Z65 -> 6724860 | AB65: =AA65*3.5% -> 235370.1 | AC65: =(AA65*0.9-(W65*12))*11%-AD65 -> 350294.42 | AD65: =AA65*0.9*5% -> 302618.7 | AE65: =AA65*3% -> 201745.8 | AF65: =AA65+AC65+AD65+AE65+AB65 -> 7814889 | AG65: РБ
A66: =A65+1 -> #REF! | B66: Педагог-психолог | C66: Мансурова Румилям Карлиновна | E66: 1 | F66: 17697 | G66: 44908 | H66: 20 | I66: =E66*17697*H66 -> 353940 | J66: =I66*10% -> 35394 | M66: =I66*30% -> 106182 | S66: =SUM(J66:R66) -> 141576 | T66: =I66+S66 -> 495516 | U66: =T66*10% -> 49551.6 | V66: =((T66-U66-W66)-(14*4325))*10% -> 37550.408 | W66: =T66*2% -> 9910.32 | X66: =T66-U66-V66-W66 -> 398503.67 | Y66: =T66*12 -> 5946192 | Z66: =I66*2 -> 707880 | AA66: =Y66+Z66 -> 6654072 | AB66: =AA66*3.5% -> 232892.52 | AC66: =(AA66*0.9-(W66*12))*11%-AD66 -> 346238.27 | AD66: =AA66*0.9*5% -> 299433.24 | AE66: =AA66*3% -> 199622.16 | AF66: =AA66+AC66+AD66+AE66+AB66 -> 7732258.2 | AG66: РБ
A67: =A66+1 -> #REF! | B67: Педагог-психолог | C67: Сеиткали Дидар Мараткызы | E67: 1 | F67: 17697 | G67: 45160 | H67: 19 | I67: =E67*17697*H67 -> 336243 | J67: =I67*10% -> 33624.3 | K67: =10*4325 -> 43250 | S67: =SUM(J67:R67) -> 76874.3 | T67: =I67+S67 -> 413117.3 | U67: =T67*10% -> 41311.73 | V67: =((T67-U67-W67)-(14*4325))*10% -> 30299.322 | W67: =T67*2% -> 8262.346 | X67: =T67-U67-V67-W67 -> 333243.9 | Y67: =T67*12 -> 4957407.6 | Z67: =I67*2 -> 672486 | AA67: =Y67+Z67 -> 5629893.6 | AB67: =AA67*3.5% -> 197046.28 | AC67: =(AA67*0.9-(W67*12))*11%-AD67 -> 293107.96 | AD67: =AA67*0.9*5% -> 253345.21 | AE67: =AA67*3% -> 168896.81 | AF67: =AA67+AC67+AD67+AE67+AB67 -> 6542289.9 | AG67: РБ
A68: =A67+1 -> #REF! | B68: Педагог-психолог | C68: Тлеубердинова Жанат Мураткановна | E68: 1 | F68: 17697 | G68: 43773 | H68: 25 | I68: =E68*17697*H68 -> 442425 | J68: =I68*10% -> 44242.5 | M68: =I68*30% -> 132727.5 | S68: =SUM(J68:R68) -> 176970 | T68: =I68+S68 -> 619395 | U68: =T68*10% -> 61939.5 | V68: =((T68-U68-W68)-(14*4325))*10% -> 48451.76 | W68: =T68*2% -> 12387.9 | X68: =T68-U68-V68-W68 -> 496615.84 | Y68: =T68*12 -> 7432740 | Z68: =I68*2 -> 884850 | AA68: =Y68+Z68 -> 8317590 | AB68: =AA68*3.5% -> 291115.65 | AC68: =(AA68*0.9-(W68*12))*11%-AD68 -> 432797.83 | AD68: =AA68*0.9*5% -> 374291.55 | AE68: =AA68*3% -> 249527.7 | AF68: =AA68+AC68+AD68+AE68+AB68 -> 9665322.7 | AG68: РБ
A69: =A68+1 -> #REF! | B69: Социальный педагог | C69: Дюсупова Зарина Канатпаевна | D69: 1 | E69: 1 | F69: 17697 | G69: 43064 | H69: 22 | I69: =E69*17697*H69 -> 389334 | J69: =I69*10% -> 38933.4 | K69: =10*4325 -> 43250 | M69: =I69*30% -> 116800.2 | S69: =SUM(J69:R69) -> 198983.6 | T69: =I69+S69 -> 588317.6 | U69: =T69*10% -> 58831.76 | V69: =((T69-U69-W69)-(14*4325))*10% -> 45716.949 | W69: =T69*2% -> 11766.352 | X69: =T69-U69-V69-W69 -> 472002.54 | Y69: =T69*12 -> 7059811.2 | Z69: =I69*2 -> 778668 | AA69: =Y69+Z69 -> 7838479.2 | AB69: =AA69*3.5% -> 274346.77 | AC69: =(AA69*0.9-(W69*12))*11%-AD69 -> 407746.29 | AD69: =AA69*0.9*5% -> 352731.56 | AE69: =AA69*3% -> 235154.38 | AF69: =AA69+AC69+AD69+AE69+AB69 -> 9108458.2 | AG69: РБ
A70: =A69+1 -> #REF! | B70: Заведующий библиотекой | C70: Смагулова Нургуль Бактурсыновна | D70: 1 | E70: 1 | F70: 17697 | G70: 42661 | H70: 20 | I70: =E70*17697*H70 -> 353940 | J70: =I70*10% -> 35394 | P70: =17697*30% -> 5309.1 | S70: =SUM(J70:R70) -> 40703.1 | T70: =I70+S70 -> 394643.1 | U70: =T70*10% -> 39464.31 | V70: =((T70-U70-W70)-(14*4325))*10% -> 28673.593 | W70: =T70*2% -> 7892.862 | X70: =T70-U70-V70-W70 -> 318612.34 | Y70: =T70*12 -> 4735717.2 | Z70: =I70*2 -> 707880 | AA70: =Y70+Z70 -> 5443597.2 | AB70: =AA70*3.5% -> 190525.9 | AC70: =(AA70*0.9-(W70*12))*11%-AD70 -> 283535.67 | AD70: =AA70*0.9*5% -> 244961.87 | AE70: =AA70*3% -> 163307.92 | AF70: =AA70+AC70+AD70+AE70+AB70 -> 6325928.6 | AG70: РБ
A71: =A70+1 -> #REF! | B71: Библиотекарь | C71: Алжанова Айжан Копжасаровна | D71: 2 | E71: 1 | F71: 17697 | G71: 34736 | H71: 16 | I71: =E71*17697*H71 -> 283152 | J71: =I71*10% -> 28315.2 | P71: =17697*30% -> 5309.1 | S71: =SUM(J71:R71) -> 33624.3 | T71: =I71+S71 -> 316776.3 | U71: =T71*10% -> 31677.63 | V71: =((T71-U71-W71)-(14*4325))*10% -> 21821.314 | W71: =T71*2% -> 6335.526 | X71: =T71-U71-V71-W71 -> 256941.83 | Y71: =T71*12 -> 3801315.6 | Z71: =I71*2 -> 566304 | AA71: =Y71+Z71 -> 4367619.6 | AB71: =AA71*3.5% -> 152866.69 | AC71: =(AA71*0.9-(W71*12))*11%-AD71 -> 227488.56 | AD71: =AA71*0.9*5% -> 196542.88 | AE71: =AA71*3% -> 131028.59 | AF71: =AA71+AC71+AD71+AE71+AB71 -> 5075546.3 | AG71: РБ
A72: =A71+1 -> #REF! | B72: Библиотекарь | C72: Имангожина Рая Аскергалиевна | E72: 1 | F72: 17697 | G72: 44536 | H72: 16 | I72: =E72*17697*H72 -> 283152 | J72: =I72*10% -> 28315.2 | P72: =17697*30% -> 5309.1 | S72: =SUM(J72:R72) -> 33624.3 | T72: =I72+S72 -> 316776.3 | U72: =T72*10% -> 31677.63 | V72: =((T72-U72-W72)-(14*4325))*10% -> 21821.314 | W72: =T72*2% -> 6335.526 | X72: =T72-U72-V72-W72 -> 256941.83 | Y72: =T72*12 -> 3801315.6 | Z72: =I72*2 -> 566304 | AA72: =Y72+Z72 -> 4367619.6 | AB72: =AA72*3.5% -> 152866.69 | AC72: =(AA72*0.9-(W72*12))*11%-AD72 -> 227488.56 | AD72: =AA72*0.9*5% -> 196542.88 | AE72: =AA72*3% -> 131028.59 | AF72: =AA72+AC72+AD72+AE72+AB72 -> 5075546.3 | AG72: РБ
A73: =A72+1 -> #REF! | B73: Педагог организатор НВП | C73: Атканов Нурлан Аканович | D73: 1 | E73: 0.5 | F73: 17697 | G73: 45903 | H73: 11 | I73: =E73*17697*H73 -> 97333.5 | J73: =I73*10% -> 9733.35 | S73: =SUM(J73:R73) -> 9733.35 | T73: =I73+S73 -> 107066.85 | U73: =T73*10% -> 10706.685 | V73: =((T73-U73-W73)-(14*4325))*10% -> 3366.8828 | W73: =T73*2% -> 2141.337 | X73: =T73-U73-V73-W73 -> 90851.945 | Y73: =T73*12 -> 1284802.2 | Z73: =I73*2 -> 194667 | AA73: =Y73+Z73 -> 1479469.2 | AB73: =AA73*3.5% -> 51781.422 | AC73: =(AA73*0.9-(W73*12))*11%-AD73 -> 77064.772 | AD73: =AA73*0.9*5% -> 66576.114 | AE73: =AA73*3% -> 44384.076 | AF73: =AA73+AC73+AD73+AE73+AB73 -> 1719275.6 | AG73: РБ
A74: =A73+1 -> #REF! | B74: Педагог организатор НВП | C74: Вакансия-0,5 | F74: 17697 | H74: 25 | I74: =0.5*17697*H74 -> 221212.5 | J74: =I74*10% -> 22121.25 | K74: =10*4325 -> 43250 | S74: =SUM(J74:R74) -> 65371.25 | T74: =I74+S74 -> 286583.75 | U74: =T74*10% -> 28658.375 | V74: =((T74-U74-W74)-(14*4325))*10% -> 19164.37 | W74: =T74*2% -> 5731.675 | X74: =T74-U74-V74-W74 -> 233029.33 | Y74: =T74*12 -> 3439005 | Z74: =I74*2 -> 442425 | AA74: =Y74+Z74 -> 3881430 | AB74: =AA74*3.5% -> 135850.05 | AC74: =(AA74*0.9-(W74*12))*11%-AD74 -> 202031.41 | AD74: =AA74*0.9*5% -> 174664.35 | AE74: =AA74*3% -> 116442.9 | AF74: =AA74+AC74+AD74+AE74+AB74 -> 4510418.7 | AG74: РБ
A75: =A74+1 -> #REF! | B75: Системный администратор | C75: Құсатай Серікжан Қалимұратұлы | D75: 1 | E75: 1 | F75: 17697 | G75: 40702 | H75: 24 | I75: =E75*17697*H75 -> 424728 | J75: =I75*10% -> 42472.8 | S75: =SUM(J75:R75) -> 42472.8 | T75: =I75+S75 -> 467200.8 | U75: =T75*10% -> 46720.08 | V75: =((T75-U75-W75)-(14*4325))*10% -> 35058.67 | W75: =T75*2% -> 9344.016 | X75: =T75-U75-V75-W75 -> 376078.03 | Y75: =T75*12 -> 5606409.6 | Z75: =I75*2 -> 849456 | AA75: =Y75+Z75 -> 6455865.6 | AB75: =AA75*3.5% -> 225955.3 | AC75: =(AA75*0.9-(W75*12))*11%-AD75 -> 336282.64 | AD75: =AA75*0.9*5% -> 290513.95 | AE75: =AA75*3% -> 193675.97 | AF75: =AA75+AC75+AD75+AE75+AB75 -> 7502293.5 | AG75: РБ
A76: =A75+1 -> #REF! | B76: Специалист по специальному оборудованию (фото-видео) | C76: Ізбай Арнұр Рысбекұлы | D76: 1 | E76: 1 | F76: 17697 | G76: 44998 | H76: 18 | I76: =E76*17697*H76 -> 318546 | J76: =I76*10% -> 31854.6 | S76: =SUM(J76:R76) -> 31854.6 | T76: =I76+S76 -> 350400.6 | U76: =T76*10% -> 35040.06 | V76: =((T76-U76-W76)-(14*4325))*10% -> 24780.253 | W76: =T76*2% -> 7008.012 | X76: =T76-U76-V76-W76 -> 283572.28 | Y76: =T76*12 -> 4204807.2 | Z76: =I76*2 -> 637092 | AA76: =Y76+Z76 -> 4841899.2 | AB76: =AA76*3.5% -> 169466.47 | AC76: =(AA76*0.9-(W76*12))*11%-AD76 -> 252211.98 | AD76: =AA76*0.9*5% -> 217885.46 | AE76: =AA76*3% -> 145256.98 | AF76: =AA76+AC76+AD76+AE76+AB76 -> 5626720.1 | AG76: РБ
A77: =A76+1 -> #REF! | B77: Специалист по программному обепечению | C77: Альжанов Мадияр Ерғалиұлы | D77: 2 | E77: 1 | F77: 17697 | G77: 43077 | H77: 24 | I77: =E77*17697*H77 -> 424728 | J77: =I77*10% -> 42472.8 | S77: =SUM(J77:R77) -> 42472.8 | T77: =I77+S77 -> 467200.8 | U77: =T77*10% -> 46720.08 | V77: =((T77-U77-W77)-(14*4325))*10% -> 35058.67 | W77: =T77*2% -> 9344.016 | X77: =T77-U77-V77-W77 -> 376078.03 | Y77: =T77*12 -> 5606409.6 | Z77: =I77*2 -> 849456 | AA77: =Y77+Z77 -> 6455865.6 | AB77: =AA77*3.5% -> 225955.3 | AC77: =(AA77*0.9-(W77*12))*11%-AD77 -> 336282.64 | AD77: =AA77*0.9*5% -> 290513.95 | AE77: =AA77*3% -> 193675.97 | AF77: =AA77+AC77+AD77+AE77+AB77 -> 7502293.5 | AG77: РБ
A78: =A77+1 -> #REF! | B78: Специалист по программному обепечению | C78: Вакансия-1 | F78: 17697 | H78: 25 | I78: =17697*H78 -> 442425 | J78: =I78*10% -> 44242.5 | S78: =SUM(J78:R78) -> 44242.5 | T78: =I78+S78 -> 486667.5 | U78: =T78*10% -> 48666.75 | V78: =((T78-U78-W78)-(14*4325))*10% -> 36771.74 | W78: =T78*2% -> 9733.35 | X78: =T78-U78-V78-W78 -> 391495.66 | Y78: =T78*12 -> 5840010 | Z78: =I78*2 -> 884850 | AA78: =Y78+Z78 -> 6724860 | AB78: =AA78*3.5%+2000000 -> 2235370.1 | AC78: =(AA78*0.9-(W78*12))*11%-AD78+5000000 -> 5350294.4 | AD78: =AA78*0.9*5% -> 302618.7 | AE78: =AA78*3% -> 201745.8 | AF78: =AA78+AC78+AD78+AE78+AB78 -> 14814889 | AG78: РБ
A79: =A78+1 -> #REF! | B79: Лаборант | C79: Ахметов Нурали Боранказыұлы | D79: 8 | E79: 1 | F79: 17697 | G79: 45183 | H79: 15 | I79: =E79*17697*H79 -> 265455 | J79: =I79*10% -> 26545.5 | S79: =SUM(J79:R79) -> 26545.5 | T79: =I79+S79 -> 292000.5 | U79: =T79*10% -> 29200.05 | V79: =((T79-U79-W79)-(14*4325))*10% -> 19641.044 | W79: =T79*2% -> 5840.01 | X79: =T79-U79-V79-W79 -> 237319.4 | Y79: =T79*12 -> 3504006 | Z79: =I79*2 -> 530910 | AA79: =Y79+Z79 -> 4034916 | AB79: =AA79*3.5% -> 141222.06 | AC79: =(AA79*0.9-(W79*12))*11%-AD79 -> 210176.65 | AD79: =AA79*0.9*5% -> 181571.22 | AE79: =AA79*3% -> 121047.48 | AF79: =AA79+AC79+AD79+AE79+AB79 -> 4688933.4 | AG79: РБ
A80: =A79+1 -> #REF! | B80: Лаборант | C80: Қуанышбай Айбар Мұратұлы | E80: 0.75 | F80: 17697 | G80: 44890 | H80: 24 | I80: =E80*17697*H80 -> 318546 | J80: =I80*10% -> 31854.6 | S80: =SUM(J80:R80) -> 31854.6 | T80: =I80+S80 -> 350400.6 | U80: =T80*10% -> 35040.06 | V80: =((T80-U80-W80)-(14*4325))*10% -> 24780.253 | W80: =T80*2% -> 7008.012 | X80: =T80-U80-V80-W80 -> 283572.28 | Y80: =T80*12 -> 4204807.2 | Z80: =I80*2 -> 637092 | AA80: =Y80+Z80 -> 4841899.2 | AB80: =AA80*3.5% -> 169466.47 | AC80: =(AA80*0.9-(W80*12))*11%-AD80 -> 252211.98 | AD80: =AA80*0.9*5% -> 217885.46 | AE80: =AA80*3% -> 145256.98 | AF80: =AA80+AC80+AD80+AE80+AB80 -> 5626720.1 | AG80: РБ
A81: =A80+1 -> #REF! | B81: Лаборант | C81: Жамишева Сауле Абрашовна | E81: 0.5 | F81: 17697 | G81: 45562 | H81: 12 | I81: =E81*17697*H81 -> 106182 | J81: =I81*10% -> 10618.2 | S81: =SUM(J81:R81) -> 10618.2 | T81: =I81+S81 -> 116800.2 | U81: =T81*10% -> 11680.02 | V81: =((T81-U81-W81)-(14*4325))*10% -> 4223.4176 | W81: =T81*2% -> 2336.004 | X81: =T81-U81-V81-W81 -> 98560.758 | Y81: =T81*12 -> 1401602.4 | Z81: =I81*2 -> 212364 | AA81: =Y81+Z81 -> 1613966.4 | AB81: =AA81*3.5% -> 56488.824 | AC81: =(AA81*0.9-(W81*12))*11%-AD81 -> 84070.66 | AD81: =AA81*0.9*5% -> 72628.488 | AE81: =AA81*3% -> 48418.992 | AF81: =AA81+AC81+AD81+AE81+AB81 -> 1875573.4 | AG81: РБ
A82: =A81+1 -> #REF! | B82: Лаборант | C82: Тулғанова Аида Әшірәліқызы | E82: 1 | F82: 17697 | G82: 45537 | H82: 15 | I82: =E82*17697*H82 -> 265455 | J82: =I82*10% -> 26545.5 | S82: =SUM(J82:R82) -> 26545.5 | T82: =I82+S82 -> 292000.5 | U82: =T82*10% -> 29200.05 | V82: =((T82-U82-W82)-(14*4325))*10% -> 19641.044 | W82: =T82*2% -> 5840.01 | X82: =T82-U82-V82-W82 -> 237319.4 | Y82: =T82*12 -> 3504006 | Z82: =I82*2 -> 530910 | AA82: =Y82+Z82 -> 4034916 | AB82: =AA82*3.5% -> 141222.06 | AC82: =(AA82*0.9-(W82*12))*11%-AD82 -> 210176.65 | AD82: =AA82*0.9*5% -> 181571.22 | AE82: =AA82*3% -> 121047.48 | AF82: =AA82+AC82+AD82+AE82+AB82 -> 4688933.4 | AG82: РБ
A83: =A82+1 -> #REF! | B83: Лаборант | C83: Алтынбеков Батырхан | E83: 0.75 | F83: 17697 | G83: 45902 | H83: 20 | I83: =E83*17697*H83 -> 265455 | J83: =I83*10% -> 26545.5 | S83: =SUM(J83:R83) -> 26545.5 | T83: =I83+S83 -> 292000.5 | U83: =T83*10% -> 29200.05 | V83: =((T83-U83-W83)-(14*4325))*10% -> 19641.044 | W83: =T83*2% -> 5840.01 | X83: =T83-U83-V83-W83 -> 237319.4 | Y83: =T83*12 -> 3504006 | Z83: =I83*2 -> 530910 | AA83: =Y83+Z83 -> 4034916 | AB83: =AA83*3.5% -> 141222.06 | AC83: =(AA83*0.9-(W83*12))*11%-AD83 -> 210176.65 | AD83: =AA83*0.9*5% -> 181571.22 | AE83: =AA83*3% -> 121047.48 | AF83: =AA83+AC83+AD83+AE83+AB83 -> 4688933.4 | AG83: РБ
A84: =A83+1 -> #REF! | B84: Лаборант | C84: Асқар Аманжол (по совместительству) | E84: 0.75 | F84: 17697 | G84: 45902 | H84: 24 | I84: =E84*17697*H84 -> 318546 | J84: =I84*10% -> 31854.6 | S84: =SUM(J84:R84) -> 31854.6 | T84: =I84+S84 -> 350400.6 | U84: =T84*10% -> 35040.06 | V84: =((T84-U84-W84)-(14*4325))*10% -> 24780.253 | W84: =T84*2% -> 7008.012 | X84: =T84-U84-V84-W84 -> 283572.28 | Y84: =T84*12 -> 4204807.2 | Z84: =I84*2 -> 637092 | AA84: =Y84+Z84 -> 4841899.2 | AB84: =AA84*3.5% -> 169466.47 | AC84: =(AA84*0.9-(W84*12))*11%-AD84 -> 252211.98 | AD84: =AA84*0.9*5% -> 217885.46 | AE84: =AA84*3% -> 145256.98 | AF84: =AA84+AC84+AD84+AE84+AB84 -> 5626720.1 | AG84: РБ
A85: =A84+1 -> #REF! | B85: Лаборант | C85: Меньщиков Андрей Борисович | E85: 1 | F85: 17697 | G85: 45902 | H85: 21 | I85: =E85*17697*H85 -> 371637 | J85: =I85*10% -> 37163.7 | S85: =SUM(J85:R85) -> 37163.7 | T85: =I85+S85 -> 408800.7 | U85: =T85*10% -> 40880.07 | V85: =((T85-U85-W85)-(14*4325))*10% -> 29919.462 | W85: =T85*2% -> 8176.014 | X85: =T85-U85-V85-W85 -> 329825.15 | Y85: =T85*12 -> 4905608.4 | Z85: =I85*2 -> 743274 | AA85: =Y85+Z85 -> 5648882.4 | AB85: =AA85*3.5% -> 197710.88 | AC85: =(AA85*0.9-(W85*12))*11%-AD85 -> 294247.31 | AD85: =AA85*0.9*5% -> 254199.71 | AE85: =AA85*3% -> 169466.47 | AF85: =AA85+AC85+AD85+AE85+AB85 -> 6564506.8 | AG85: РБ
A86: =A85+1 -> #REF! | B86: Лаборант | C86: Рабиғұлова Гүлдана Берікханқызы | E86: 0.5 | F86: 17697 | G86: 45901 | H86: 20 | I86: =E86*17697*H86 -> 176970 | J86: =I86*10% -> 17697 | S86: =SUM(J86:R86) -> 17697 | T86: =I86+S86 -> 194667 | U86: =T86*10% -> 19466.7 | V86: =((T86-U86-W86)-(14*4325))*10% -> 11075.696 | W86: =T86*2% -> 3893.34 | X86: =T86-U86-V86-W86 -> 160231.26 | Y86: =T86*12 -> 2336004 | Z86: =I86*2 -> 353940 | AA86: =Y86+Z86 -> 2689944 | AB86: =AA86*3.5% -> 94148.04 | AC86: =(AA86*0.9-(W86*12))*11%-AD86 -> 140117.77 | AD86: =AA86*0.9*5% -> 121047.48 | AE86: =AA86*3% -> 80698.32 | AF86: =AA86+AC86+AD86+AE86+AB86 -> 3125955.6 | AG86: РБ
A87: =A86+1 -> #REF! | B87: Лаборант | C87: Вакансия-1,75 | F87: 17697 | H87: 25 | I87: =1.75*17697*H87 -> 774243.75 | J87: =I87*10% -> 77424.375 | S87: =SUM(J87:R87) -> 77424.375 | T87: =I87+S87 -> 851668.12 | U87: =T87*10% -> 85166.812 | V87: =((T87-U87-W87)-(14*4325))*10% -> 68891.795 | W87: =T87*2% -> 17033.362 | X87: =T87-U87-V87-W87 -> 680576.15 | Y87: =T87*12 -> 10220018 | Z87: =I87*2 -> 1548487.5 | AA87: =Y87+Z87 -> 11768505 | AB87: =AA87*3.5%+2000000 -> 2411897.7 | AC87: =(AA87*0.9-(W87*12))*11%-AD87+5000000 -> 5613015.2 | AD87: =AA87*0.9*5% -> 529582.72 | AE87: =AA87*3% -> 353055.15 | AF87: =AA87+AC87+AD87+AE87+AB87 -> 20676056 | AG87: РБ
B88: ИТОГО по УВП | D88: =SUM(D42:D87) -> 45.75 | E88: =SUM(E42:E87) -> 34.75 | I88: =SUM(I42:I87) -> 19692337 | J88: =SUM(J42:J87) -> 1969233.7 | K88: =SUM(K42:K87) -> 129750 | L88: =SUM(L42:L87) -> 0 | M88: =SUM(M42:M87) -> 355709.7 | N88: =SUM(N42:N87) -> 0 | O88: =SUM(O42:O87) -> 0 | P88: =SUM(P42:P87) -> 15927.3 | ... AF88: =SUM(AF42:AF87) -> 3.8599057e+08
A89: Медицинский персонал (МП)
A90: =A87+1 -> #REF! | B90: Врач-педиатр | C90: Даулетярова Нургайша Адаевна | D90: 1 | E90: 1 | G90: 44797 | H90: 21 | I90: =E90*17697*H90 -> 371637 | J90: =I90*10% -> 37163.7 | S90: =SUM(J90:R90) -> 37163.7 | T90: =I90+S90 -> 408800.7 | U90: =T90*10% -> 40880.07 | V90: =((T90-U90-W90)-(14*4325))*10% -> 29919.462 | W90: =T90*2% -> 8176.014 | X90: =T90-U90-V90-W90 -> 329825.15 | Y90: =T90*12 -> 4905608.4 | Z90: =I90*2 -> 743274 | AA90: =Y90+Z90 -> 5648882.4 | AB90: =AA90*3.5% -> 197710.88 | AC90: =(AA90*0.9-(W90*12))*11%-AD90 -> 294247.31 | AD90: =AA90*0.9*5% -> 254199.71 | AE90: =AA90*3% -> 169466.47 | AF90: =AA90+AC90+AD90+AE90+AB90 -> 6564506.8 | AG90: РБ
A91: =A90+1 -> #REF! | B91: Медицинская сестра | C91: Вакансия-1 | D91: 1 | G91: 45699 | H91: 25 | I91: =17697*H91 -> 442425 | J91: =I91*10% -> 44242.5 | S91: =SUM(J91:R91) -> 44242.5 | T91: =I91+S91 -> 486667.5 | U91: =T91*10% -> 48666.75 | V91: =((T91-U91-W91)-(14*4325))*10% -> 36771.74 | W91: =T91*2% -> 9733.35 | X91: =T91-U91-V91-W91 -> 391495.66 | Y91: =T91*12 -> 5840010 | Z91: =I91*2 -> 884850 | AA91: =Y91+Z91 -> 6724860 | AB91: =AA91*3.5% -> 235370.1 | AC91: =(AA91*0.9-(W91*12))*11%-AD91+6667589.35 -> 7017883.8 | AD91: =AA91*0.9*5% -> 302618.7 | AE91: =AA91*3% -> 201745.8 | AF91: =AA91+AC91+AD91+AE91+AB91 -> 14482478 | AG91: РБ
A92: =A91+1 -> #REF! | B92: Диетическая медсестра | C92: Аксакалова Анар Сагидолдановна | D92: 1 | E92: 1 | G92: 44151 | H92: 16 | I92: =E92*17697*H92 -> 283152 | J92: =I92*10% -> 28315.2 | S92: =SUM(J92:R92) -> 28315.2 | T92: =I92+S92 -> 311467.2 | U92: =T92*10% -> 31146.72 | V92: =((T92-U92-W92)-(14*4325))*10% -> 21354.114 | W92: =T92*2% -> 6229.344 | X92: =T92-U92-V92-W92 -> 252737.02 | Y92: =T92*12 -> 3737606.4 | Z92: =I92*2 -> 566304 | AA92: =Y92+Z92 -> 4303910.4 | AB92: =AA92*3.5% -> 150636.86 | AC92: =(AA92*0.9-(W92*12))*11%-AD92 -> 224188.43 | AD92: =AA92*0.9*5% -> 193675.97 | AE92: =AA92*3% -> 129117.31 | AF92: =AA92+AC92+AD92+AE92+AB92 -> 5001529 | AG92: РБ
B93: ИТОГО по МП | D93: =SUM(D90:D92) -> 3 | E93: =SUM(E90:E92) -> 2 | I93: =SUM(I90:I92) -> 1097214 | J93: =SUM(J90:J92) -> 109721.4 | K93: =SUM(K90:K92) -> 0 | L93: =SUM(L90:L92) -> 0 | M93: =SUM(M90:M92) -> 0 | N93: =SUM(N90:N92) -> 0 | O93: =SUM(O90:O92) -> 0 | P93: =SUM(P90:P92) -> 0 | ... AF93: =SUM(AF90:AF92) -> 26048514
A94: Обслуживающий и вспомогательный персонал (ОВП)
A95: =A92+1 -> #REF! | B95: Инженер по охране труда и техники безопасности | C95: Алимжанов Ислам Алимжанович | D95: 1 | E95: 1 | G95: 44872 | H95: 30 | I95: =E95*17697*H95 -> 530910 | J95: =I95*10% -> 53091 | S95: =SUM(J95:R95) -> 53091 | T95: =I95+S95 -> 584001 | U95: =T95*10% -> 58400.1 | V95: =((T95-U95-W95)-(14*4325))*10% -> 45337.088 | W95: =T95*2% -> 11680.02 | X95: =T95-U95-V95-W95 -> 468583.79 | Y95: =T95*12 -> 7008012 | Z95: =I95*2 -> 1061820 | AA95: =Y95+Z95 -> 8069832 | AB95: =AA95*3.5% -> 282444.12 | AC95: =(AA95*0.9-(W95*12))*11%-AD95 -> 420353.3 | AD95: =AA95*0.9*5% -> 363142.44 | AE95: =AA95*3% -> 242094.96 | AF95: =AA95+AC95+AD95+AE95+AB95 -> 9377866.8 | AG95: РБ
A96: =A95+1 -> #REF! | B96: Инженер по оборудованию | C96: Вакансия-1 | D96: 1 | H96: 35 | I96: =D96*17697*H96 -> 619395 | J96: =I96*10% -> 61939.5 | S96: =SUM(J96:R96) -> 61939.5 | T96: =I96+S96 -> 681334.5 | U96: =T96*10% -> 68133.45 | V96: =((T96-U96-W96)-(14*4325))*10% -> 53902.436 | W96: =T96*2% -> 13626.69 | X96: =T96-U96-V96-W96 -> 545671.92 | Y96: =T96*12 -> 8176014 | Z96: =I96*2 -> 1238790 | AA96: =Y96+Z96 -> 9414804 | AB96: =AA96*3.5% -> 329518.14 | AC96: =(AA96*0.9-(W96*12))*11%-AD96 -> 490412.19 | AD96: =AA96*0.9*5% -> 423666.18 | AE96: =AA96*3% -> 282444.12 | AF96: =AA96+AC96+AD96+AE96+AB96 -> 10940845 | AG96: РБ
A97: =A96+1 -> #REF! | B97: Заведующий складом | C97: Байбосунова Шолпан Сагындыковна | D97: 1 | E97: 1 | G97: 44986 | H97: 16 | I97: =E97*17697*H97 -> 283152 | J97: =I97*10% -> 28315.2 | R97: =25%*17697 -> 4424.25 | S97: =SUM(J97:R97) -> 32739.45 | T97: =I97+S97 -> 315891.45 | U97: =T97*10% -> 31589.145 | V97: =((T97-U97-W97)-(14*4325))*10% -> 21743.448 | W97: =T97*2% -> 6317.829 | X97: =T97-U97-V97-W97 -> 256241.03 | Y97: =T97*12 -> 3790697.4 | Z97: =I97*2 -> 566304 | AA97: =Y97+Z97 -> 4357001.4 | AB97: =AA97*3.5% -> 152495.05 | AC97: =(AA97*0.9-(W97*12))*11%-AD97 -> 226938.54 | AD97: =AA97*0.9*5% -> 196065.06 | AE97: =AA97*3% -> 130710.04 | AF97: =AA97+AC97+AD97+AE97+AB97 -> 5063210.1 | AG97: РБ
A98: =A97+1 -> #REF! | B98: Водитель | C98: Асылбаев Кайрат Бекенович | D98: 1 | E98: 1 | G98: 42324 | H98: 14 | I98: =E98*17697*H98 -> 247758 | J98: =I98*10% -> 24775.8 | O98: =35%*17697 -> 6193.95 | S98: =SUM(J98:R98) -> 30969.75 | T98: =I98+S98 -> 278727.75 | U98: =T98*10% -> 27872.775 | V98: =((T98-U98-W98)-(14*4325))*10% -> 18473.042 | W98: =T98*2% -> 5574.555 | X98: =T98-U98-V98-W98 -> 226807.38 | Y98: =T98*12 -> 3344733 | Z98: =I98*2 -> 495516 | AA98: =Y98+Z98 -> 3840249 | AB98: =AA98*3.5% -> 134408.72 | AC98: =(AA98*0.9-(W98*12))*11%-AD98 -> 200015.03 | AD98: =AA98*0.9*5% -> 172811.21 | AE98: =AA98*3% -> 115207.47 | AF98: =AA98+AC98+AD98+AE98+AB98 -> 4462691.4 | AG98: РБ
A99: =A98+1 -> #REF! | B99: Энергетик | C99: Пивоваров Сергей Геннадьевич | D99: 1 | E99: 1 | G99: 44075 | H99: 18 | I99: =E99*17697*H99 -> 318546 | J99: =I99*10% -> 31854.6 | S99: =SUM(J99:R99) -> 31854.6 | T99: =I99+S99 -> 350400.6 | U99: =T99*10% -> 35040.06 | V99: =((T99-U99-W99)-(14*4325))*10% -> 24780.253 | W99: =T99*2% -> 7008.012 | X99: =T99-U99-V99-W99 -> 283572.28 | Y99: =T99*12 -> 4204807.2 | Z99: =I99*2 -> 637092 | AA99: =Y99+Z99 -> 4841899.2 | AB99: =AA99*3.5% -> 169466.47 | AC99: =(AA99*0.9-(W99*12))*11%-AD99 -> 252211.98 | AD99: =AA99*0.9*5% -> 217885.46 | AE99: =AA99*3% -> 145256.98 | AF99: =AA99+AC99+AD99+AE99+AB99 -> 5626720.1 | AG99: РБ
A100: =A99+1 -> #REF! | B100: Элекромонтер | C100: Вакансия-1,5 | D100: 2 | H100: 20 | I100: =1.5*17697*H100 -> 530910 | J100: =I100*10% -> 53091 | S100: =SUM(J100:R100) -> 53091 | T100: =I100+S100 -> 584001 | U100: =T100*10% -> 58400.1 | V100: =((T100-U100-W100)-(14*4325))*10% -> 45337.088 | W100: =T100*2% -> 11680.02 | X100: =T100-U100-V100-W100 -> 468583.79 | Y100: =T100*12 -> 7008012 | Z100: =I100*2 -> 1061820 | AA100: =Y100+Z100 -> 8069832 | AB100: =AA100*3.5% -> 282444.12 | AC100: =(AA100*0.9-(W100*12))*11%-AD100 -> 420353.3 | AD100: =AA100*0.9*5% -> 363142.44 | AE100: =AA100*3% -> 242094.96 | AF100: =AA100+AC100+AD100+AE100+AB100 -> 9377866.8 | AG100: РБ
A101: =A100+1 -> #REF! | B101: Элекромонтер | C101: Алиев Бакыт Мелсович | E101: 0.5 | G101: 45659 | H101: 12 | I101: =0.5*17697*H101 -> 106182 | J101: =I101*10% -> 10618.2 | S101: =SUM(J101:R101) -> 10618.2 | T101: =I101+S101 -> 116800.2 | U101: =T101*10% -> 11680.02 | V101: =((T101-U101-W101)-(14*4325))*10% -> 4223.4176 | W101: =T101*2% -> 2336.004 | X101: =T101-U101-V101-W101 -> 98560.758 | Y101: =T101*12 -> 1401602.4 | Z101: =I101*2 -> 212364 | AA101: =Y101+Z101 -> 1613966.4 | AB101: =AA101*3.5% -> 56488.824 | AC101: =(AA101*0.9-(W101*12))*11%-AD101 -> 84070.66 | AD101: =AA101*0.9*5% -> 72628.488 | AE101: =AA101*3% -> 48418.992 | AF101: =AA101+AC101+AD101+AE101+AB101 -> 1875573.4
A102: =A101+1 -> #REF! | B102: Плотник | C102: Суймагамбетов Багитжан Тургалиевич | D102: 1 | E102: 1 | G102: 42780 | H102: 12 | I102: =E102*17697*H102 -> 212364 | J102: =I102*10% -> 21236.4 | S102: =SUM(J102:R102) -> 21236.4 | T102: =I102+S102 -> 233600.4 | U102: =T102*10% -> 23360.04 | V102: =((T102-U102-W102)-(14*4325))*10% -> 14501.835 | W102: =T102*2% -> 4672.008 | X102: =T102-U102-V102-W102 -> 191066.52 | Y102: =T102*12 -> 2803204.8 | Z102: =I102*2 -> 424728 | AA102: =Y102+Z102 -> 3227932.8 | AB102: =AA102*3.5% -> 112977.65 | AC102: =(AA102*0.9-(W102*12))*11%-AD102 -> 168141.32 | AD102: =AA102*0.9*5% -> 145256.98 | AE102: =AA102*3% -> 96837.984 | AF102: =AA102+AC102+AD102+AE102+AB102 -> 3751146.7 | AG102: РБ
A103: =#REF!+1 -> #REF! | B103: Слесарь-сантехник | C103: Вакансия-1 | D103: 2 | G103: 45659 | H103: 20 | I103: =17697*H103 -> 353940 | J103: =I103*10% -> 35394 | S103: =SUM(J103:R103) -> 35394 | T103: =I103+S103 -> 389334 | U103: =T103*10% -> 38933.4 | V103: =((T103-U103-W103)-(14*4325))*10% -> 28206.392 | W103: =T103*2% -> 7786.68 | X103: =T103-U103-V103-W103 -> 314407.53 | Y103: =T103*12 -> 4672008 | Z103: =I103*2 -> 707880 | AA103: =Y103+Z103 -> 5379888 | AB103: =AA103*3.5% -> 188296.08 | AC103: =(AA103*0.9-(W103*12))*11%-AD103+3000000 -> 3280235.5 | AD103: =AA103*0.9*5% -> 242094.96 | AE103: =AA103*3% -> 161396.64 | AF103: =AA103+AC103+AD103+AE103+AB103 -> 9251911.2 | AG103: РБ
A104: =A103+1 -> #REF! | B104: Слесарь-сантехник | C104: Садықов Қайрат Пірмағанбетұлы | E104: 1 | G104: 43654 | H104: 12 | I104: =E104*17697*H104 -> 212364 | J104: =I104*10% -> 21236.4 | S104: =SUM(J104:R104) -> 21236.4 | T104: =I104+S104 -> 233600.4 | U104: =T104*10% -> 23360.04 | V104: =((T104-U104-W104)-(14*4325))*10% -> 14501.835 | W104: =T104*2% -> 4672.008 | X104: =T104-U104-V104-W104 -> 191066.52 | Y104: =T104*12 -> 2803204.8 | Z104: =I104*2 -> 424728 | AA104: =Y104+Z104 -> 3227932.8 | AB104: =AA104*3.5% -> 112977.65 | AC104: =(AA104*0.9-(W104*12))*11%-AD104 -> 168141.32 | AD104: =AA104*0.9*5% -> 145256.98 | AE104: =AA104*3% -> 96837.984 | AF104: =AA104+AC104+AD104+AE104+AB104 -> 3751146.7 | AG104: РБ
A105: =A104+1 -> #REF! | B105: Садовник | C105: Литвинова Бахытгул Айхимовна | D105: 1 | E105: 1 | G105: 44508 | H105: 11 | I105: =E105*17697*H105 -> 194667 | J105: =I105*10% -> 19466.7 | S105: =SUM(J105:R105) -> 19466.7 | T105: =I105+S105 -> 214133.7 | U105: =T105*10% -> 21413.37 | V105: =((T105-U105-W105)-(14*4325))*10% -> 12788.766 | W105: =T105*2% -> 4282.674 | X105: =T105-U105-V105-W105 -> 175648.89 | Y105: =T105*12 -> 2569604.4 | Z105: =I105*2 -> 389334 | AA105: =Y105+Z105 -> 2958938.4 | AB105: =AA105*3.5% -> 103562.84 | AC105: =(AA105*0.9-(W105*12))*11%-AD105 -> 154129.54 | AD105: =AA105*0.9*5% -> 133152.23 | AE105: =AA105*3% -> 88768.152 | AF105: =AA105+AC105+AD105+AE105+AB105 -> 3438551.2 | AG105: РБ
A106: =A105+1 -> #REF! | B106: Дворник | C106: Аркашев Бахтияр Саметович | D106: 2 | E106: 1 | G106: 45246 | H106: 12 | I106: =E106*17697*H106 -> 212364 | J106: =I106*10% -> 21236.4 | S106: =SUM(J106:R106) -> 21236.4 | T106: =I106+S106 -> 233600.4 | U106: =T106*10% -> 23360.04 | V106: =((T106-U106-W106)-(14*4325))*10% -> 14501.835 | W106: =T106*2% -> 4672.008 | X106: =T106-U106-V106-W106 -> 191066.52 | Y106: =T106*12 -> 2803204.8 | Z106: =I106*2 -> 424728 | AA106: =Y106+Z106 -> 3227932.8 | AB106: =AA106*3.5% -> 112977.65 | AC106: =(AA106*0.9-(W106*12))*11%-AD106 -> 168141.32 | AD106: =AA106*0.9*5% -> 145256.98 | AE106: =AA106*3% -> 96837.984 | AF106: =AA106+AC106+AD106+AE106+AB106 -> 3751146.7 | AG106: РБ
A107: =A106+1 -> #REF! | B107: Дворник | C107: Ескелді Хушанг Мухаммед | E107: 1 | G107: 44219 | H107: 12 | I107: =E107*17697*H107 -> 212364 | J107: =I107*10% -> 21236.4 | S107: =SUM(J107:R107) -> 21236.4 | T107: =I107+S107 -> 233600.4 | U107: =T107*10% -> 23360.04 | V107: =((T107-U107-W107)-(14*4325))*10% -> 14501.835 | W107: =T107*2% -> 4672.008 | X107: =T107-U107-V107-W107 -> 191066.52 | Y107: =T107*12 -> 2803204.8 | Z107: =I107*2 -> 424728 | AA107: =Y107+Z107 -> 3227932.8 | AB107: =AA107*3.5% -> 112977.65 | AC107: =(AA107*0.9-(W107*12))*11%-AD107 -> 168141.32 | AD107: =AA107*0.9*5% -> 145256.98 | AE107: =AA107*3% -> 96837.984 | AF107: =AA107+AC107+AD107+AE107+AB107 -> 3751146.7 | AG107: РБ
A108: =A107+1 -> #REF! | B108: Рабочий по комплекному обслуживанию и текущему ремонту зданий | C108: Бургибаев Айдын Сатыбалдиевич | D108: 2 | E108: 1 | G108: 44201 | H108: 13 | I108: =E108*17697*H108 -> 230061 | J108: =I108*10% -> 23006.1 | R108: =25%*17697 -> 4424.25 | S108: =SUM(J108:R108) -> 27430.35 | T108: =I108+S108 -> 257491.35 | U108: =T108*10% -> 25749.135 | V108: =((T108-U108-W108)-(14*4325))*10% -> 16604.239 | W108: =T108*2% -> 5149.827 | X108: =T108-U108-V108-W108 -> 209988.15 | Y108: =T108*12 -> 3089896.2 | Z108: =I108*2 -> 460122 | AA108: =Y108+Z108 -> 3550018.2 | AB108: =AA108*3.5% -> 124250.64 | AC108: =(AA108*0.9-(W108*12))*11%-AD108 -> 184903.21 | AD108: =AA108*0.9*5% -> 159750.82 | AE108: =AA108*3% -> 106500.55 | AF108: =AA108+AC108+AD108+AE108+AB108 -> 4125423.4 | AG108: РБ
A109: =A108+1 -> #REF! | B109: Рабочий по комплекному обслуживанию и текущему ремонту зданий | C109: Нуркожаев Усен Абдикадирбекулы | E109: 1 | G109: 44593 | H109: 11 | I109: =E109*17697*H109 -> 194667 | J109: =I109*10% -> 19466.7 | R109: =25%*17697 -> 4424.25 | S109: =SUM(J109:R109) -> 23890.95 | T109: =I109+S109 -> 218557.95 | U109: =T109*10% -> 21855.795 | V109: =((T109-U109-W109)-(14*4325))*10% -> 13178.1 | W109: =T109*2% -> 4371.159 | X109: =T109-U109-V109-W109 -> 179152.9 | Y109: =T109*12 -> 2622695.4 | Z109: =I109*2 -> 389334 | AA109: =Y109+Z109 -> 3012029.4 | AB109: =AA109*3.5% -> 105421.03 | AC109: =(AA109*0.9-(W109*12))*11%-AD109 -> 156879.66 | AD109: =AA109*0.9*5% -> 135541.32 | AE109: =AA109*3% -> 90360.882 | AF109: =AA109+AC109+AD109+AE109+AB109 -> 3500232.3 | AG109: РБ
...

Sheet Тариф Свод Алматы 2026 
P3: Бекітемін:
P5: Алматы қаласындағы «Республикалық физика-математика мектебі»
P6: коммерциялық емес акционерлік қоғамы филиалының директоры
P7: ________________Меирбек М.Е.
P8: «01» қыркүйек 2025 жыл
A9: Алматы қаласындағы «РФММ» КеАҚ филиалының 2026 жылғы 01 қаңтардағы тарификациялық ведомостің жинағы
A10: Свод тарификационной ведомости на 01 января 2026 года филиала НАО «РФМШ» в г.Алматы
B11: тенге | AZ11: АЕК, МРП 4325тн
A12: № | C12: Мұғалімдердің аты-жөні ФИО УЧИТЕЛЯ | D12: Лауазымдық (қызметтік) атаулары Наименование должностей | E12: Білімі Образование | F12: Біліктілігік санаты Педагогическое мастерство | G12: Доктор,магистр дәрежесі Ученая степень | H12: Педагогикалық өтілі Педагогический стаж работинка | I12: НЛЖ БДО | J12: Коэффциент | K12: Жалақы Оклад | L12: Инварианттық компоненттен сыныптар бойынша нақты жүктеме Фактическая нагрузка по классам-инвариативный компонент | Q12: Инварианттық компонент бойынша жалпы сағаты Итого часов инвариат. компонент | R12: Вариативтік компоненттен сыныптар бойынша нақты жүктемесі Фактическая нагрузка по классам-вариативный компонент | W12: Вариативтік компонент бойынша жалпы сағаты Итого часов вариат. компонент | X12: Барлық сағат саны ИТОГО кол-во часов | Y12: Сағаттың сомасы Сумма за часы | Z12: Қосымща ақы, Доплата 10% на ДО | AA12: Дәптер тексеру Проверка тетрадей 40%, 50% от БДО | AC12: Сыныпты топқа бөлу кезіндегі дәптер тексеру Проверка тетрадей при делении класса (40%,50%/2) | AE12: Кафедра меңгеру үшін сомасы Сумма за заведование кафедрой | AF12: Кабинет меңгірушілігі үшін За заведование кабинетом 20% от БДО | AH12: Сынып жетекшілігі үшін За классное руководство ст. и ср. классы-200% от БДО | AJ12: Тереңдетіліп оқытылатын пәндер сағаты үшін қосымша төлем Доплата за углубленное изучение предмета 40% от БДО | AL12: Жаңартылған мазмұн үшін қосымша төлем Доплата за обновленное содержание 30% от ДО | AN12: Біліктілігік санаты Педагогическое мастерство | AO12: Біліктілік санаты үшін қосымша төлем Доплата за педагогическое мастерство от ДО | AS12: Оқыту әдістеріне шетелдік тәжірибені енгізгені үшін қосымша ақы 100 АЕК-ке дейін Доплата за внедрение в методику преподавания на зарубежном опыт не более 100 МРП | AU12: AР пәндерін (жобаларды іске асыратын- дарды қоса алғанда) оқыту үшін қосымша ақы 200 АЕК-ке дейін Доплата за преподавание по АР предметам ( в том числе внедряющим проекты) до 200 МРП | AW12: Доктор,магистр дәрежесі Ученая степень | AX12: Доктор, магистр дәрежесі үшін қосымша ақы Доплата за ученую степень Магистра 10 МРП, Доктор (PhD) 17 МРП | AY12: НЛЖ 100% тәлімгерлік үшін қосымша ақы Доплата за наставничество 100% от БДО | AZ12: Барлық қосымша ақы Итого доплаты | BA12: Ай сайынғы барлық жалақы қоры Всего ФЗП за месяц | BB12: МЗЖ айына, ОПВ 10% в месяц | BC12: МӘМСЖ, ВОСМС 2% | BD12: ЖТС айына 14 АЕК ИПН в месяц (14 МРП) | BE12: Ай сайын жалпы қолға алатын Итого на руки в месяц | BF12: Жылына барлық жалақы қоры Всего ФЗП в год | BG12: Сауықтыру жәрдемақысы Оздоровительные пособия | BH12: Сауықтыру жәрдемақысымен барлық жалақы қоры Всего ФЗП с леч пособием | BI12: ЖБМЗЖ ОПВР 3,5% | BJ12: Әлеуметтік салық Социальный налог (11 % -5%)=6% в год | BK12: Әлеуметтік аударымдар Социальные отчисления 5% в год | BL12: МӘМС, ОСМС 3% в год | BM12: Жылдық еңбек ақы төлеу қоры ФОТ на год | BN12: Штат. кесте бойынша қосымша бірліктер Доп.единицы по шт.рас.
L13: 7 | M13: 8 | N13: 9 | O13: 10 | P13: 11 | R13: 7 | S13: 8 | T13: 9 | U13: 10 | V13: 11 | AA13: Саны Кол-во | AB13: Сома Сумма | AC13: Саны Кол-во | AD13: Сома Сумма | AF13: Кабинет | AG13: Сома Сумма | AH13: Сынып Класс | AI13: Сома Сумма | AJ13: СағаттарЧасы | AK13: Сома Сумма | AL13: Сағаттар Часы | AM13: Сома Сумма | AO13: Педагог-шебер 50% | AP13: Педагог-зерттеуші 40% | AQ13: Педагог-сарапшы 35% | AR13: Педагог-модератор 30% | AS13: АЕК МРП | AT13: Сома Сумма | AU13: АЕК МРП | AV13: Сома Сумма
A14: 1 | B14: 1 | C14: Абилгазиев Жанарбек Нурбакытович | D14: алгебра және анализ бастамалары, геометрия 11ABCH | E14: Ж | F14: Педагог-шебер | G14: Магистр-математика | H14: 17.04.00 | I14: 17697 | J14: 11.02 | K14: =I14*J14 -> 195020.94 | P14: 36 | Q14: =SUM(L14:P14) -> 36 | W14: =SUM(R14:V14) -> 0 | X14: =Q14+W14 -> 36 | Y14: =K14/16*X14 -> 438797.11 | Z14: =Y14*10% -> 43879.712 | AA14: 0 | AB14: =I14/16*AA14*40% -> 0 | AC14: 36 | AD14: =I14/16*AC14*40%*50% -> 7963.65 | AF14: А317 | AG14: =17697*20% -> 3539.4 | AJ14: =X14 -> 36 | AK14: =I14/16*AJ14*40% -> 15927.3 | AL14: =X14 -> 36 | AM14: =K14/16*AL14*30% -> 131639.13 | AN14: =F14 -> Педагог-шебер | AO14: =IF(AN14="Педагог-зерттеуші", "0", IF(AN14="Педагог-шебер",K14/16*X14*50%, IF(AN14="Педагог-сарапшы", "0", IF(AN14="Педагог-модератор", "0", "0")))) -> 219398.56 | AP14: =IF(AN14="Педагог-шебер", "0", IF(AN14="Педагог-зерттеуші",K14/16*X14*40%, IF(AN14="Педагог-сарапшы", "0", IF(AN14="Педагог-модератор", "0", "0")))) -> 0 | AQ14: =IF(AN14="Педагог-шебер", "0", IF(AN14="Педагог-сарапшы",K14/16*X14*35%, IF(AN14="Педагог-зерттеуші", "0", IF(AN14="Педагог-модератор", "0", "0")))) -> 0 | AR14: =IF(AN14="Педагог-шебер", "0", IF(AN14="Педагог-модератор",K14/16*X14*30%, IF(AN14="Педагог-зерттеуші", "0", IF(AN14="Педагог-сарапшы", "0", "0")))) -> 0 | AW14: =G14 -> Магистр-математика | AX14: =10*4325 -> 43250 | AZ14: =Z14+AB14+AD14+AE14+AG14+AI14+AK14+AM14+AO14+AP14+AQ14++AR14+AT14+AV14+AX14+AY14 -> 465597.75 | BA14: =Y14+AZ14 -> 904394.87 | BB14: =BA14*10% -> 90439.487 | BC14: =BA14*2% -> 18087.897 | BD14: =(BA14-BB14-BC14-(14*4325))*10% -> 73531.748 | BE14: =BA14-BB14-BC14-BD14 -> 722335.74 | BF14: =BA14*12 -> 10852738 | BG14: =Y14*2 -> 877594.23 | BH14: =BF14+BG14 -> 11730333 | BI14: =BH14*3.5% -> 410561.64 | BJ14: =(BH14*0.9-(BC14*12))*11%-BK14 -> 609561.94 | BK14: =BH14*0.9*5% -> 527864.97 | BL14: =BH14*3% -> 351909.98 | BM14: =BH14+BJ14+BK14+BL14+BI14 -> 13630231
A15: =A14+1 -> 2 | B15: =B14+1 -> 2 | C15: Айтжанов Ердос Ержанұлы | D15: алгебра, геометрия, есептерді шешу практикумы 8L 9DEF | E15: Ж | F15: Педагог-модератор | G15: Магистр-математика | H15: 04.03.18 | I15: 17697 | J15: 10 | K15: =I15*J15 -> 176970 | M15: 8 | N15: 24 | Q15: =SUM(L15:P15) -> 32 | S15: 1 | T15: 3 | W15: =SUM(R15:V15) -> 4 | X15: =Q15+W15 -> 36 | Y15: =K15/16*X15 -> 398182.5 | Z15: =Y15*10% -> 39818.25 | AA15: 36 | AB15: =I15/16*AA15*40% -> 15927.3 | AC15: 0 | AD15: =I15/16*AC15*40%*50% -> 0 | AF15: А008 | AG15: =17697*20% -> 3539.4 | AJ15: =X15 -> 36 | AK15: =I15/16*AJ15*40% -> 15927.3 | AL15: =X15 -> 36 | AM15: =K15/16*AL15*30% -> 119454.75 | AN15: =F15 -> Педагог-модератор | AO15: =IF(AN15="Педагог-зерттеуші", "0", IF(AN15="Педагог-шебер",K15/16*X15*50%, IF(AN15="Педагог-сарапшы", "0", IF(AN15="Педагог-модератор", "0", "0")))) -> 0 | AP15: =IF(AN15="Педагог-шебер", "0", IF(AN15="Педагог-зерттеуші",K15/16*X15*40%, IF(AN15="Педагог-сарапшы", "0", IF(AN15="Педагог-модератор", "0", "0")))) -> 0 | AQ15: =IF(AN15="Педагог-шебер", "0", IF(AN15="Педагог-сарапшы",K15/16*X15*35%, IF(AN15="Педагог-зерттеуші", "0", IF(AN15="Педагог-модератор", "0", "0")))) -> 0 | AR15: =IF(AN15="Педагог-шебер", "0", IF(AN15="Педагог-модератор",K15/16*X15*30%, IF(AN15="Педагог-зерттеуші", "0", IF(AN15="Педагог-сарапшы", "0", "0")))) -> 119454.75 | AW15: =G15 -> Магистр-математика | AX15: =10*4325 -> 43250 | AZ15: =Z15+AB15+AD15+AE15+AG15+AI15+AK15+AM15+AO15+AP15+AQ15++AR15+AT15+AV15+AX15+AY15 -> 357371.75 | BA15: =Y15+AZ15 -> 755554.25 | BB15: =BA15*10% -> 75555.425 | BC15: =BA15*2% -> 15111.085 | BD15: =(BA15-BB15-BC15-(14*4325))*10% -> 60433.774 | BE15: =BA15-BB15-BC15-BD15 -> 604453.97 | BF15: =BA15*12 -> 9066651 | BG15: =Y15*2 -> 796365 | BH15: =BF15+BG15 -> 9863016 | BI15: =BH15*3.5% -> 345205.56 | BJ15: =(BH15*0.9-(BC15*12))*11%-BK15 -> 512656.23 | BK15: =BH15*0.9*5% -> 443835.72 | BL15: =BH15*3% -> 295890.48 | BM15: =BH15+BJ15+BK15+BL15+BI15 -> 11460604
A16: =A15+1 -> 3 | B16: =B15+1 -> 3 | C16: Аманкельдыұлы Қалмас | D16: алгебра, геометрия 10DEF | E16: Ж | F16: Педагог-модератор | G16: Магистр-математика | H16: 06.03.09 | I16: 17697 | J16: 10.22 | K16: =I16*J16 -> 180863.34 | O16: 24 | Q16: =SUM(L16:P16) -> 24 | W16: =SUM(R16:V16) -> 0 | X16: =Q16+W16 -> 24 | Y16: =K16/16*X16 -> 271295.01 | Z16: =Y16*10% -> 27129.501 | AA16: 27 | AB16: =I16/16*AA16*40% -> 11945.475 | AC16: 0 | AD16: =I16/16*AC16*40%*50% -> 0 | AJ16: =X16 -> 24 | AK16: =I16/16*AJ16*40% -> 10618.2 | AL16: =X16 -> 24 | AM16: =K16/16*AL16*30% -> 81388.503 | AN16: =F16 -> Педагог-модератор | AO16: =IF(AN16="Педагог-зерттеуші", "0", IF(AN16="Педагог-шебер",K16/16*X16*50%, IF(AN16="Педагог-сарапшы", "0", IF(AN16="Педагог-модератор", "0", "0")))) -> 0 | AP16: =IF(AN16="Педагог-шебер", "0", IF(AN16="Педагог-зерттеуші",K16/16*X16*40%, IF(AN16="Педагог-сарапшы", "0", IF(AN16="Педагог-модератор", "0", "0")))) -> 0 | AQ16: =IF(AN16="Педагог-шебер", "0", IF(AN16="Педагог-сарапшы",K16/16*X16*35%, IF(AN16="Педагог-зерттеуші", "0", IF(AN16="Педагог-модератор", "0", "0")))) -> 0 | AR16: =IF(AN16="Педагог-шебер", "0", IF(AN16="Педагог-модератор",K16/16*X16*30%, IF(AN16="Педагог-зерттеуші", "0", IF(AN16="Педагог-сарапшы", "0", "0")))) -> 81388.503 | AW16: =G16 -> Магистр-математика | AX16: =10*4325 -> 43250 | AZ16: =Z16+AB16+AD16+AE16+AG16+AI16+AK16+AM16+AO16+AP16+AQ16++AR16+AT16+AV16+AX16+AY16 -> 255720.18 | BA16: =Y16+AZ16 -> 527015.19 | BB16: =BA16*10% -> 52701.519 | BC16: =BA16*2% -> 10540.304 | BD16: =(BA16-BB16-BC16-(14*4325))*10% -> 40322.337 | BE16: =BA16-BB16-BC16-BD16 -> 423451.03 | BF16: =BA16*12 -> 6324182.3 | BG16: =Y16*2 -> 542590.02 | BH16: =BF16+BG16 -> 6866772.3 | BI16: =BH16*3.5% -> 240337.03 | BJ16: =(BH16*0.9-(BC16*12))*11%-BK16 -> 356892.5 | BK16: =BH16*0.9*5% -> 309004.75 | BL16: =BH16*3% -> 206003.17 | BM16: =BH16+BJ16+BK16+BL16+BI16 -> 7979009.8
A17: =A16+1 -> 4 | B17: =B16+1 -> 4 | C17: Ахметов Талгат Дуйсеналиевич | D17: алгебра, геометрия, есептерді шешу практикумы 8DF | E17: Ж | F17: Педагог-зерттеуші | H17: 40.00.01 | I17: 17697 | J17: 11.4 | K17: =I17*J17 -> 201745.8 | M17: 16 | Q17: =SUM(L17:P17) -> 16 | S17: 2 | W17: =SUM(R17:V17) -> 2 | X17: =Q17+W17 -> 18 | Y17: =K17/16*X17 -> 226964.03 | Z17: =Y17*10% -> 22696.403 | AA17: 18 | AB17: =I17/16*AA17*40% -> 7963.65 | AC17: 0 | AD17: =I17/16*AC17*40%*50% -> 0 | AJ17: =X17 -> 18 | AK17: =I17/16*AJ17*40% -> 7963.65 | AL17: =X17 -> 18 | AM17: =K17/16*AL17*30% -> 68089.208 | AN17: =F17 -> Педагог-зерттеуші | AO17: =IF(AN17="Педагог-зерттеуші", "0", IF(AN17="Педагог-шебер",K17/16*X17*50%, IF(AN17="Педагог-сарапшы", "0", IF(AN17="Педагог-модератор", "0", "0")))) -> 0 | AP17: =IF(AN17="Педагог-шебер", "0", IF(AN17="Педагог-зерттеуші",K17/16*X17*40%, IF(AN17="Педагог-сарапшы", "0", IF(AN17="Педагог-модератор", "0", "0")))) -> 90785.61 | AQ17: =IF(AN17="Педагог-шебер", "0", IF(AN17="Педагог-сарапшы",K17/16*X17*35%, IF(AN17="Педагог-зерттеуші", "0", IF(AN17="Педагог-модератор", "0", "0")))) -> 0 | AR17: =IF(AN17="Педагог-шебер", "0", IF(AN17="Педагог-модератор",K17/16*X17*30%, IF(AN17="Педагог-зерттеуші", "0", IF(AN17="Педагог-сарапшы", "0", "0")))) -> 0 | AW17: =G17 -> 0 | AZ17: =Z17+AB17+AD17+AE17+AG17+AI17+AK17+AM17+AO17+AP17+AQ17++AR17+AT17+AV17+AX17+AY17 -> 197498.52 | BA17: =Y17+AZ17 -> 424462.55 | BB17: =BA17*10% -> 42446.255 | BC17: =BA17*2% -> 8489.2509 | BD17: =(BA17-BB17-BC17-(14*4325))*10% -> 31297.704 | BE17: =BA17-BB17-BC17-BD17 -> 342229.34 | BF17: =BA17*12 -> 5093550.5 | BG17: =Y17*2 -> 453928.05 | BH17: =BF17+BG17 -> 5547478.6 | BI17: =BH17*3.5% -> 194161.75 | BJ17: =(BH17*0.9-(BC17*12))*11%-BK17 -> 288358.03 | BK17: =BH17*0.9*5% -> 249636.54 | BL17: =BH17*3% -> 166424.36 | BM17: =BH17+BJ17+BK17+BL17+BI17 -> 6446059.3
A18: =A17+1 -> 5 | B18: =B17+1 -> 5 | C18: Ахметова Ғалия Зейноллақызы | D18: алгебра және анализ бастамалары, геометрия 11DK | E18: Ж | F18: Педагог-зерттеуші | H18: 38.01.01 | I18: 17697 | J18: 11.4 | K18: =I18*J18 -> 201745.8 | P18: 18 | Q18: =SUM(L18:P18) -> 18 | W18: =SUM(R18:V18) -> 0 | X18: =Q18+W18 -> 18 | Y18: =K18/16*X18 -> 226964.03 | Z18: =Y18*10% -> 22696.403 | AA18: 18 | AB18: =I18/16*AA18*40% -> 7963.65 | AC18: 0 | AD18: =I18/16*AC18*40%*50% -> 0 | AF18: A209 | AG18: =17697*20% -> 3539.4 | AH18: 11K | AI18: =I18*200% -> 35394 | AJ18: =X18 -> 18 | AK18: =I18/16*AJ18*40% -> 7963.65 | AL18: =X18 -> 18 | AM18: =K18/16*AL18*30% -> 68089.208 | AN18: =F18 -> Педагог-зерттеуші | AO18: =IF(AN18="Педагог-зерттеуші", "0", IF(AN18="Педагог-шебер",K18/16*X18*50%, IF(AN18="Педагог-сарапшы", "0", IF(AN18="Педагог-модератор", "0", "0")))) -> 0 | AP18: =IF(AN18="Педагог-шебер", "0", IF(AN18="Педагог-зерттеуші",K18/16*X18*40%, IF(AN18="Педагог-сарапшы", "0", IF(AN18="Педагог-модератор", "0", "0")))) -> 90785.61 | AQ18: =IF(AN18="Педагог-шебер", "0", IF(AN18="Педагог-сарапшы",K18/16*X18*35%, IF(AN18="Педагог-зерттеуші", "0", IF(AN18="Педагог-модератор", "0", "0")))) -> 0 | AR18: =IF(AN18="Педагог-шебер", "0", IF(AN18="Педагог-модератор",K18/16*X18*30%, IF(AN18="Педагог-зерттеуші", "0", IF(AN18="Педагог-сарапшы", "0", "0")))) -> 0 | AW18: =G18 -> 0 | AZ18: =Z18+AB18+AD18+AE18+AG18+AI18+AK18+AM18+AO18+AP18+AQ18++AR18+AT18+AV18+AX18+AY18 -> 236431.92 | BA18: =Y18+AZ18 -> 463395.95 | BB18: =BA18*10% -> 46339.595 | BC18: =BA18*2% -> 9267.9189 | BD18: =(BA18-BB18-BC18-(14*4325))*10% -> 34723.843 | BE18: =BA18-BB18-BC18-BD18 -> 373064.59 | BF18: =BA18*12 -> 5560751.3 | BG18: =Y18*2 -> 453928.05 | BH18: =BF18+BG18 -> 6014679.4 | BI18: =BH18*3.5% -> 210513.78 | BJ18: =(BH18*0.9-(BC18*12))*11%-BK18 -> 312559.03 | BK18: =BH18*0.9*5% -> 270660.57 | BL18: =BH18*3% -> 180440.38 | BM18: =BH18+BJ18+BK18+BL18+BI18 -> 6988853.2
A19: =A18+1 -> 6 | B19: =B18+1 -> 6 | C19: Бегимбетов Талгат Полатович | D19: алгебра және анализ бастамалары 10K | E19: Ж | F19: Педагог-сарапшы | G19: Магистр-математика | H19: 08.04.00 | I19: 17697 | J19: 10.4 | K19: =I19*J19 -> 184048.8 | O19: 5 | Q19: =SUM(L19:P19) -> 5 | W19: =SUM(R19:V19) -> 0 | X19: =Q19+W19 -> 5 | Y19: =K19/16*X19 -> 57515.25 | AA19: 5 | AB19: =I19/16*AA19*40% -> 2212.125 | AC19: 0 | AD19: =I19/16*AC19*40%*50% -> 0 | AJ19: =X19 -> 5 | AK19: =I19/16*AJ19*40% -> 2212.125 | AL19: =X19 -> 5 | AM19: =K19/16*AL19*30% -> 17254.575 | AN19: =F19 -> Педагог-сарапшы | AO19: =IF(AN19="Педагог-зерттеуші", "0", IF(AN19="Педагог-шебер",K19/16*X19*50%, IF(AN19="Педагог-сарапшы", "0", IF(AN19="Педагог-модератор", "0", "0")))) -> 0 | AP19: =IF(AN19="Педагог-шебер", "0", IF(AN19="Педагог-зерттеуші",K19/16*X19*40%, IF(AN19="Педагог-сарапшы", "0", IF(AN19="Педагог-модератор", "0", "0")))) -> 0 | AQ19: =IF(AN19="Педагог-шебер", "0", IF(AN19="Педагог-сарапшы",K19/16*X19*35%, IF(AN19="Педагог-зерттеуші", "0", IF(AN19="Педагог-модератор", "0", "0")))) -> 20130.338 | AR19: =IF(AN19="Педагог-шебер", "0", IF(AN19="Педагог-модератор",K19/16*X19*30%, IF(AN19="Педагог-зерттеуші", "0", IF(AN19="Педагог-сарапшы", "0", "0")))) -> 0 | AW19: =G19 -> Магистр-математика | AX19: =10*4325 -> 43250 | AZ19: =Z19+AB19+AD19+AE19+AG19+AI19+AK19+AM19+AO19+AP19+AQ19++AR19+AT19+AV19+AX19+AY19 -> 85059.163 | BA19: =Y19+AZ19 -> 142574.41 | BB19: =BA19*10% -> 14257.441 | BC19: =BA19*2% -> 2851.4883 | BD19: =(BA19-BB19-BC19-(14*4325))*10% -> 6491.5483 | BE19: =BA19-BB19-BC19-BD19 -> 118973.93 | BF19: =BA19*12 -> 1710893 | BG19: =Y19*2 -> 115030.5 | BH19: =BF19+BG19 -> 1825923.5 | BI19: =BH19*3.5% -> 63907.321 | BJ19: =(BH19*0.9-(BC19*12))*11%-BK19 -> 94835.902 | BK19: =BH19*0.9*5% -> 82166.555 | BL19: =BH19*3% -> 54777.704 | BM19: =BH19+BJ19+BK19+BL19+BI19 -> 2121610.9 | BN19: 1.25
A20: =A19+1 -> 7 | B20: =B19+1 -> 7 | C20: Бекен Дәулет Еркінұлы | D20: алгебра, геометрия, есептерді шешу практикумы 7BH, 9G | E20: Ж | H20: 00.04.00 | I20: 17697 | J20: 9.5 | K20: =I20*J20 -> 168121.5 | L20: 16 | N20: 8 | Q20: =SUM(L20:P20) -> 24 | R20: 2 | T20: 1 | W20: =SUM(R20:V20) -> 3 | X20: =Q20+W20 -> 27 | Y20: =K20/16*X20 -> 283705.03 | Z20: =Y20*10% -> 28370.503 | AA20: 9 | AB20: =I20/16*AA20*40% -> 3981.825 | AC20: 18 | AD20: =I20/16*AC20*40%*50% -> 3981.825 | AJ20: =X20 -> 27 | AK20: =I20/16*AJ20*40% -> 11945.475 | AL20: =X20 -> 27 | AM20: =K20/16*AL20*30% -> 85111.509 | AN20: =F20 -> 0 | AO20: =IF(AN20="Педагог-зерттеуші", "0", IF(AN20="Педагог-шебер",K20/16*X20*50%, IF(AN20="Педагог-сарапшы", "0", IF(AN20="Педагог-модератор", "0", "0")))) -> 0 | AP20: =IF(AN20="Педагог-шебер", "0", IF(AN20="Педагог-зерттеуші",K20/16*X20*40%, IF(AN20="Педагог-сарапшы", "0", IF(AN20="Педагог-модератор", "0", "0")))) -> 0 | AQ20: =IF(AN20="Педагог-шебер", "0", IF(AN20="Педагог-сарапшы",K20/16*X20*35%, IF(AN20="Педагог-зерттеуші", "0", IF(AN20="Педагог-модератор", "0", "0")))) -> 0 | AR20: =IF(AN20="Педагог-шебер", "0", IF(AN20="Педагог-модератор",K20/16*X20*30%, IF(AN20="Педагог-зерттеуші", "0", IF(AN20="Педагог-сарапшы", "0", "0")))) -> 0 | AW20: =G20 -> 0 | AZ20: =Z20+AB20+AD20+AE20+AG20+AI20+AK20+AM20+AO20+AP20+AQ20++AR20+AT20+AV20+AX20+AY20 -> 133391.14 | BA20: =Y20+AZ20 -> 417096.17 | BB20: =BA20*10% -> 41709.617 | BC20: =BA20*2% -> 8341.9234 | BD20: =(BA20-BB20-BC20-(14*4325))*10% -> 30649.463 | BE20: =BA20-BB20-BC20-BD20 -> 336395.17 | BF20: =BA20*12 -> 5005154 | BG20: =Y20*2 -> 567410.06 | BH20: =BF20+BG20 -> 5572564.1 | BI20: =BH20*3.5% -> 195039.74 | BJ20: =(BH20*0.9-(BC20*12))*11%-BK20 -> 289907.12 | BK20: =BH20*0.9*5% -> 250765.38 | BL20: =BH20*3% -> 167176.92 | BM20: =BH20+BJ20+BK20+BL20+BI20 -> 6475453.3
A21: =A20+1 -> 8 | B21: =B20+1 -> 8 | C21: Дайрабай Бақдәулет Бақытжанұлы | D21: алгебра, геометрия, есептерді шешу практикумы 8ABC | E21: Ж | H21: 01.04.00 | I21: 17697 | J21: 9.66 | K21: =I21*J21 -> 170953.02 | M21: 24 | Q21: =SUM(L21:P21) -> 24 | S21: 3 | W21: =SUM(R21:V21) -> 3 | X21: =Q21+W21 -> 27 | Y21: =K21/16*X21 -> 288483.22 | Z21: =Y21*10% -> 28848.322 | AA21: 9 | AB21: =I21/16*AA21*40% -> 3981.825 | AC21: 18 | AD21: =I21/16*AC21*40%*50% -> 3981.825 | AF21: A010 | AG21: =17697*20% -> 3539.4 | AJ21: =X21 -> 27 | AK21: =I21/16*AJ21*40% -> 11945.475 | AL21: =X21 -> 27 | AM21: =K21/16*AL21*30% -> 86544.966 | AN21: =F21 -> 0 | AO21: =IF(AN21="Педагог-зерттеуші", "0", IF(AN21="Педагог-шебер",K21/16*X21*50%, IF(AN21="Педагог-сарапшы", "0", IF(AN21="Педагог-модератор", "0", "0")))) -> 0 | AP21: =IF(AN21="Педагог-шебер", "0", IF(AN21="Педагог-зерттеуші",K21/16*X21*40%, IF(AN21="Педагог-сарапшы", "0", IF(AN21="Педагог-модератор", "0", "0")))) -> 0 | AQ21: =IF(AN21="Педагог-шебер", "0", IF(AN21="Педагог-сарапшы",K21/16*X21*35%, IF(AN21="Педагог-зерттеуші", "0", IF(AN21="Педагог-модератор", "0", "0")))) -> 0 | AR21: =IF(AN21="Педагог-шебер", "0", IF(AN21="Педагог-модератор",K21/16*X21*30%, IF(AN21="Педагог-зерттеуші", "0", IF(AN21="Педагог-сарапшы", "0", "0")))) -> 0 | AW21: =G21 -> 0 | AZ21: =Z21+AB21+AD21+AE21+AG21+AI21+AK21+AM21+AO21+AP21+AQ21++AR21+AT21+AV21+AX21+AY21 -> 138841.81 | BA21: =Y21+AZ21 -> 427325.03 | BB21: =BA21*10% -> 42732.503 | BC21: =BA21*2% -> 8546.5007 | BD21: =(BA21-BB21-BC21-(14*4325))*10% -> 31549.603 | BE21: =BA21-BB21-BC21-BD21 -> 344496.43 | BF21: =BA21*12 -> 5127900.4 | BG21: =Y21*2 -> 576966.44 | BH21: =BF21+BG21 -> 5704866.9 | BI21: =BH21*3.5% -> 199670.34 | BJ21: =(BH21*0.9-(BC21*12))*11%-BK21 -> 296781.43 | BK21: =BH21*0.9*5% -> 256719.01 | BL21: =BH21*3% -> 171146.01 | BM21: =BH21+BJ21+BK21+BL21+BI21 -> 6629183.6
A22: =A21+1 -> 9 | B22: =B21+1 -> 9 | C22: Долаев Архат Садырбаевич | D22: алгебра, геометрия, есептерді шешу практикумы 9DE | E22: Ж | F22: Педагог-шебер | H22: 43.08.00 | I22: 17697 | J22: 11.4 | K22: =I22*J22 -> 201745.8 | N22: 16 | Q22: =SUM(L22:P22) -> 16 | T22: 2 | W22: =SUM(R22:V22) -> 2 | X22: =Q22+W22 -> 18 | Y22: =K22/16*X22 -> 226964.03 | Z22: =Y22*10% -> 22696.403 | AA22: 18 | AB22: =I22/16*AA22*40% -> 7963.65 | AC22: 0 | AD22: =I22/16*AC22*40%*50% -> 0 | AF22: A305 | AG22: =17697*20% -> 3539.4 | AJ22: =X22 -> 18 | AK22: =I22/16*AJ22*40% -> 7963.65 | AL22: =X22 -> 18 | AM22: =K22/16*AL22*30% -> 68089.208 | AN22: =F22 -> Педагог-шебер | AO22: =IF(AN22="Педагог-зерттеуші", "0", IF(AN22="Педагог-шебер",K22/16*X22*50%, IF(AN22="Педагог-сарапшы", "0", IF(AN22="Педагог-модератор", "0", "0")))) -> 113482.01 | AP22: =IF(AN22="Педагог-шебер", "0", IF(AN22="Педагог-зерттеуші",K22/16*X22*40%, IF(AN22="Педагог-сарапшы", "0", IF(AN22="Педагог-модератор", "0", "0")))) -> 0 | AQ22: =IF(AN22="Педагог-шебер", "0", IF(AN22="Педагог-сарапшы",K22/16*X22*35%, IF(AN22="Педагог-зерттеуші", "0", IF(AN22="Педагог-модератор", "0", "0")))) -> 0 | AR22: =IF(AN22="Педагог-шебер", "0", IF(AN22="Педагог-модератор",K22/16*X22*30%, IF(AN22="Педагог-зерттеуші", "0", IF(AN22="Педагог-сарапшы", "0", "0")))) -> 0 | AW22: =G22 -> 0 | AZ22: =Z22+AB22+AD22+AE22+AG22+AI22+AK22+AM22+AO22+AP22+AQ22++AR22+AT22+AV22+AX22+AY22 -> 223734.32 | BA22: =Y22+AZ22 -> 450698.35 | BB22: =BA22*10% -> 45069.835 | BC22: =BA22*2% -> 9013.9669 | BD22: =(BA22-BB22-BC22-(14*4325))*10% -> 33606.455 | BE22: =BA22-BB22-BC22-BD22 -> 363008.09 | BF22: =BA22*12 -> 5408380.2 | BG22: =Y22*2 -> 453928.05 | BH22: =BF22+BG22 -> 5862308.2 | BI22: =BH22*3.5% -> 205180.79 | BJ22: =(BH22*0.9-(BC22*12))*11%-BK22 -> 304666.21 | BK22: =BH22*0.9*5% -> 263803.87 | BL22: =BH22*3% -> 175869.25 | BM22: =BH22+BJ22+BK22+BL22+BI22 -> 6811828.3
A23: =A22+1 -> 10 | B23: =B22+1 -> 10 | C23: Ермеков Нұржан Харпесұлы | D23: алгебра, геометрия, есептерді шешу практикум 8КL 9FK | E23: А/О | F23: Педагог-модератор | H23: 01.03.14 | I23: 17697 | J23: 8.14 | K23: =I23*J23 -> 144053.58 | M23: 16 | N23: 16 | Q23: =SUM(L23:P23) -> 32 | S23: 2 | T23: 2 | W23: =SUM(R23:V23) -> 4 | X23: =Q23+W23 -> 36 | Y23: =K23/16*X23 -> 324120.56 | Z23: =Y23*10% -> 32412.056 | AA23: 18 | AB23: =I23/16*AA23*40% -> 7963.65 | AC23: 18 | AD23: =I23/16*AC23*40%*50% -> 3981.825 | AF23: A003 | AG23: =17697*20% -> 3539.4 | AJ23: =X23 -> 36 | AK23: =I23/16*AJ23*40% -> 15927.3 | AL23: =X23 -> 36 | AM23: =K23/16*AL23*30% -> 97236.167 | AN23: =F23 -> Педагог-модератор | AO23: =IF(AN23="Педагог-зерттеуші", "0", IF(AN23="Педагог-шебер",K23/16*X23*50%, IF(AN23="Педагог-сарапшы", "0", IF(AN23="Педагог-модератор", "0", "0")))) -> 0 | AP23: =IF(AN23="Педагог-шебер", "0", IF(AN23="Педагог-зерттеуші",K23/16*X23*40%, IF(AN23="Педагог-сарапшы", "0", IF(AN23="Педагог-модератор", "0", "0")))) -> 0 | AQ23: =IF(AN23="Педагог-шебер", "0", IF(AN23="Педагог-сарапшы",K23/16*X23*35%, IF(AN23="Педагог-зерттеуші", "0", IF(AN23="Педагог-модератор", "0", "0")))) -> 0 | AR23: =IF(AN23="Педагог-шебер", "0", IF(AN23="Педагог-модератор",K23/16*X23*30%, IF(AN23="Педагог-зерттеуші", "0", IF(AN23="Педагог-сарапшы", "0", "0")))) -> 97236.167 | AW23: =G23 -> 0 | AZ23: =Z23+AB23+AD23+AE23+AG23+AI23+AK23+AM23+AO23+AP23+AQ23++AR23+AT23+AV23+AX23+AY23 -> 258296.56 | BA23: =Y23+AZ23 -> 582417.12 | BB23: =BA23*10% -> 58241.712 | BC23: =BA23*2% -> 11648.342 | BD23: =(BA23-BB23-BC23-(14*4325))*10% -> 45197.706 | BE23: =BA23-BB23-BC23-BD23 -> 467329.36 | BF23: =BA23*12 -> 6989005.4 | BG23: =Y23*2 -> 648241.11 | BH23: =BF23+BG23 -> 7637246.5 | BI23: =BH23*3.5% -> 267303.63 | BJ23: =(BH23*0.9-(BC23*12))*11%-BK23 -> 397035.5 | BK23: =BH23*0.9*5% -> 343676.09 | BL23: =BH23*3% -> 229117.4 | BM23: =BH23+BJ23+BK23+BL23+BI23 -> 8874379.2
A24: =A23+1 -> 11 | B24: =B23+1 -> 11 | C24: Есмагамбетова Лязат Амиргалиевна | D24: алгебра, геометрия, есептерді шешу практикумы 11DK | E24: Ж | F24: Педагог-шебер | H24: 41.11.19 | I24: 17697 | J24: 11.4 | K24: =I24*J24 -> 201745.8 | P24: 18 | Q24: =SUM(L24:P24) -> 18 | W24: =SUM(R24:V24) -> 0 | X24: =Q24+W24 -> 18 | Y24: =K24/16*X24 -> 226964.03 | Z24: =Y24*10% -> 22696.403 | AA24: 18 | AB24: =I24/16*AA24*40% -> 7963.65 | AC24: 0 | AD24: =I24/16*AC24*40%*50% -> 0 | AJ24: =X24 -> 18 | AK24: =I24/16*AJ24*40% -> 7963.65 | AL24: =X24 -> 18 | AM24: =K24/16*AL24*30% -> 68089.208 | AN24: =F24 -> Педагог-шебер | AO24: =IF(AN24="Педагог-зерттеуші", "0", IF(AN24="Педагог-шебер",K24/16*X24*50%, IF(AN24="Педагог-сарапшы", "0", IF(AN24="Педагог-модератор", "0", "0")))) -> 113482.01 | AP24: =IF(AN24="Педагог-шебер", "0", IF(AN24="Педагог-зерттеуші",K24/16*X24*40%, IF(AN24="Педагог-сарапшы", "0", IF(AN24="Педагог-модератор", "0", "0")))) -> 0 | AQ24: =IF(AN24="Педагог-шебер", "0", IF(AN24="Педагог-сарапшы",K24/16*X24*35%, IF(AN24="Педагог-зерттеуші", "0", IF(AN24="Педагог-модератор", "0", "0")))) -> 0 | AR24: =IF(AN24="Педагог-шебер", "0", IF(AN24="Педагог-модератор",K24/16*X24*30%, IF(AN24="Педагог-зерттеуші", "0", IF(AN24="Педагог-сарапшы", "0", "0")))) -> 0 | AW24: =G24 -> 0 | AZ24: =Z24+AB24+AD24+AE24+AG24+AI24+AK24+AM24+AO24+AP24+AQ24++AR24+AT24+AV24+AX24+AY24 -> 220194.92 | BA24: =Y24+AZ24 -> 447158.95 | BB24: =BA24*10% -> 44715.895 | BC24: =BA24*2% -> 8943.1789 | BD24: =(BA24-BB24-BC24-(14*4325))*10% -> 33294.987 | BE24: =BA24-BB24-BC24-BD24 -> 360204.89 | BF24: =BA24*12 -> 5365907.4 | BG24: =Y24*2 -> 453928.05 | BH24: =BF24+BG24 -> 5819835.4 | BI24: =BH24*3.5% -> 203694.24 | BJ24: =(BH24*0.9-(BC24*12))*11%-BK24 -> 302466.12 | BK24: =BH24*0.9*5% -> 261892.59 | BL24: =BH24*3% -> 174595.06 | BM24: =BH24+BJ24+BK24+BL24+BI24 -> 6762483.4
A25: =A24+1 -> 12 | B25: =B24+1 -> 12 | C25: Жаруллаев Дастан Берікұлы | D25: алгебра, геометрия, есептерді шешу практикумы 7АCGH | E25: Ж | F25: Педагог-модератор | H25: 06.04.00 | I25: 17697 | J25: 10.22 | K25: =I25*J25 -> 180863.34 | L25: 32 | Q25: =SUM(L25:P25) -> 32 | R25: 4 | W25: =SUM(R25:V25) -> 4 | X25: =Q25+W25 -> 36 | Y25: =K25/16*X25 -> 406942.52 | Z25: =Y25*10% -> 40694.252 | AA25: 0 | AB25: =I25/16*AA25*40% -> 0 | AC25: 36 | AD25: =I25/16*AC25*40%*50% -> 7963.65 | AF25: A005 | AG25: =17697*20% -> 3539.4 | AJ25: =X25 -> 36 | AK25: =I25/16*AJ25*40% -> 15927.3 | AL25: =X25 -> 36 | AM25: =K25/16*AL25*30% -> 122082.75 | AN25: =F25 -> Педагог-модератор | AO25: =IF(AN25="Педагог-зерттеуші", "0", IF(AN25="Педагог-шебер",K25/16*X25*50%, IF(AN25="Педагог-сарапшы", "0", IF(AN25="Педагог-модератор", "0", "0")))) -> 0 | AP25: =IF(AN25="Педагог-шебер", "0", IF(AN25="Педагог-зерттеуші",K25/16*X25*40%, IF(AN25="Педагог-сарапшы", "0", IF(AN25="Педагог-модератор", "0", "0")))) -> 0 | AQ25: =IF(AN25="Педагог-шебер", "0", IF(AN25="Педагог-сарапшы",K25/16*X25*35%, IF(AN25="Педагог-зерттеуші", "0", IF(AN25="Педагог-модератор", "0", "0")))) -> 0 | AR25: =IF(AN25="Педагог-шебер", "0", IF(AN25="Педагог-модератор",K25/16*X25*30%, IF(AN25="Педагог-зерттеуші", "0", IF(AN25="Педагог-сарапшы", "0", "0")))) -> 122082.75 | AW25: =G25 -> 0 | AZ25: =Z25+AB25+AD25+AE25+AG25+AI25+AK25+AM25+AO25+AP25+AQ25++AR25+AT25+AV25+AX25+AY25 -> 312290.11 | BA25: =Y25+AZ25 -> 719232.63 | BB25: =BA25*10% -> 71923.263 | BC25: =BA25*2% -> 14384.653 | BD25: =(BA25-BB25-BC25-(14*4325))*10% -> 57237.471 | BE25: =BA25-BB25-BC25-BD25 -> 575687.24 | BF25: =BA25*12 -> 8630791.5 | BG25: =Y25*2 -> 813885.03 | BH25: =BF25+BG25 -> 9444676.5 | BI25: =BH25*3.5% -> 330563.68 | BJ25: =(BH25*0.9-(BC25*12))*11%-BK25 -> 491024.79 | BK25: =BH25*0.9*5% -> 425010.44 | BL25: =BH25*3% -> 283340.3 | BM25: =BH25+BJ25+BK25+BL25+BI25 -> 10974616
