Workbook

Sheet План 2024
C6: филиал НАО "Республиканская физико-математическая школа" в г.Алматы
C7: План финансирования по платежам на 2024 год
C8: Регион: | G8: город Алматы
C9: Вид бюджета: | G9: За счет средств из республиканского бюджета- государственный образовательный грант в виде дотации
C10: Период: | G10: 2024 год
C11: Единицы измерения: | G11: в тенге
G12: АО "Финансовый центр"
B14: № | C14: Программа Подпрограмма Специфика | G14: Наименование расходов | H14: Финансовый план на 2024 год по ДОГОВОРУ | I14: План по месяцам
I15: Январь | J15: Февраль | K15: Март | L15: Апрель | M15: Май | N15: Июнь | O15: Июль | P15: Август | Q15: Сентябрь | R15: Октябрь | S15: Ноябрь | T15: Декабрь
G16: Государственный образовательный грант | H16: =I16+J16+K16+L16+M16+Q16+R16+S16+T16 -> 1.0890545e+08 | I16: 12100606 | J16: 12100606 | K16: 12100606 | L16: 12100606 | M16: 12100606 | Q16: 12100606 | R16: 12100606 | S16: 12100606 | T16: 12100606
B17: 1 | C17: Оплата труда | H17: =I17+J17+K17+L17+M17+Q17+R17+S17+T17 -> 94900213 | I17: =I16-I18-I19-I20-I21 -> 10544468 | J17: =J16-J18-J19-J20-J21 -> 10544468 | K17: =K16-K18-K19-K20-K21 -> 10544468 | L17: =L16-L18-L19-L20-L21 -> 10544468 | M17: =M16-M18-M19-M20-M21 -> 10544468 | Q17: =Q16-Q18-Q19-Q20-Q21 -> 10544468 | R17: =R16-R18-R19-R20-R21 -> 10544468 | S17: =S16-S18-S19-S20-S21 -> 10544468 | T17: =T16-T18-T19-T20-T21 -> 10544468
B18: 2 | C18: Социальный налог | H18: =I18+J18+K18+L18+M18+Q18+R18+S18+T18 -> 5673974.2 | I18: =((I16*0.9)-(I16*2%))*9.5%-I19 -> 630441.58 | J18: =((J16*0.9)-(J16*2%))*9.5%-J19 -> 630441.58 | K18: =((K16*0.9)-(K16*2%))*9.5%-K19 -> 630441.58 | L18: =((L16*0.9)-(L16*2%))*9.5%-L19 -> 630441.58 | M18: =((M16*0.9)-(M16*2%))*9.5%-M19 -> 630441.58 | Q18: =((Q16*0.9)-(Q16*2%))*9.5%-Q19 -> 630441.58 | R18: =((R16*0.9)-(R16*2%))*9.5%-R19 -> 630441.58 | S18: =((S16*0.9)-(S16*2%))*9.5%-S19 -> 630441.58 | T18: =((T16*0.9)-(T16*2%))*9.5%-T19 -> 630441.58
B19: 3 | C19: Социальные отчисление в Государственный фонд Социального страхования | H19: =I19+J19+K19+L19+M19+Q19+R19+S19+T19 -> 3430521.8 | I19: =I16*0.9*3.5% -> 381169.09 | J19: =J16*0.9*3.5% -> 381169.09 | K19: =K16*0.9*3.5% -> 381169.09 | L19: =L16*0.9*3.5% -> 381169.09 | M19: =M16*0.9*3.5% -> 381169.09 | Q19: =Q16*0.9*3.5% -> 381169.09 | R19: =R16*0.9*3.5% -> 381169.09 | S19: =S16*0.9*3.5% -> 381169.09 | T19: =T16*0.9*3.5% -> 381169.09
B20: 4 | C20: Отчисление на обязательное социальное медицинское страхование | H20: =I20+J20+K20+L20+M20+Q20+R20+S20+T20 -> 3267163.6 | I20: =I16*3% -> 363018.18 | J20: =J16*3% -> 363018.18 | K20: =K16*3% -> 363018.18 | L20: =L16*3% -> 363018.18 | M20: =M16*3% -> 363018.18 | Q20: =Q16*3% -> 363018.18 | R20: =R16*3% -> 363018.18 | S20: =S16*3% -> 363018.18 | T20: =T16*3% -> 363018.18
B21: 5 | C21: Обязательные пенсионные взносы | H21: =I21+J21+K21+L21+M21+Q21+R21+S21+T21 -> 1633581.8 | I21: =I16*1.5% -> 181509.09 | J21: =J16*1.5% -> 181509.09 | K21: =K16*1.5% -> 181509.09 | L21: =L16*1.5% -> 181509.09 | M21: =M16*1.5% -> 181509.09 | Q21: =Q16*1.5% -> 181509.09 | R21: =R16*1.5% -> 181509.09 | S21: =S16*1.5% -> 181509.09 | T21: =T16*1.5% -> 181509.09
G22: Всего: | H22: =H17+H18+H19+H20+H21 -> 1.0890545e+08 | I22: =I17+I18+I19+I20+I21 -> 12100606 | J22: =J17+J18+J19+J20+J21 -> 12100606 | K22: =K17+K18+K19+K20+K21 -> 12100606 | L22: =L17+L18+L19+L20+L21 -> 12100606 | M22: =M17+M18+M19+M20+M21 -> 12100606 | Q22: =Q17+Q18+Q19+Q20+Q21 -> 12100606 | R22: =R17+R18+R19+R20+R21 -> 12100606 | S22: =S17+S18+S19+S20+S21 -> 12100606 | T22: =T17+T18+T19+T20+T21 -> 12100606
D26: Директор ФНАО "РФМШ" Алматы | M26: Меирбек Меирлан Едигерулы
D27: Индивидуального плана финансирования | J27: (подпись) | M27: (расшифровка подписи)
D29: Экономист ФНАО "РФМШ" Алматы | M29: Куюкова Гаухар Ермековна
D30: Индивидуального плана финансирования | J30: (подпись) | M30: (расшифровка подписи)

Sheet План дотация 2026
C6: филиал НАО «Республиканская физико-математическая школа» в г.Алматы
C7: План финансирования Государственный образовательный заказ (ДОТАЦИЯ) на 2026 год
C8: Регион: | G8: город Алматы
C9: Вид бюджета: | G9: За счет средств из республиканского бюджета- государственный образовательный грант в виде дотации
C10: Период: | G10: 2026 год
C11: Единицы измерения: | G11: в тенге
C12: Администратор бюджетных программ ГУ: | H12: Управление образования г.Алматы
B14: № | C14: Наименование расходов | G14: Финансовый план на 2026 год по ДОГОВОРУ | H14: План по месяцам
H15: Январь | I15: Февраль | J15: Март | K15: Апрель | L15: Май | M15: Июнь | N15: Июль | O15: Август | P15: Сентябрь | Q15: Октябрь | R15: Ноябрь | S15: Декабрь
B16: 1 | C16: Оплата труда | G16: =H16+I16+J16+K16+L16+P16+Q16+R16+S16 -> 1.2523235e+08 | H16: 13914706 | I16: 13914706 | J16: 13914706 | K16: 13914706 | L16: 13914706 | P16: 13914706 | Q16: 13914706 | R16: 13914706 | S16: 13914706
B17: 2 | C17: Обязательные пенсионные взносы за счет работодателя | G17: =H17+I17+J17+K17+L17+P17+Q17+R17+S17 -> 4383132.3 | H17: 487014.7 | I17: 487014.7 | J17: 487014.7 | K17: 487014.7 | L17: 487014.7 | P17: 487014.7 | Q17: 487014.7 | R17: 487014.7 | S17: 487014.67
B18: 3 | C18: Социальный налог | G18: =H18+I18+J18+K18+L18+P18+Q18+R18+S18 -> 6487035.8 | H18: 720781.75 | I18: 720781.75 | J18: 720781.75 | K18: 720781.75 | L18: 720781.75 | P18: 720781.75 | Q18: 720781.75 | R18: 720781.75 | S18: 720781.76
B19: 4 | C19: Социальные отчисления в Государственный фонд социального страхования | G19: =H19+I19+J19+K19+L19+P19+Q19+R19+S19 -> 5635455.8 | H19: 626161.75 | I19: 626161.75 | J19: 626161.75 | K19: 626161.75 | L19: 626161.75 | P19: 626161.75 | Q19: 626161.75 | R19: 626161.75 | S19: 626161.78
B20: 5 | C20: Обязательное социальное медицинское страхование | G20: =H20+I20+J20+K20+L20+P20+Q20+R20+S20 -> 3756970.5 | H20: 417441.17 | I20: 417441.17 | J20: 417441.17 | K20: 417441.17 | L20: 417441.17 | P20: 417441.17 | Q20: 417441.17 | R20: 417441.17 | S20: 417441.16
G21: =G16+G17+G18+G19+G20 -> 145494945 | H21: =H16+H17+H18+H19+H20 -> 16166105 | I21: =I16+I17+I18+I19+I20 -> 16166105 | J21: =J16+J17+J18+J19+J20 -> 16166105 | K21: =K16+K17+K18+K19+K20 -> 16166105 | L21: =L16+L17+L18+L19+L20 -> 16166105 | M21: =M16+M17+M18+M19+M20 -> 0 | N21: =N16+N17+N18+N19+N20 -> 0 | ... S21: =S16+S17+S18+S19+S20 -> 16166105
D26: Директор ФНАО «РФМШ» Алматы | L26: Меирбек Меирлан Едигерулы
D27: Индивидуального плана финансирования | I27: (подпись) | L27: (расшифровка подписи)
D29: Экономист ФНАО «РФМШ» Алматы | L29: Куюкова Гаухар Ермековна
D30: Индивидуального плана финансирования | I30: (подпись) | L30: (расшифровка подписи)

Sheet ПЛАН ПУ 2026 
C5: филиал НАО «Республиканская физико-математическая школа» в г.Алматы
C6: План финансирования по платежам на 2026 год филиала г.Алматы
C7: Регион: | G7: город Алматы
C8: Вид бюджета: | G8: За счет средств от реализации образовательных услуг на возмездной основе
C9: Период: | G9: 2026 год
C10: Единицы измерения: в тенге
B12: № | C12: Наименование расходов | H12: Финансовый план на 2026 год | I12: План по месяцам
I13: Январь | J13: Февраль | K13: Март | L13: Апрель | M13: Май | N13: Июнь | O13: Июль | P13: Август | Q13: Сентябрь | R13: Октябрь | S13: Ноябрь | T13: Декабрь
C14: Оплата прочих услуг и работ
B15: =0+1 -> 1 | C15: Оплата труда | H15: =I15+J15+K15+L15+M15+N15+O15+P15+Q15+R15+S15+T15 -> 32829577 | I15: =2735798.08+0.01 -> 2735798.1 | J15: 2735798.1 | K15: 2735798.1 | L15: 2735798.1 | M15: =2735798.08*1.4 -> 3830117.3 | N15: =2735798.08*1.3 -> 3556537.5 | O15: =2735798.08*0.7 -> 1915058.7 | P15: =2735798.08*0.6-0.01 -> 1641478.8 | Q15: 2735798.1 | R15: 2735798.1 | S15: 2735798.1 | T15: 2735798.1
B16: =B15+1 -> 2 | C16: Дополнительные денежные выплаты | H16: =I16+J16+K16+L16+M16+N16+O16+P16+Q16+R16+S16+T16 -> 3.6145763e+08 | K16: 90364407 | N16: 90364407 | Q16: =90364407.07-0.01 -> 90364407 | T16: 90364407
B17: =B16+1 -> 3 | C17: Компенсационные выплаты | H17: =I17+J17+K17+L17+M17+N17+O17+P17+Q17+R17+S17+T17 -> 3448613.9 | I17: 1000000 | M17: 1224307 | N17: 1224307
B18: =B17+1 -> 4 | C18: Обязательные пенсионные взносы за счет средств работодателя | H18: =I18+J18+K18+L18+M18+N18+O18+P18+Q18+R18+S18+T18 -> 13920754 | I18: 1160062.8 | J18: 1160062.8 | K18: 1160062.8 | L18: 1160062.8 | M18: =1160062.8*1.4 -> 1624087.9 | N18: =1160062.8*1.3+0.07 -> 1508081.7 | O18: =1160062.8*0.7 -> 812043.96 | P18: =1160062.8*0.6 -> 696037.68 | Q18: 1160062.8 | R18: 1160062.8 | S18: 1160062.8 | T18: 1160062.8
B19: =B18+1 -> 5 | C19: Социальный налог | H19: =I19+J19+K19+L19+M19+N19+O19+P19+Q19+R19+S19+T19 -> 23263209 | I19: 1938600.7 | J19: 1938600.7 | K19: 1938600.7 | L19: 1938600.7 | M19: =1938600.73*1.4 -> 2714041 | N19: =1938600.73*1.3+0.04 -> 2520181 | O19: =1938600.73*0.7 -> 1357020.5 | P19: =1938600.73*0.6 -> 1163160.4 | Q19: 1938600.7 | R19: 1938600.7 | S19: 1938600.7 | T19: 1938600.7
B20: =B19+1 -> 6 | C20: Социальные отчисления в Государственный фонд социального страхования | H20: =I20+J20+K20+L20+M20+N20+O20+P20+Q20+R20+S20+T20 -> 17898112 | I20: 1491509.3 | J20: 1491509.3 | K20: 1491509.3 | L20: 1491509.3 | M20: =1491509.32*1.4 -> 2088113 | N20: =1491509.32*1.3+0.02 -> 1938962.1 | O20: =1491509.32*0.7 -> 1044056.5 | P20: =1491509.32*0.6 -> 894905.59 | Q20: 1491509.3 | R20: 1491509.3 | S20: 1491509.3 | T20: 1491509.3
B21: =B20+1 -> 7 | C21: Обязательное медицинское страхование | H21: =I21+J21+K21+L21+M21+N21+O21+P21+Q21+R21+S21+T21 -> 11932075 | I21: 994339.55 | J21: 994339.55 | K21: 994339.55 | L21: 994339.55 | M21: =994339.55*1.4 -> 1392075.4 | N21: =994339.55*1.3-0.03 -> 1292641.4 | O21: =994339.55*0.7 -> 696037.68 | P21: =994339.55*0.6 -> 596603.73 | Q21: 994339.55 | R21: 994339.55 | S21: 994339.55 | T21: 994339.55
B22: =B21+1 -> 8 | C22: Приобретение топлива, горюче-смазочных материалов | H22: =I22+J22+K22+L22+M22+N22+O22+P22+Q22+R22+S22+T22 -> 357000 | I22: 357000
B23: =B22+1 -> 9 | C23: Приобретение прочих запасов | H23: =I23+J23+K23+L23+M23+N23+O23+P23+Q23+R23+S23+T23 -> 1397640 | I23: 465880 | J23: 465880 | K23: 465880
B24: =B23+1 -> 10 | C24: Оплата прочих услуг и работ | H24: =I24+J24+K24+L24+M24+N24+O24+P24+Q24+R24+S24+T24 -> 36649723 | I24: 4072191.5 | J24: 4072191.5 | K24: 4072191.5 | L24: 4072191.5 | M24: 4072191.5 | N24: 4072191.5 | O24: 4072191.5 | P24: 4072191.5 | Q24: 4072191.5
B25: =B24+1 -> 11 | C25: Командировки и служебные разъеды в пределах РК филиала г.Алматы | H25: =I25+J25+K25+L25+M25+N25+O25+P25+Q25+R25+S25+T25 -> 8165850 | I25: 680487.5 | J25: 680487.5 | K25: 680487.5 | L25: 680487.5 | M25: 680487.5 | N25: 680487.5 | O25: 680487.5 | P25: 680487.5 | Q25: 680487.5 | R25: 680487.5 | S25: 680487.5 | T25: 680487.5
B26: =B25+1 -> 12 | C26: Командировки и служебные разъеды за пределы РК филиала г.Алматы | H26: =I26+J26+K26+L26+M26+N26+O26+P26+Q26+R26+S26+T26 -> 15245596 | I26: 2540932.7 | K26: 2540932.7 | M26: 2540932.7 | O26: 2540932.7 | Q26: 2540932.7 | T26: 2540932.7
B27: =B26+1 -> 13 | C27: Организация горячим пятиразовым питанием учащихся проживающих в интернате в рамках фонда всеобуча | H27: =I27+J27+K27+L27+M27+N27+O27+P27+Q27+R27+S27+T27 -> 10121100 | I27: 1124566.7 | J27: 1124566.7 | K27: 1124566.7 | L27: 1124566.7 | M27: 1124566.7 | Q27: 1124566.7 | R27: 1124566.7 | S27: 1124566.7 | T27: 1124566.7
B28: =B27+1 -> 14 | C28: Прочие текущие затраты | H28: =I28+J28+K28+L28+M28+N28+O28+P28+Q28+R28+S28+T28 -> 15971789 | I28: 1330982.4 | J28: 1330982.4 | K28: 1330982.4 | L28: 1330982.4 | M28: 1330982.4 | N28: 1330982.4 | O28: 1330982.4 | P28: 1330982.4 | Q28: 1330982.4 | R28: 1330982.4 | S28: 1330982.4 | T28: 1330982.4
B29: =B28+1 -> 15 | C29: Приобретение машин, оборудования, инструментов, производственного и хозяйственного инвентаря | H29: =I29+J29+K29+L29+M29+N29+O29+P29+Q29+R29+S29+T29 -> 130274348 | I29: 32568587 | J29: 32568587 | K29: 32568587 | L29: 32568587
B30: =B29+1 -> 16 | C30: Приобретение прочих основных средств (библиотечный фонд) | H30: =I30+J30+K30+L30+M30+N30+O30+P30+Q30+R30+S30+T30 -> 19986850 | Q30: 4996712.5 | R30: 4996712.5 | S30: 4996712.5 | T30: 4996712.5
B31: =B30+1 -> 17 | C31: Дополнительные денежные выплаты за счет средств ФНАО РФМШ Астаны | H31: =I31+J31+K31+L31+M31+N31+O31+P31+Q31+R31+S31+T31 -> -1.4307986e+08 | K31: -35769966 | N31: -35769966 | Q31: -35769966 | T31: -35769966
H32: =SUM(H15:H31) -> 559840000 | I32: =SUM(I15:I31) -> 52460938 | J32: =SUM(J15:J31) -> 48563006 | K32: =SUM(K15:K31) -> 1.0569838e+08 | L32: =SUM(L15:L31) -> 48097126 | M32: =SUM(M15:M31) -> 22621902 | N32: =SUM(N15:N31) -> 72718813 | O32: =SUM(O15:O31) -> 14448811 | ... T32: =SUM(T15:T31) -> 73588433
C38: Директор филиала НАО «РФМШ» | L38: Меирбек Меирлан Едигерулы
C42: Экономист филиала НАО «РФМШ» | L42: Куюкова Гаухар Ермековна

Sheet СВОД ПЛАНА 2026
C5: филиал НАО «Республиканская физико-математическая школа» в г.Алматы
C6: План финансирования по платежам на 2026 год филиала г.Алматы
C7: Регион: | G7: город Алматы
C8: Вид бюджета: | G8: За счет средств от реализации образовательных услуг на возмездной основе, также дотация за счет средств республиканского бюджета
C9: Период: | G9: 2026 год
C10: Единицы измерения: в тенге
B12: № | C12: Наименование расходов | H12: Финансовый план на 2026 год | I12: План по месяцам
I13: Январь | J13: Февраль | K13: Март | L13: Апрель | M13: Май | N13: Июнь | O13: Июль | P13: Август | Q13: Сентябрь | R13: Октябрь | S13: Ноябрь | T13: Декабрь
C14: Оплата прочих услуг и работ
B15: =0+1 -> 1 | C15: Оплата труда | H15: =I15+J15+K15+L15+M15+N15+O15+P15+Q15+R15+S15+T15 -> 1.5806193e+08 | I15: ='План дотация 2026'!H16+'ПЛАН ПУ 2026 '!I15 -> 16650504 | J15: ='План дотация 2026'!I16+'ПЛАН ПУ 2026 '!J15 -> 16650504 | K15: ='План дотация 2026'!J16+'ПЛАН ПУ 2026 '!K15 -> 16650504 | L15: ='План дотация 2026'!K16+'ПЛАН ПУ 2026 '!L15 -> 16650504 | M15: ='План дотация 2026'!L16+'ПЛАН ПУ 2026 '!M15 -> 17744823 | N15: ='План дотация 2026'!M16+'ПЛАН ПУ 2026 '!N15 -> 3556537.5 | O15: ='План дотация 2026'!N16+'ПЛАН ПУ 2026 '!O15 -> 1915058.7 | P15: ='План дотация 2026'!O16+'ПЛАН ПУ 2026 '!P15 -> 1641478.8 | ... T15: ='План дотация 2026'!S16+'ПЛАН ПУ 2026 '!T15 -> 16650504
B16: =B15+1 -> 2 | C16: Дополнительные денежные выплаты | H16: =I16+J16+K16+L16+M16+N16+O16+P16+Q16+R16+S16+T16 -> 3.6145763e+08 | I16: ='ПЛАН ПУ 2026 '!I16 -> 0 | J16: ='ПЛАН ПУ 2026 '!J16 -> 0 | K16: ='ПЛАН ПУ 2026 '!K16 -> 90364407 | L16: ='ПЛАН ПУ 2026 '!L16 -> 0 | M16: ='ПЛАН ПУ 2026 '!M16 -> 0 | N16: ='ПЛАН ПУ 2026 '!N16 -> 90364407 | O16: ='ПЛАН ПУ 2026 '!O16 -> 0 | P16: ='ПЛАН ПУ 2026 '!P16 -> 0 | ... T16: ='ПЛАН ПУ 2026 '!T16 -> 90364407
B17: =B16+1 -> 3 | C17: Компенсационные выплаты | H17: =I17+J17+K17+L17+M17+N17+O17+P17+Q17+R17+S17+T17 -> 3448613.9 | I17: ='ПЛАН ПУ 2026 '!I17 -> 1000000 | J17: ='ПЛАН ПУ 2026 '!J17 -> 0 | K17: ='ПЛАН ПУ 2026 '!K17 -> 0 | L17: ='ПЛАН ПУ 2026 '!L17 -> 0 | M17: ='ПЛАН ПУ 2026 '!M17 -> 1224307 | N17: ='ПЛАН ПУ 2026 '!N17 -> 1224307 | O17: ='ПЛАН ПУ 2026 '!O17 -> 0 | P17: ='ПЛАН ПУ 2026 '!P17 -> 0 | ... T17: ='ПЛАН ПУ 2026 '!T17 -> 0
B18: =B17+1 -> 4 | C18: Обязательные пенсионные взносы за счет средств работодателя | H18: =I18+J18+K18+L18+M18+N18+O18+P18+Q18+R18+S18+T18 -> 18303886 | I18: ='План дотация 2026'!H17+'ПЛАН ПУ 2026 '!I18 -> 1647077.5 | J18: ='План дотация 2026'!I17+'ПЛАН ПУ 2026 '!J18 -> 1647077.5 | K18: ='План дотация 2026'!J17+'ПЛАН ПУ 2026 '!K18 -> 1647077.5 | L18: ='План дотация 2026'!K17+'ПЛАН ПУ 2026 '!L18 -> 1647077.5 | M18: ='План дотация 2026'!L17+'ПЛАН ПУ 2026 '!M18 -> 2111102.6 | N18: ='План дотация 2026'!M17+'ПЛАН ПУ 2026 '!N18 -> 1508081.7 | O18: ='План дотация 2026'!N17+'ПЛАН ПУ 2026 '!O18 -> 812043.96 | P18: ='План дотация 2026'!O17+'ПЛАН ПУ 2026 '!P18 -> 696037.68 | ... T18: ='План дотация 2026'!S17+'ПЛАН ПУ 2026 '!T18 -> 1647077.5
B19: =B18+1 -> 5 | C19: Социальный налог | H19: =I19+J19+K19+L19+M19+N19+O19+P19+Q19+R19+S19+T19 -> 29750245 | I19: ='План дотация 2026'!H18+'ПЛАН ПУ 2026 '!I19 -> 2659382.5 | J19: ='План дотация 2026'!I18+'ПЛАН ПУ 2026 '!J19 -> 2659382.5 | K19: ='План дотация 2026'!J18+'ПЛАН ПУ 2026 '!K19 -> 2659382.5 | L19: ='План дотация 2026'!K18+'ПЛАН ПУ 2026 '!L19 -> 2659382.5 | M19: ='План дотация 2026'!L18+'ПЛАН ПУ 2026 '!M19 -> 3434822.8 | N19: ='План дотация 2026'!M18+'ПЛАН ПУ 2026 '!N19 -> 2520181 | O19: ='План дотация 2026'!N18+'ПЛАН ПУ 2026 '!O19 -> 1357020.5 | P19: ='План дотация 2026'!O18+'ПЛАН ПУ 2026 '!P19 -> 1163160.4 | ... T19: ='План дотация 2026'!S18+'ПЛАН ПУ 2026 '!T19 -> 2659382.5
B20: =B19+1 -> 6 | C20: Социальные отчисления в Государственный фонд социального страхования | H20: =I20+J20+K20+L20+M20+N20+O20+P20+Q20+R20+S20+T20 -> 23533568 | I20: ='План дотация 2026'!H19+'ПЛАН ПУ 2026 '!I20 -> 2117671.1 | J20: ='План дотация 2026'!I19+'ПЛАН ПУ 2026 '!J20 -> 2117671.1 | K20: ='План дотация 2026'!J19+'ПЛАН ПУ 2026 '!K20 -> 2117671.1 | L20: ='План дотация 2026'!K19+'ПЛАН ПУ 2026 '!L20 -> 2117671.1 | M20: ='План дотация 2026'!L19+'ПЛАН ПУ 2026 '!M20 -> 2714274.8 | N20: ='План дотация 2026'!M19+'ПЛАН ПУ 2026 '!N20 -> 1938962.1 | O20: ='План дотация 2026'!N19+'ПЛАН ПУ 2026 '!O20 -> 1044056.5 | P20: ='План дотация 2026'!O19+'ПЛАН ПУ 2026 '!P20 -> 894905.59 | ... T20: ='План дотация 2026'!S19+'ПЛАН ПУ 2026 '!T20 -> 2117671.1
B21: =B20+1 -> 7 | C21: Обязательное медицинское страхование | H21: =I21+J21+K21+L21+M21+N21+O21+P21+Q21+R21+S21+T21 -> 15689045 | I21: ='План дотация 2026'!H20+'ПЛАН ПУ 2026 '!I21 -> 1411780.7 | J21: ='План дотация 2026'!I20+'ПЛАН ПУ 2026 '!J21 -> 1411780.7 | K21: ='План дотация 2026'!J20+'ПЛАН ПУ 2026 '!K21 -> 1411780.7 | L21: ='План дотация 2026'!K20+'ПЛАН ПУ 2026 '!L21 -> 1411780.7 | M21: ='План дотация 2026'!L20+'ПЛАН ПУ 2026 '!M21 -> 1809516.5 | N21: ='План дотация 2026'!M20+'ПЛАН ПУ 2026 '!N21 -> 1292641.4 | O21: ='План дотация 2026'!N20+'ПЛАН ПУ 2026 '!O21 -> 696037.68 | P21: ='План дотация 2026'!O20+'ПЛАН ПУ 2026 '!P21 -> 596603.73 | ... T21: ='План дотация 2026'!S20+'ПЛАН ПУ 2026 '!T21 -> 1411780.7
B22: =B21+1 -> 8 | C22: Приобретение топлива, горюче-смазочных материалов | H22: =I22+J22+K22+L22+M22+N22+O22+P22+Q22+R22+S22+T22 -> 357000 | I22: ='ПЛАН ПУ 2026 '!I22 -> 357000 | J22: ='ПЛАН ПУ 2026 '!J22 -> 0 | K22: ='ПЛАН ПУ 2026 '!K22 -> 0 | L22: ='ПЛАН ПУ 2026 '!L22 -> 0 | M22: ='ПЛАН ПУ 2026 '!M22 -> 0 | N22: ='ПЛАН ПУ 2026 '!N22 -> 0 | O22: ='ПЛАН ПУ 2026 '!O22 -> 0 | P22: ='ПЛАН ПУ 2026 '!P22 -> 0 | ... T22: ='ПЛАН ПУ 2026 '!T22 -> 0
B23: =B22+1 -> 9 | C23: Приобретение прочих запасов | H23: =I23+J23+K23+L23+M23+N23+O23+P23+Q23+R23+S23+T23 -> 1397640 | I23: ='ПЛАН ПУ 2026 '!I23 -> 465880 | J23: ='ПЛАН ПУ 2026 '!J23 -> 465880 | K23: ='ПЛАН ПУ 2026 '!K23 -> 465880 | L23: ='ПЛАН ПУ 2026 '!L23 -> 0 | M23: ='ПЛАН ПУ 2026 '!M23 -> 0 | N23: ='ПЛАН ПУ 2026 '!N23 -> 0 | O23: ='ПЛАН ПУ 2026 '!O23 -> 0 | P23: ='ПЛАН ПУ 2026 '!P23 -> 0 | ... T23: ='ПЛАН ПУ 2026 '!T23 -> 0
B24: =B23+1 -> 10 | C24: Оплата прочих услуг и работ | H24: =I24+J24+K24+L24+M24+N24+O24+P24+Q24+R24+S24+T24 -> 36649723 | I24: ='ПЛАН ПУ 2026 '!I24 -> 4072191.5 | J24: ='ПЛАН ПУ 2026 '!J24 -> 4072191.5 | K24: ='ПЛАН ПУ 2026 '!K24 -> 4072191.5 | L24: ='ПЛАН ПУ 2026 '!L24 -> 4072191.5 | M24: ='ПЛАН ПУ 2026 '!M24 -> 4072191.5 | N24: ='ПЛАН ПУ 2026 '!N24 -> 4072191.5 | O24: ='ПЛАН ПУ 2026 '!O24 -> 4072191.5 | P24: ='ПЛАН ПУ 2026 '!P24 -> 4072191.5 | ... T24: ='ПЛАН ПУ 2026 '!T24 -> 0
B25: =B24+1 -> 11 | C25: Командировки и служебные разъеды в пределах РК филиала г.Алматы | H25: =I25+J25+K25+L25+M25+N25+O25+P25+Q25+R25+S25+T25 -> 8165850 | I25: ='ПЛАН ПУ 2026 '!I25 -> 680487.5 | J25: ='ПЛАН ПУ 2026 '!J25 -> 680487.5 | K25: ='ПЛАН ПУ 2026 '!K25 -> 680487.5 | L25: ='ПЛАН ПУ 2026 '!L25 -> 680487.5 | M25: ='ПЛАН ПУ 2026 '!M25 -> 680487.5 | N25: ='ПЛАН ПУ 2026 '!N25 -> 680487.5 | O25: ='ПЛАН ПУ 2026 '!O25 -> 680487.5 | P25: ='ПЛАН ПУ 2026 '!P25 -> 680487.5 | ... T25: ='ПЛАН ПУ 2026 '!T25 -> 680487.5
B26: =B25+1 -> 12 | C26: Командировки и служебные разъеды за пределы РК филиала г.Алматы | H26: =I26+J26+K26+L26+M26+N26+O26+P26+Q26+R26+S26+T26 -> 15245596 | I26: ='ПЛАН ПУ 2026 '!I26 -> 2540932.7 | J26: ='ПЛАН ПУ 2026 '!J26 -> 0 | K26: ='ПЛАН ПУ 2026 '!K26 -> 2540932.7 | L26: ='ПЛАН ПУ 2026 '!L26 -> 0 | M26: ='ПЛАН ПУ 2026 '!M26 -> 2540932.7 | N26: ='ПЛАН ПУ 2026 '!N26 -> 0 | O26: ='ПЛАН ПУ 2026 '!O26 -> 2540932.7 | P26: ='ПЛАН ПУ 2026 '!P26 -> 0 | ... T26: ='ПЛАН ПУ 2026 '!T26 -> 2540932.7
B27: =B26+1 -> 13 | C27: Организация горячим пятиразовым питанием учащихся проживающих в интернате в рамках фонда всеобуча | H27: =I27+J27+K27+L27+M27+N27+O27+P27+Q27+R27+S27+T27 -> 10121100 | I27: ='ПЛАН ПУ 2026 '!I27 -> 1124566.7 | J27: ='ПЛАН ПУ 2026 '!J27 -> 1124566.7 | K27: ='ПЛАН ПУ 2026 '!K27 -> 1124566.7 | L27: ='ПЛАН ПУ 2026 '!L27 -> 1124566.7 | M27: ='ПЛАН ПУ 2026 '!M27 -> 1124566.7 | N27: ='ПЛАН ПУ 2026 '!N27 -> 0 | O27: ='ПЛАН ПУ 2026 '!O27 -> 0 | P27: ='ПЛАН ПУ 2026 '!P27 -> 0 | ... T27: ='ПЛАН ПУ 2026 '!T27 -> 1124566.7
B28: =B27+1 -> 14 | C28: Прочие текущие затраты | H28: =I28+J28+K28+L28+M28+N28+O28+P28+Q28+R28+S28+T28 -> 15971789 | I28: ='ПЛАН ПУ 2026 '!I28 -> 1330982.4 | J28: ='ПЛАН ПУ 2026 '!J28 -> 1330982.4 | K28: ='ПЛАН ПУ 2026 '!K28 -> 1330982.4 | L28: ='ПЛАН ПУ 2026 '!L28 -> 1330982.4 | M28: ='ПЛАН ПУ 2026 '!M28 -> 1330982.4 | N28: ='ПЛАН ПУ 2026 '!N28 -> 1330982.4 | O28: ='ПЛАН ПУ 2026 '!O28 -> 1330982.4 | P28: ='ПЛАН ПУ 2026 '!P28 -> 1330982.4 | ... T28: ='ПЛАН ПУ 2026 '!T28 -> 1330982.4
B29: =B28+1 -> 15 | C29: Приобретение машин, оборудования, инструментов, производственного и хозяйственного инвентаря | H29: =I29+J29+K29+L29+M29+N29+O29+P29+Q29+R29+S29+T29 -> 130274348 | I29: ='ПЛАН ПУ 2026 '!I29 -> 32568587 | J29: ='ПЛАН ПУ 2026 '!J29 -> 32568587 | K29: ='ПЛАН ПУ 2026 '!K29 -> 32568587 | L29: ='ПЛАН ПУ 2026 '!L29 -> 32568587
B30: =B29+1 -> 16 | C30: Приобретение прочих основных средств (библиотечный фонд) | H30: =I30+J30+K30+L30+M30+N30+O30+P30+Q30+R30+S30+T30 -> 19986850 | Q30: ='ПЛАН ПУ 2026 '!Q30 -> 4996712.5 | R30: ='ПЛАН ПУ 2026 '!R30 -> 4996712.5 | S30: ='ПЛАН ПУ 2026 '!S30 -> 4996712.5 | T30: ='ПЛАН ПУ 2026 '!T30 -> 4996712.5
B31: =B30+1 -> 17 | C31: Дополнительные денежные выплаты за счет средств ФНАО РФМШ Астаны | H31: =I31+J31+K31+L31+M31+N31+O31+P31+Q31+R31+S31+T31 -> -1.4307986e+08 | I31: ='ПЛАН ПУ 2026 '!I31 -> 0 | J31: ='ПЛАН ПУ 2026 '!J31 -> 0 | K31: ='ПЛАН ПУ 2026 '!K31 -> -35769966 | L31: ='ПЛАН ПУ 2026 '!L31 -> 0 | M31: ='ПЛАН ПУ 2026 '!M31 -> 0 | N31: ='ПЛАН ПУ 2026 '!N31 -> -35769966 | O31: ='ПЛАН ПУ 2026 '!O31 -> 0 | P31: ='ПЛАН ПУ 2026 '!P31 -> 0 | ... T31: ='ПЛАН ПУ 2026 '!T31 -> -35769966
H32: =SUM(H15:H31) -> 705334945 | I32: =SUM(I15:I31) -> 68627043 | J32: =SUM(J15:J31) -> 64729111 | K32: =SUM(K15:K31) -> 1.2186448e+08 | L32: =SUM(L15:L31) -> 64263231 | M32: =SUM(M15:M31) -> 38788007 | N32: =SUM(N15:N31) -> 72718813 | O32: =SUM(O15:O31) -> 14448811 | ... T32: =SUM(T15:T31) -> 89754538
H34: =H16+H31 -> 2.1837776e+08 | K34: =K16+K31 -> 54594441 | N34: =N16+N31 -> 54594441 | Q34: =Q16+Q31 -> 54594441 | T34: =T16+T31 -> 54594441
C38: Директор филиала НАО «РФМШ» | L38: Меирбек Меирлан Едигерулы
C41: Экономист филиала НАО «РФМШ» | L41: Куюкова Гаухар Ермековна
